Workbook

Sheet PANEL COMPRAS
A1: PANEL DE COMPRAS -- MARINAFISK PESCADOS | N1: AUX PROVEEDORES (no borrar) | O1: -- TODOS LOS PROVEEDORES -- | S1: AUX PRODUCTOS (no borrar) | T1: -- TODOS LOS ARTICULOS -- | X1: AUX SELECTOR (no borrar)
N2: =PROVEEDORES!A3 -> 50001 | O2: =PROVEEDORES!B3 -> COPESA | P2: =IF(N2<>"",SUMIFS(COMPRAS!$J$3:$J$4997,COMPRAS!$D$3:$D$4997,N2,COMPRAS!$B$3:$B$4997,">="&IF($C$4="",DATE(1900,1,1),$C$4),COMPRAS!$B$3:$B$4997,"<="&IF($F$4="",DATE(2999,12,31),$F$4)),0) -> 18026.85 | Q2: =IF(N2<>"",SUMIFS(COMPRAS!$O$3:$O$4997,COMPRAS!$D$3:$D$4997,N2,COMPRAS!$B$3:$B$4997,">="&IF($C$4="",DATE(1900,1,1),$C$4),COMPRAS!$B$3:$B$4997,"<="&IF($F$4="",DATE(2999,12,31),$F$4)),0) -> 81085.323 | S2: =PRODUCTOS!A3 -> 0 | T2: =PRODUCTOS!B3 -> 0 | U2: =IF(S2<>"",SUMIFS(COMPRAS!$J$3:$J$4997,COMPRAS!$G$3:$G$4997,S2,COMPRAS!$B$3:$B$4997,">="&IF($C$4="",DATE(1900,1,1),$C$4),COMPRAS!$B$3:$B$4997,"<="&IF($F$4="",DATE(2999,12,31),$F$4)),0) -> 0 | V2: =IF(S2<>"",SUMIFS(COMPRAS!$O$3:$O$4997,COMPRAS!$G$3:$G$4997,S2,COMPRAS!$B$3:$B$4997,">="&IF($C$4="",DATE(1900,1,1),$C$4),COMPRAS!$B$3:$B$4997,"<="&IF($F$4="",DATE(2999,12,31),$F$4)),0) -> 0 | X2: =IF($B$45="-- TODOS LOS PROVEEDORES --","TODOS",IFERROR(INDEX($N$1:$N$206,MATCH($B$45,$O$1:$O$206,0)),"")) -> TODOS | Y2: =IF($X$2="TODOS",U2,IF(S2<>"",SUMIFS(COMPRAS!$J$3:$J$4997,COMPRAS!$G$3:$G$4997,S2,COMPRAS!$D$3:$D$4997,$X$2,COMPRAS!$B$3:$B$4997,">="&IF($C$4="",DATE(1900,1,1),$C$4),COMPRAS!$B$3:$B$4997,"<="&IF($F$4="",DATE(2999,12,31),$F$4)),0)) -> 0 | Z2: =IF($X$2="TODOS",V2,IF(S2<>"",SUMIFS(COMPRAS!$O$3:$O$4997,COMPRAS!$G$3:$G$4997,S2,COMPRAS!$D$3:$D$4997,$X$2,COMPRAS!$B$3:$B$4997,">="&IF($C$4="",DATE(1900,1,1),$C$4),COMPRAS!$B$3:$B$4997,"<="&IF($F$4="",DATE(2999,12,31),$F$4)),0)) -> 0
A3: Se actualiza solo con las compras registradas en la hoja COMPRAS -- no hay que tocar nada a mano. | N3: =PROVEEDORES!A4 -> 50010 | O3: =PROVEEDORES!B4 -> PERFECTO MONTERO | P3: =IF(N3<>"",SUMIFS(COMPRAS!$J$3:$J$4997,COMPRAS!$D$3:$D$4997,N3,COMPRAS!$B$3:$B$4997,">="&IF($C$4="",DATE(1900,1,1),$C$4),COMPRAS!$B$3:$B$4997,"<="&IF($F$4="",DATE(2999,12,31),$F$4)),0) -> 2834.25 | Q3: =IF(N3<>"",SUMIFS(COMPRAS!$O$3:$O$4997,COMPRAS!$D$3:$D$4997,N3,COMPRAS!$B$3:$B$4997,">="&IF($C$4="",DATE(1900,1,1),$C$4),COMPRAS!$B$3:$B$4997,"<="&IF($F$4="",DATE(2999,12,31),$F$4)),0) -> 15098.976 | S3: =PRODUCTOS!A4 -> 0 | T3: =PRODUCTOS!B4 -> 0 | U3: =IF(S3<>"",SUMIFS(COMPRAS!$J$3:$J$4997,COMPRAS!$G$3:$G$4997,S3,COMPRAS!$B$3:$B$4997,">="&IF($C$4="",DATE(1900,1,1),$C$4),COMPRAS!$B$3:$B$4997,"<="&IF($F$4="",DATE(2999,12,31),$F$4)),0) -> 0 | V3: =IF(S3<>"",SUMIFS(COMPRAS!$O$3:$O$4997,COMPRAS!$G$3:$G$4997,S3,COMPRAS!$B$3:$B$4997,">="&IF($C$4="",DATE(1900,1,1),$C$4),COMPRAS!$B$3:$B$4997,"<="&IF($F$4="",DATE(2999,12,31),$F$4)),0) -> 0 | X3: =IF(OR($B$46="",$B$46="-- TODOS LOS ARTICULOS --"),"*",IFERROR(INDEX($S$1:$S$231,MATCH($B$46,$T$1:$T$231,0)),"*")) -> * | Y3: =IF($X$2="TODOS",U3,IF(S3<>"",SUMIFS(COMPRAS!$J$3:$J$4997,COMPRAS!$G$3:$G$4997,S3,COMPRAS!$D$3:$D$4997,$X$2,COMPRAS!$B$3:$B$4997,">="&IF($C$4="",DATE(1900,1,1),$C$4),COMPRAS!$B$3:$B$4997,"<="&IF($F$4="",DATE(2999,12,31),$F$4)),0)) -> 0 | Z3: =IF($X$2="TODOS",V3,IF(S3<>"",SUMIFS(COMPRAS!$O$3:$O$4997,COMPRAS!$G$3:$G$4997,S3,COMPRAS!$D$3:$D$4997,$X$2,COMPRAS!$B$3:$B$4997,">="&IF($C$4="",DATE(1900,1,1),$C$4),COMPRAS!$B$3:$B$4997,"<="&IF($F$4="",DATE(2999,12,31),$F$4)),0)) -> 0
A4: Filtrar por fecha -- Desde: | E4: Hasta: | H4: (vacio = todas las fechas) | N4: =PROVEEDORES!A5 -> 50019 | O4: =PROVEEDORES!B5 -> ANGELITA VILLAR | P4: =IF(N4<>"",SUMIFS(COMPRAS!$J$3:$J$4997,COMPRAS!$D$3:$D$4997,N4,COMPRAS!$B$3:$B$4997,">="&IF($C$4="",DATE(1900,1,1),$C$4),COMPRAS!$B$3:$B$4997,"<="&IF($F$4="",DATE(2999,12,31),$F$4)),0) -> 205.1 | Q4: =IF(N4<>"",SUMIFS(COMPRAS!$O$3:$O$4997,COMPRAS!$D$3:$D$4997,N4,COMPRAS!$B$3:$B$4997,">="&IF($C$4="",DATE(1900,1,1),$C$4),COMPRAS!$B$3:$B$4997,"<="&IF($F$4="",DATE(2999,12,31),$F$4)),0) -> 1402.2348 | S4: =PRODUCTOS!A5 -> 0 | T4: =PRODUCTOS!B5 -> 0 | U4: =IF(S4<>"",SUMIFS(COMPRAS!$J$3:$J$4997,COMPRAS!$G$3:$G$4997,S4,COMPRAS!$B$3:$B$4997,">="&IF($C$4="",DATE(1900,1,1),$C$4),COMPRAS!$B$3:$B$4997,"<="&IF($F$4="",DATE(2999,12,31),$F$4)),0) -> 0 | V4: =IF(S4<>"",SUMIFS(COMPRAS!$O$3:$O$4997,COMPRAS!$G$3:$G$4997,S4,COMPRAS!$B$3:$B$4997,">="&IF($C$4="",DATE(1900,1,1),$C$4),COMPRAS!$B$3:$B$4997,"<="&IF($F$4="",DATE(2999,12,31),$F$4)),0) -> 0 | Y4: =IF($X$2="TODOS",U4,IF(S4<>"",SUMIFS(COMPRAS!$J$3:$J$4997,COMPRAS!$G$3:$G$4997,S4,COMPRAS!$D$3:$D$4997,$X$2,COMPRAS!$B$3:$B$4997,">="&IF($C$4="",DATE(1900,1,1),$C$4),COMPRAS!$B$3:$B$4997,"<="&IF($F$4="",DATE(2999,12,31),$F$4)),0)) -> 0 | Z4: =IF($X$2="TODOS",V4,IF(S4<>"",SUMIFS(COMPRAS!$O$3:$O$4997,COMPRAS!$G$3:$G$4997,S4,COMPRAS!$D$3:$D$4997,$X$2,COMPRAS!$B$3:$B$4997,">="&IF($C$4="",DATE(1900,1,1),$C$4),COMPRAS!$B$3:$B$4997,"<="&IF($F$4="",DATE(2999,12,31),$F$4)),0)) -> 0
A5: TOP 15 PROVEEDORES -- MAS KILOS COMPRADOS | E5: TOP 15 PROVEEDORES -- MAS IMPORTE COMPRADO | N5: =PROVEEDORES!A6 -> 50020 | O5: =PROVEEDORES!B6 -> PACO MOINELO | P5: =IF(N5<>"",SUMIFS(COMPRAS!$J$3:$J$4997,COMPRAS!$D$3:$D$4997,N5,COMPRAS!$B$3:$B$4997,">="&IF($C$4="",DATE(1900,1,1),$C$4),COMPRAS!$B$3:$B$4997,"<="&IF($F$4="",DATE(2999,12,31),$F$4)),0) -> 1761.55 | Q5: =IF(N5<>"",SUMIFS(COMPRAS!$O$3:$O$4997,COMPRAS!$D$3:$D$4997,N5,COMPRAS!$B$3:$B$4997,">="&IF($C$4="",DATE(1900,1,1),$C$4),COMPRAS!$B$3:$B$4997,"<="&IF($F$4="",DATE(2999,12,31),$F$4)),0) -> 10973.989 | S5: =PRODUCTOS!A6 -> 0 | T5: =PRODUCTOS!B6 -> 0 | U5: =IF(S5<>"",SUMIFS(COMPRAS!$J$3:$J$4997,COMPRAS!$G$3:$G$4997,S5,COMPRAS!$B$3:$B$4997,">="&IF($C$4="",DATE(1900,1,1),$C$4),COMPRAS!$B$3:$B$4997,"<="&IF($F$4="",DATE(2999,12,31),$F$4)),0) -> 0 | V5: =IF(S5<>"",SUMIFS(COMPRAS!$O$3:$O$4997,COMPRAS!$G$3:$G$4997,S5,COMPRAS!$B$3:$B$4997,">="&IF($C$4="",DATE(1900,1,1),$C$4),COMPRAS!$B$3:$B$4997,"<="&IF($F$4="",DATE(2999,12,31),$F$4)),0) -> 0 | Y5: =IF($X$2="TODOS",U5,IF(S5<>"",SUMIFS(COMPRAS!$J$3:$J$4997,COMPRAS!$G$3:$G$4997,S5,COMPRAS!$D$3:$D$4997,$X$2,COMPRAS!$B$3:$B$4997,">="&IF($C$4="",DATE(1900,1,1),$C$4),COMPRAS!$B$3:$B$4997,"<="&IF($F$4="",DATE(2999,12,31),$F$4)),0)) -> 0 | Z5: =IF($X$2="TODOS",V5,IF(S5<>"",SUMIFS(COMPRAS!$O$3:$O$4997,COMPRAS!$G$3:$G$4997,S5,COMPRAS!$D$3:$D$4997,$X$2,COMPRAS!$B$3:$B$4997,">="&IF($C$4="",DATE(1900,1,1),$C$4),COMPRAS!$B$3:$B$4997,"<="&IF($F$4="",DATE(2999,12,31),$F$4)),0)) -> 0
A6: # | B6: Proveedor | C6: Kilos | E6: # | F6: Proveedor | G6: Importe | N6: =PROVEEDORES!A7 -> 50034 | O6: =PROVEEDORES!B7 -> MANUEL CEBREIRA MELLA | P6: =IF(N6<>"",SUMIFS(COMPRAS!$J$3:$J$4997,COMPRAS!$D$3:$D$4997,N6,COMPRAS!$B$3:$B$4997,">="&IF($C$4="",DATE(1900,1,1),$C$4),COMPRAS!$B$3:$B$4997,"<="&IF($F$4="",DATE(2999,12,31),$F$4)),0) -> 0 | Q6: =IF(N6<>"",SUMIFS(COMPRAS!$O$3:$O$4997,COMPRAS!$D$3:$D$4997,N6,COMPRAS!$B$3:$B$4997,">="&IF($C$4="",DATE(1900,1,1),$C$4),COMPRAS!$B$3:$B$4997,"<="&IF($F$4="",DATE(2999,12,31),$F$4)),0) -> 0 | S6: =PRODUCTOS!A7 -> 0 | T6: =PRODUCTOS!B7 -> 0 | U6: =IF(S6<>"",SUMIFS(COMPRAS!$J$3:$J$4997,COMPRAS!$G$3:$G$4997,S6,COMPRAS!$B$3:$B$4997,">="&IF($C$4="",DATE(1900,1,1),$C$4),COMPRAS!$B$3:$B$4997,"<="&IF($F$4="",DATE(2999,12,31),$F$4)),0) -> 0 | V6: =IF(S6<>"",SUMIFS(COMPRAS!$O$3:$O$4997,COMPRAS!$G$3:$G$4997,S6,COMPRAS!$B$3:$B$4997,">="&IF($C$4="",DATE(1900,1,1),$C$4),COMPRAS!$B$3:$B$4997,"<="&IF($F$4="",DATE(2999,12,31),$F$4)),0) -> 0 | Y6: =IF($X$2="TODOS",U6,IF(S6<>"",SUMIFS(COMPRAS!$J$3:$J$4997,COMPRAS!$G$3:$G$4997,S6,COMPRAS!$D$3:$D$4997,$X$2,COMPRAS!$B$3:$B$4997,">="&IF($C$4="",DATE(1900,1,1),$C$4),COMPRAS!$B$3:$B$4997,"<="&IF($F$4="",DATE(2999,12,31),$F$4)),0)) -> 0 | Z6: =IF($X$2="TODOS",V6,IF(S6<>"",SUMIFS(COMPRAS!$O$3:$O$4997,COMPRAS!$G$3:$G$4997,S6,COMPRAS!$D$3:$D$4997,$X$2,COMPRAS!$B$3:$B$4997,">="&IF($C$4="",DATE(1900,1,1),$C$4),COMPRAS!$B$3:$B$4997,"<="&IF($F$4="",DATE(2999,12,31),$F$4)),0)) -> 0
A7: 1 | B7: =IFERROR(INDEX($O$2:$O$206,MATCH(LARGE($P$2:$P$206,1),$P$2:$P$206,0)),"") -> XESTION NOVA LONXA RIVEIRA S.L. | C7: =IFERROR(LARGE($P$2:$P$206,1),0) -> 41663.771 | E7: 1 | F7: =IFERROR(INDEX($O$2:$O$206,MATCH(LARGE($Q$2:$Q$206,1),$Q$2:$Q$206,0)),"") -> XESTION NOVA LONXA RIVEIRA S.L. | G7: =IFERROR(LARGE($Q$2:$Q$206,1),0) -> 101872.87 | N7: =PROVEEDORES!A8 -> 50035 | O7: =PROVEEDORES!B8 -> SCANFISK SEAFFOD S,L | P7: =IF(N7<>"",SUMIFS(COMPRAS!$J$3:$J$4997,COMPRAS!$D$3:$D$4997,N7,COMPRAS!$B$3:$B$4997,">="&IF($C$4="",DATE(1900,1,1),$C$4),COMPRAS!$B$3:$B$4997,"<="&IF($F$4="",DATE(2999,12,31),$F$4)),0) -> 4941.7 | Q7: =IF(N7<>"",SUMIFS(COMPRAS!$O$3:$O$4997,COMPRAS!$D$3:$D$4997,N7,COMPRAS!$B$3:$B$4997,">="&IF($C$4="",DATE(1900,1,1),$C$4),COMPRAS!$B$3:$B$4997,"<="&IF($F$4="",DATE(2999,12,31),$F$4)),0) -> 35388.74 | S7: =PRODUCTOS!A8 -> 0 | T7: =PRODUCTOS!B8 -> 0 | U7: =IF(S7<>"",SUMIFS(COMPRAS!$J$3:$J$4997,COMPRAS!$G$3:$G$4997,S7,COMPRAS!$B$3:$B$4997,">="&IF($C$4="",DATE(1900,1,1),$C$4),COMPRAS!$B$3:$B$4997,"<="&IF($F$4="",DATE(2999,12,31),$F$4)),0) -> 0 | V7: =IF(S7<>"",SUMIFS(COMPRAS!$O$3:$O$4997,COMPRAS!$G$3:$G$4997,S7,COMPRAS!$B$3:$B$4997,">="&IF($C$4="",DATE(1900,1,1),$C$4),COMPRAS!$B$3:$B$4997,"<="&IF($F$4="",DATE(2999,12,31),$F$4)),0) -> 0 | Y7: =IF($X$2="TODOS",U7,IF(S7<>"",SUMIFS(COMPRAS!$J$3:$J$4997,COMPRAS!$G$3:$G$4997,S7,COMPRAS!$D$3:$D$4997,$X$2,COMPRAS!$B$3:$B$4997,">="&IF($C$4="",DATE(1900,1,1),$C$4),COMPRAS!$B$3:$B$4997,"<="&IF($F$4="",DATE(2999,12,31),$F$4)),0)) -> 0 | Z7: =IF($X$2="TODOS",V7,IF(S7<>"",SUMIFS(COMPRAS!$O$3:$O$4997,COMPRAS!$G$3:$G$4997,S7,COMPRAS!$D$3:$D$4997,$X$2,COMPRAS!$B$3:$B$4997,">="&IF($C$4="",DATE(1900,1,1),$C$4),COMPRAS!$B$3:$B$4997,"<="&IF($F$4="",DATE(2999,12,31),$F$4)),0)) -> 0
A8: 2 | B8: =IFERROR(INDEX($O$2:$O$206,MATCH(LARGE($P$2:$P$206,2),$P$2:$P$206,0)),"") -> SUBASTAS CORUÑA S.L. | C8: =IFERROR(LARGE($P$2:$P$206,2),0) -> 18832.8 | E8: 2 | F8: =IFERROR(INDEX($O$2:$O$206,MATCH(LARGE($Q$2:$Q$206,2),$Q$2:$Q$206,0)),"") -> COPESA | G8: =IFERROR(LARGE($Q$2:$Q$206,2),0) -> 81085.323 | N8: =PROVEEDORES!A9 -> 50048 | O8: =PROVEEDORES!B9 -> JOSE LUIS CORREA KESSLER S.L. | P8: =IF(N8<>"",SUMIFS(COMPRAS!$J$3:$J$4997,COMPRAS!$D$3:$D$4997,N8,COMPRAS!$B$3:$B$4997,">="&IF($C$4="",DATE(1900,1,1),$C$4),COMPRAS!$B$3:$B$4997,"<="&IF($F$4="",DATE(2999,12,31),$F$4)),0) -> 15321 | Q8: =IF(N8<>"",SUMIFS(COMPRAS!$O$3:$O$4997,COMPRAS!$D$3:$D$4997,N8,COMPRAS!$B$3:$B$4997,">="&IF($C$4="",DATE(1900,1,1),$C$4),COMPRAS!$B$3:$B$4997,"<="&IF($F$4="",DATE(2999,12,31),$F$4)),0) -> 31840.2 | S8: =PRODUCTOS!A9 -> 0 | T8: =PRODUCTOS!B9 -> 0 | U8: =IF(S8<>"",SUMIFS(COMPRAS!$J$3:$J$4997,COMPRAS!$G$3:$G$4997,S8,COMPRAS!$B$3:$B$4997,">="&IF($C$4="",DATE(1900,1,1),$C$4),COMPRAS!$B$3:$B$4997,"<="&IF($F$4="",DATE(2999,12,31),$F$4)),0) -> 0 | V8: =IF(S8<>"",SUMIFS(COMPRAS!$O$3:$O$4997,COMPRAS!$G$3:$G$4997,S8,COMPRAS!$B$3:$B$4997,">="&IF($C$4="",DATE(1900,1,1),$C$4),COMPRAS!$B$3:$B$4997,"<="&IF($F$4="",DATE(2999,12,31),$F$4)),0) -> 0 | Y8: =IF($X$2="TODOS",U8,IF(S8<>"",SUMIFS(COMPRAS!$J$3:$J$4997,COMPRAS!$G$3:$G$4997,S8,COMPRAS!$D$3:$D$4997,$X$2,COMPRAS!$B$3:$B$4997,">="&IF($C$4="",DATE(1900,1,1),$C$4),COMPRAS!$B$3:$B$4997,"<="&IF($F$4="",DATE(2999,12,31),$F$4)),0)) -> 0 | Z8: =IF($X$2="TODOS",V8,IF(S8<>"",SUMIFS(COMPRAS!$O$3:$O$4997,COMPRAS!$G$3:$G$4997,S8,COMPRAS!$D$3:$D$4997,$X$2,COMPRAS!$B$3:$B$4997,">="&IF($C$4="",DATE(1900,1,1),$C$4),COMPRAS!$B$3:$B$4997,"<="&IF($F$4="",DATE(2999,12,31),$F$4)),0)) -> 0
A9: 3 | B9: =IFERROR(INDEX($O$2:$O$206,MATCH(LARGE($P$2:$P$206,3),$P$2:$P$206,0)),"") -> COPESA | C9: =IFERROR(LARGE($P$2:$P$206,3),0) -> 18026.85 | E9: 3 | F9: =IFERROR(INDEX($O$2:$O$206,MATCH(LARGE($Q$2:$Q$206,3),$Q$2:$Q$206,0)),"") -> SUBASTAS RIVERA S.L. | G9: =IFERROR(LARGE($Q$2:$Q$206,3),0) -> 43626.4 | N9: =PROVEEDORES!A10 -> 50056 | O9: =PROVEEDORES!B10 -> COTON Y SANCHEZ S.L. | P9: =IF(N9<>"",SUMIFS(COMPRAS!$J$3:$J$4997,COMPRAS!$D$3:$D$4997,N9,COMPRAS!$B$3:$B$4997,">="&IF($C$4="",DATE(1900,1,1),$C$4),COMPRAS!$B$3:$B$4997,"<="&IF($F$4="",DATE(2999,12,31),$F$4)),0) -> 36 | Q9: =IF(N9<>"",SUMIFS(COMPRAS!$O$3:$O$4997,COMPRAS!$D$3:$D$4997,N9,COMPRAS!$B$3:$B$4997,">="&IF($C$4="",DATE(1900,1,1),$C$4),COMPRAS!$B$3:$B$4997,"<="&IF($F$4="",DATE(2999,12,31),$F$4)),0) -> 100.8 | S9: =PRODUCTOS!A10 -> 0 | T9: =PRODUCTOS!B10 -> 0 | U9: =IF(S9<>"",SUMIFS(COMPRAS!$J$3:$J$4997,COMPRAS!$G$3:$G$4997,S9,COMPRAS!$B$3:$B$4997,">="&IF($C$4="",DATE(1900,1,1),$C$4),COMPRAS!$B$3:$B$4997,"<="&IF($F$4="",DATE(2999,12,31),$F$4)),0) -> 0 | V9: =IF(S9<>"",SUMIFS(COMPRAS!$O$3:$O$4997,COMPRAS!$G$3:$G$4997,S9,COMPRAS!$B$3:$B$4997,">="&IF($C$4="",DATE(1900,1,1),$C$4),COMPRAS!$B$3:$B$4997,"<="&IF($F$4="",DATE(2999,12,31),$F$4)),0) -> 0 | Y9: =IF($X$2="TODOS",U9,IF(S9<>"",SUMIFS(COMPRAS!$J$3:$J$4997,COMPRAS!$G$3:$G$4997,S9,COMPRAS!$D$3:$D$4997,$X$2,COMPRAS!$B$3:$B$4997,">="&IF($C$4="",DATE(1900,1,1),$C$4),COMPRAS!$B$3:$B$4997,"<="&IF($F$4="",DATE(2999,12,31),$F$4)),0)) -> 0 | Z9: =IF($X$2="TODOS",V9,IF(S9<>"",SUMIFS(COMPRAS!$O$3:$O$4997,COMPRAS!$G$3:$G$4997,S9,COMPRAS!$D$3:$D$4997,$X$2,COMPRAS!$B$3:$B$4997,">="&IF($C$4="",DATE(1900,1,1),$C$4),COMPRAS!$B$3:$B$4997,"<="&IF($F$4="",DATE(2999,12,31),$F$4)),0)) -> 0
A10: 4 | B10: =IFERROR(INDEX($O$2:$O$206,MATCH(LARGE($P$2:$P$206,4),$P$2:$P$206,0)),"") -> JOSE LUIS CORREA KESSLER S.L. | C10: =IFERROR(LARGE($P$2:$P$206,4),0) -> 15321 | E10: 4 | F10: =IFERROR(INDEX($O$2:$O$206,MATCH(LARGE($Q$2:$Q$206,4),$Q$2:$Q$206,0)),"") -> SCANFISK SEAFFOD S,L | G10: =IFERROR(LARGE($Q$2:$Q$206,4),0) -> 35388.74 | N10: =PROVEEDORES!A11 -> 50064 | O10: =PROVEEDORES!B11 -> PESCADOS CORCUBION | P10: =IF(N10<>"",SUMIFS(COMPRAS!$J$3:$J$4997,COMPRAS!$D$3:$D$4997,N10,COMPRAS!$B$3:$B$4997,">="&IF($C$4="",DATE(1900,1,1),$C$4),COMPRAS!$B$3:$B$4997,"<="&IF($F$4="",DATE(2999,12,31),$F$4)),0) -> 0 | Q10: =IF(N10<>"",SUMIFS(COMPRAS!$O$3:$O$4997,COMPRAS!$D$3:$D$4997,N10,COMPRAS!$B$3:$B$4997,">="&IF($C$4="",DATE(1900,1,1),$C$4),COMPRAS!$B$3:$B$4997,"<="&IF($F$4="",DATE(2999,12,31),$F$4)),0) -> 0 | S10: =PRODUCTOS!A11 -> 0 | T10: =PRODUCTOS!B11 -> 0 | U10: =IF(S10<>"",SUMIFS(COMPRAS!$J$3:$J$4997,COMPRAS!$G$3:$G$4997,S10,COMPRAS!$B$3:$B$4997,">="&IF($C$4="",DATE(1900,1,1),$C$4),COMPRAS!$B$3:$B$4997,"<="&IF($F$4="",DATE(2999,12,31),$F$4)),0) -> 0 | V10: =IF(S10<>"",SUMIFS(COMPRAS!$O$3:$O$4997,COMPRAS!$G$3:$G$4997,S10,COMPRAS!$B$3:$B$4997,">="&IF($C$4="",DATE(1900,1,1),$C$4),COMPRAS!$B$3:$B$4997,"<="&IF($F$4="",DATE(2999,12,31),$F$4)),0) -> 0 | Y10: =IF($X$2="TODOS",U10,IF(S10<>"",SUMIFS(COMPRAS!$J$3:$J$4997,COMPRAS!$G$3:$G$4997,S10,COMPRAS!$D$3:$D$4997,$X$2,COMPRAS!$B$3:$B$4997,">="&IF($C$4="",DATE(1900,1,1),$C$4),COMPRAS!$B$3:$B$4997,"<="&IF($F$4="",DATE(2999,12,31),$F$4)),0)) -> 0 | Z10: =IF($X$2="TODOS",V10,IF(S10<>"",SUMIFS(COMPRAS!$O$3:$O$4997,COMPRAS!$G$3:$G$4997,S10,COMPRAS!$D$3:$D$4997,$X$2,COMPRAS!$B$3:$B$4997,">="&IF($C$4="",DATE(1900,1,1),$C$4),COMPRAS!$B$3:$B$4997,"<="&IF($F$4="",DATE(2999,12,31),$F$4)),0)) -> 0
A11: 5 | B11: =IFERROR(INDEX($O$2:$O$206,MATCH(LARGE($P$2:$P$206,5),$P$2:$P$206,0)),"") -> ACERGA | C11: =IFERROR(LARGE($P$2:$P$206,5),0) -> 13166 | E11: 5 | F11: =IFERROR(INDEX($O$2:$O$206,MATCH(LARGE($Q$2:$Q$206,5),$Q$2:$Q$206,0)),"") -> SUBASTAS CORUÑA S.L. | G11: =IFERROR(LARGE($Q$2:$Q$206,5),0) -> 35085.682 | N11: =PROVEEDORES!A12 -> 50069 | O11: =PROVEEDORES!B12 -> PESCADOS ILLANES S.L. | P11: =IF(N11<>"",SUMIFS(COMPRAS!$J$3:$J$4997,COMPRAS!$D$3:$D$4997,N11,COMPRAS!$B$3:$B$4997,">="&IF($C$4="",DATE(1900,1,1),$C$4),COMPRAS!$B$3:$B$4997,"<="&IF($F$4="",DATE(2999,12,31),$F$4)),0) -> 1083.6 | Q11: =IF(N11<>"",SUMIFS(COMPRAS!$O$3:$O$4997,COMPRAS!$D$3:$D$4997,N11,COMPRAS!$B$3:$B$4997,">="&IF($C$4="",DATE(1900,1,1),$C$4),COMPRAS!$B$3:$B$4997,"<="&IF($F$4="",DATE(2999,12,31),$F$4)),0) -> 4802.8434 | S11: =PRODUCTOS!A12 -> C650 | T11: =PRODUCTOS!B12 -> ABADEJO RIA (POL) | U11: =IF(S11<>"",SUMIFS(COMPRAS!$J$3:$J$4997,COMPRAS!$G$3:$G$4997,S11,COMPRAS!$B$3:$B$4997,">="&IF($C$4="",DATE(1900,1,1),$C$4),COMPRAS!$B$3:$B$4997,"<="&IF($F$4="",DATE(2999,12,31),$F$4)),0) -> 0 | V11: =IF(S11<>"",SUMIFS(COMPRAS!$O$3:$O$4997,COMPRAS!$G$3:$G$4997,S11,COMPRAS!$B$3:$B$4997,">="&IF($C$4="",DATE(1900,1,1),$C$4),COMPRAS!$B$3:$B$4997,"<="&IF($F$4="",DATE(2999,12,31),$F$4)),0) -> 0 | Y11: =IF($X$2="TODOS",U11,IF(S11<>"",SUMIFS(COMPRAS!$J$3:$J$4997,COMPRAS!$G$3:$G$4997,S11,COMPRAS!$D$3:$D$4997,$X$2,COMPRAS!$B$3:$B$4997,">="&IF($C$4="",DATE(1900,1,1),$C$4),COMPRAS!$B$3:$B$4997,"<="&IF($F$4="",DATE(2999,12,31),$F$4)),0)) -> 0 | Z11: =IF($X$2="TODOS",V11,IF(S11<>"",SUMIFS(COMPRAS!$O$3:$O$4997,COMPRAS!$G$3:$G$4997,S11,COMPRAS!$D$3:$D$4997,$X$2,COMPRAS!$B$3:$B$4997,">="&IF($C$4="",DATE(1900,1,1),$C$4),COMPRAS!$B$3:$B$4997,"<="&IF($F$4="",DATE(2999,12,31),$F$4)),0)) -> 0
A12: 6 | B12: =IFERROR(INDEX($O$2:$O$206,MATCH(LARGE($P$2:$P$206,6),$P$2:$P$206,0)),"") -> SUBASTAS DE ATLANTICO S.L | C12: =IFERROR(LARGE($P$2:$P$206,6),0) -> 9861.3 | E12: 6 | F12: =IFERROR(INDEX($O$2:$O$206,MATCH(LARGE($Q$2:$Q$206,6),$Q$2:$Q$206,0)),"") -> JOSE LUIS CORREA KESSLER S.L. | G12: =IFERROR(LARGE($Q$2:$Q$206,6),0) -> 31840.2 | N12: =PROVEEDORES!A13 -> 50106 | O12: =PROVEEDORES!B13 -> SONIA VENTAS S.L | P12: =IF(N12<>"",SUMIFS(COMPRAS!$J$3:$J$4997,COMPRAS!$D$3:$D$4997,N12,COMPRAS!$B$3:$B$4997,">="&IF($C$4="",DATE(1900,1,1),$C$4),COMPRAS!$B$3:$B$4997,"<="&IF($F$4="",DATE(2999,12,31),$F$4)),0) -> 4675.7 | Q12: =IF(N12<>"",SUMIFS(COMPRAS!$O$3:$O$4997,COMPRAS!$D$3:$D$4997,N12,COMPRAS!$B$3:$B$4997,">="&IF($C$4="",DATE(1900,1,1),$C$4),COMPRAS!$B$3:$B$4997,"<="&IF($F$4="",DATE(2999,12,31),$F$4)),0) -> 29402.495 | S12: =PRODUCTOS!A13 -> C620 | T12: =PRODUCTOS!B13 -> ACEDIA (CET) | U12: =IF(S12<>"",SUMIFS(COMPRAS!$J$3:$J$4997,COMPRAS!$G$3:$G$4997,S12,COMPRAS!$B$3:$B$4997,">="&IF($C$4="",DATE(1900,1,1),$C$4),COMPRAS!$B$3:$B$4997,"<="&IF($F$4="",DATE(2999,12,31),$F$4)),0) -> 0 | V12: =IF(S12<>"",SUMIFS(COMPRAS!$O$3:$O$4997,COMPRAS!$G$3:$G$4997,S12,COMPRAS!$B$3:$B$4997,">="&IF($C$4="",DATE(1900,1,1),$C$4),COMPRAS!$B$3:$B$4997,"<="&IF($F$4="",DATE(2999,12,31),$F$4)),0) -> 0 | Y12: =IF($X$2="TODOS",U12,IF(S12<>"",SUMIFS(COMPRAS!$J$3:$J$4997,COMPRAS!$G$3:$G$4997,S12,COMPRAS!$D$3:$D$4997,$X$2,COMPRAS!$B$3:$B$4997,">="&IF($C$4="",DATE(1900,1,1),$C$4),COMPRAS!$B$3:$B$4997,"<="&IF($F$4="",DATE(2999,12,31),$F$4)),0)) -> 0 | Z12: =IF($X$2="TODOS",V12,IF(S12<>"",SUMIFS(COMPRAS!$O$3:$O$4997,COMPRAS!$G$3:$G$4997,S12,COMPRAS!$D$3:$D$4997,$X$2,COMPRAS!$B$3:$B$4997,">="&IF($C$4="",DATE(1900,1,1),$C$4),COMPRAS!$B$3:$B$4997,"<="&IF($F$4="",DATE(2999,12,31),$F$4)),0)) -> 0
A13: 7 | B13: =IFERROR(INDEX($O$2:$O$206,MATCH(LARGE($P$2:$P$206,7),$P$2:$P$206,0)),"") -> SUBASTAS RIVERA S.L. | C13: =IFERROR(LARGE($P$2:$P$206,7),0) -> 9601.75 | E13: 7 | F13: =IFERROR(INDEX($O$2:$O$206,MATCH(LARGE($Q$2:$Q$206,7),$Q$2:$Q$206,0)),"") -> SONIA VENTAS S.L | G13: =IFERROR(LARGE($Q$2:$Q$206,7),0) -> 29402.495 | N13: =PROVEEDORES!A14 -> 50146 | O13: =PROVEEDORES!B14 -> MAR BERMEO S.L. | P13: =IF(N13<>"",SUMIFS(COMPRAS!$J$3:$J$4997,COMPRAS!$D$3:$D$4997,N13,COMPRAS!$B$3:$B$4997,">="&IF($C$4="",DATE(1900,1,1),$C$4),COMPRAS!$B$3:$B$4997,"<="&IF($F$4="",DATE(2999,12,31),$F$4)),0) -> 803.65 | Q13: =IF(N13<>"",SUMIFS(COMPRAS!$O$3:$O$4997,COMPRAS!$D$3:$D$4997,N13,COMPRAS!$B$3:$B$4997,">="&IF($C$4="",DATE(1900,1,1),$C$4),COMPRAS!$B$3:$B$4997,"<="&IF($F$4="",DATE(2999,12,31),$F$4)),0) -> 1788.1212 | S13: =PRODUCTOS!A14 -> C2555 | T13: =PRODUCTOS!B14 -> ALFONDIGA/RUBIO/ESCACHO (GUU) | U13: =IF(S13<>"",SUMIFS(COMPRAS!$J$3:$J$4997,COMPRAS!$G$3:$G$4997,S13,COMPRAS!$B$3:$B$4997,">="&IF($C$4="",DATE(1900,1,1),$C$4),COMPRAS!$B$3:$B$4997,"<="&IF($F$4="",DATE(2999,12,31),$F$4)),0) -> 26.95 | V13: =IF(S13<>"",SUMIFS(COMPRAS!$O$3:$O$4997,COMPRAS!$G$3:$G$4997,S13,COMPRAS!$B$3:$B$4997,">="&IF($C$4="",DATE(1900,1,1),$C$4),COMPRAS!$B$3:$B$4997,"<="&IF($F$4="",DATE(2999,12,31),$F$4)),0) -> 40.6215 | Y13: =IF($X$2="TODOS",U13,IF(S13<>"",SUMIFS(COMPRAS!$J$3:$J$4997,COMPRAS!$G$3:$G$4997,S13,COMPRAS!$D$3:$D$4997,$X$2,COMPRAS!$B$3:$B$4997,">="&IF($C$4="",DATE(1900,1,1),$C$4),COMPRAS!$B$3:$B$4997,"<="&IF($F$4="",DATE(2999,12,31),$F$4)),0)) -> 26.95 | Z13: =IF($X$2="TODOS",V13,IF(S13<>"",SUMIFS(COMPRAS!$O$3:$O$4997,COMPRAS!$G$3:$G$4997,S13,COMPRAS!$D$3:$D$4997,$X$2,COMPRAS!$B$3:$B$4997,">="&IF($C$4="",DATE(1900,1,1),$C$4),COMPRAS!$B$3:$B$4997,"<="&IF($F$4="",DATE(2999,12,31),$F$4)),0)) -> 40.6215
A14: 8 | B14: =IFERROR(INDEX($O$2:$O$206,MATCH(LARGE($P$2:$P$206,8),$P$2:$P$206,0)),"") -> SCANFISK SEAFFOD S,L | C14: =IFERROR(LARGE($P$2:$P$206,8),0) -> 4941.7 | E14: 8 | F14: =IFERROR(INDEX($O$2:$O$206,MATCH(LARGE($Q$2:$Q$206,8),$Q$2:$Q$206,0)),"") -> SUBASTAS DE ATLANTICO S.L | G14: =IFERROR(LARGE($Q$2:$Q$206,8),0) -> 24987.662 | N14: =PROVEEDORES!A15 -> 50152 | O14: =PROVEEDORES!B15 -> DOMAR CORUÑA S.L | P14: =IF(N14<>"",SUMIFS(COMPRAS!$J$3:$J$4997,COMPRAS!$D$3:$D$4997,N14,COMPRAS!$B$3:$B$4997,">="&IF($C$4="",DATE(1900,1,1),$C$4),COMPRAS!$B$3:$B$4997,"<="&IF($F$4="",DATE(2999,12,31),$F$4)),0) -> 68 | Q14: =IF(N14<>"",SUMIFS(COMPRAS!$O$3:$O$4997,COMPRAS!$D$3:$D$4997,N14,COMPRAS!$B$3:$B$4997,">="&IF($C$4="",DATE(1900,1,1),$C$4),COMPRAS!$B$3:$B$4997,"<="&IF($F$4="",DATE(2999,12,31),$F$4)),0) -> 1200 | S14: =PRODUCTOS!A15 -> C3972 | T14: =PRODUCTOS!B15 -> ATUN PATUDO (BET) | U14: =IF(S14<>"",SUMIFS(COMPRAS!$J$3:$J$4997,COMPRAS!$G$3:$G$4997,S14,COMPRAS!$B$3:$B$4997,">="&IF($C$4="",DATE(1900,1,1),$C$4),COMPRAS!$B$3:$B$4997,"<="&IF($F$4="",DATE(2999,12,31),$F$4)),0) -> 0 | V14: =IF(S14<>"",SUMIFS(COMPRAS!$O$3:$O$4997,COMPRAS!$G$3:$G$4997,S14,COMPRAS!$B$3:$B$4997,">="&IF($C$4="",DATE(1900,1,1),$C$4),COMPRAS!$B$3:$B$4997,"<="&IF($F$4="",DATE(2999,12,31),$F$4)),0) -> 0 | Y14: =IF($X$2="TODOS",U14,IF(S14<>"",SUMIFS(COMPRAS!$J$3:$J$4997,COMPRAS!$G$3:$G$4997,S14,COMPRAS!$D$3:$D$4997,$X$2,COMPRAS!$B$3:$B$4997,">="&IF($C$4="",DATE(1900,1,1),$C$4),COMPRAS!$B$3:$B$4997,"<="&IF($F$4="",DATE(2999,12,31),$F$4)),0)) -> 0 | Z14: =IF($X$2="TODOS",V14,IF(S14<>"",SUMIFS(COMPRAS!$O$3:$O$4997,COMPRAS!$G$3:$G$4997,S14,COMPRAS!$D$3:$D$4997,$X$2,COMPRAS!$B$3:$B$4997,">="&IF($C$4="",DATE(1900,1,1),$C$4),COMPRAS!$B$3:$B$4997,"<="&IF($F$4="",DATE(2999,12,31),$F$4)),0)) -> 0
A15: 9 | B15: =IFERROR(INDEX($O$2:$O$206,MATCH(LARGE($P$2:$P$206,9),$P$2:$P$206,0)),"") -> SONIA VENTAS S.L | C15: =IFERROR(LARGE($P$2:$P$206,9),0) -> 4675.7 | E15: 9 | F15: =IFERROR(INDEX($O$2:$O$206,MATCH(LARGE($Q$2:$Q$206,9),$Q$2:$Q$206,0)),"") -> ACERGA | G15: =IFERROR(LARGE($Q$2:$Q$206,9),0) -> 20065.787 | N15: =PROVEEDORES!A16 -> 50158 | O15: =PROVEEDORES!B16 -> FORO-MAREE | P15: =IF(N15<>"",SUMIFS(COMPRAS!$J$3:$J$4997,COMPRAS!$D$3:$D$4997,N15,COMPRAS!$B$3:$B$4997,">="&IF($C$4="",DATE(1900,1,1),$C$4),COMPRAS!$B$3:$B$4997,"<="&IF($F$4="",DATE(2999,12,31),$F$4)),0) -> 0 | Q15: =IF(N15<>"",SUMIFS(COMPRAS!$O$3:$O$4997,COMPRAS!$D$3:$D$4997,N15,COMPRAS!$B$3:$B$4997,">="&IF($C$4="",DATE(1900,1,1),$C$4),COMPRAS!$B$3:$B$4997,"<="&IF($F$4="",DATE(2999,12,31),$F$4)),0) -> 0 | S15: =PRODUCTOS!A16 -> C8020 | T15: =PRODUCTOS!B16 -> FILETE DE BACALO (COD) | U15: =IF(S15<>"",SUMIFS(COMPRAS!$J$3:$J$4997,COMPRAS!$G$3:$G$4997,S15,COMPRAS!$B$3:$B$4997,">="&IF($C$4="",DATE(1900,1,1),$C$4),COMPRAS!$B$3:$B$4997,"<="&IF($F$4="",DATE(2999,12,31),$F$4)),0) -> 0 | V15: =IF(S15<>"",SUMIFS(COMPRAS!$O$3:$O$4997,COMPRAS!$G$3:$G$4997,S15,COMPRAS!$B$3:$B$4997,">="&IF($C$4="",DATE(1900,1,1),$C$4),COMPRAS!$B$3:$B$4997,"<="&IF($F$4="",DATE(2999,12,31),$F$4)),0) -> 0 | Y15: =IF($X$2="TODOS",U15,IF(S15<>"",SUMIFS(COMPRAS!$J$3:$J$4997,COMPRAS!$G$3:$G$4997,S15,COMPRAS!$D$3:$D$4997,$X$2,COMPRAS!$B$3:$B$4997,">="&IF($C$4="",DATE(1900,1,1),$C$4),COMPRAS!$B$3:$B$4997,"<="&IF($F$4="",DATE(2999,12,31),$F$4)),0)) -> 0 | Z15: =IF($X$2="TODOS",V15,IF(S15<>"",SUMIFS(COMPRAS!$O$3:$O$4997,COMPRAS!$G$3:$G$4997,S15,COMPRAS!$D$3:$D$4997,$X$2,COMPRAS!$B$3:$B$4997,">="&IF($C$4="",DATE(1900,1,1),$C$4),COMPRAS!$B$3:$B$4997,"<="&IF($F$4="",DATE(2999,12,31),$F$4)),0)) -> 0
A16: 10 | B16: =IFERROR(INDEX($O$2:$O$206,MATCH(LARGE($P$2:$P$206,10),$P$2:$P$206,0)),"") -> PERFECTO MONTERO | C16: =IFERROR(LARGE($P$2:$P$206,10),0) -> 2834.25 | E16: 10 | F16: =IFERROR(INDEX($O$2:$O$206,MATCH(LARGE($Q$2:$Q$206,10),$Q$2:$Q$206,0)),"") -> PERFECTO MONTERO | G16: =IFERROR(LARGE($Q$2:$Q$206,10),0) -> 15098.976 | N16: =PROVEEDORES!A17 -> 50160 | O16: =PROVEEDORES!B17 -> SUBASTAS CORUÑA S.L. | P16: =IF(N16<>"",SUMIFS(COMPRAS!$J$3:$J$4997,COMPRAS!$D$3:$D$4997,N16,COMPRAS!$B$3:$B$4997,">="&IF($C$4="",DATE(1900,1,1),$C$4),COMPRAS!$B$3:$B$4997,"<="&IF($F$4="",DATE(2999,12,31),$F$4)),0) -> 18832.8 | Q16: =IF(N16<>"",SUMIFS(COMPRAS!$O$3:$O$4997,COMPRAS!$D$3:$D$4997,N16,COMPRAS!$B$3:$B$4997,">="&IF($C$4="",DATE(1900,1,1),$C$4),COMPRAS!$B$3:$B$4997,"<="&IF($F$4="",DATE(2999,12,31),$F$4)),0) -> 35085.682 | S16: =PRODUCTOS!A17 -> C802 | T16: =PRODUCTOS!B17 -> BACALAO FRESCO (COD) | U16: =IF(S16<>"",SUMIFS(COMPRAS!$J$3:$J$4997,COMPRAS!$G$3:$G$4997,S16,COMPRAS!$B$3:$B$4997,">="&IF($C$4="",DATE(1900,1,1),$C$4),COMPRAS!$B$3:$B$4997,"<="&IF($F$4="",DATE(2999,12,31),$F$4)),0) -> 0 | V16: =IF(S16<>"",SUMIFS(COMPRAS!$O$3:$O$4997,COMPRAS!$G$3:$G$4997,S16,COMPRAS!$B$3:$B$4997,">="&IF($C$4="",DATE(1900,1,1),$C$4),COMPRAS!$B$3:$B$4997,"<="&IF($F$4="",DATE(2999,12,31),$F$4)),0) -> 0 | Y16: =IF($X$2="TODOS",U16,IF(S16<>"",SUMIFS(COMPRAS!$J$3:$J$4997,COMPRAS!$G$3:$G$4997,S16,COMPRAS!$D$3:$D$4997,$X$2,COMPRAS!$B$3:$B$4997,">="&IF($C$4="",DATE(1900,1,1),$C$4),COMPRAS!$B$3:$B$4997,"<="&IF($F$4="",DATE(2999,12,31),$F$4)),0)) -> 0 | Z16: =IF($X$2="TODOS",V16,IF(S16<>"",SUMIFS(COMPRAS!$O$3:$O$4997,COMPRAS!$G$3:$G$4997,S16,COMPRAS!$D$3:$D$4997,$X$2,COMPRAS!$B$3:$B$4997,">="&IF($C$4="",DATE(1900,1,1),$C$4),COMPRAS!$B$3:$B$4997,"<="&IF($F$4="",DATE(2999,12,31),$F$4)),0)) -> 0
A17: 11 | B17: =IFERROR(INDEX($O$2:$O$206,MATCH(LARGE($P$2:$P$206,11),$P$2:$P$206,0)),"") -> PACO MOINELO | C17: =IFERROR(LARGE($P$2:$P$206,11),0) -> 1761.55 | E17: 11 | F17: =IFERROR(INDEX($O$2:$O$206,MATCH(LARGE($Q$2:$Q$206,11),$Q$2:$Q$206,0)),"") -> AZORFISK UNIPERSONAL LDA | G17: =IFERROR(LARGE($Q$2:$Q$206,11),0) -> 14685.925 | N17: =PROVEEDORES!A18 -> 50163 | O17: =PROVEEDORES!B18 -> SUBASTAS RIVERA S.L. | P17: =IF(N17<>"",SUMIFS(COMPRAS!$J$3:$J$4997,COMPRAS!$D$3:$D$4997,N17,COMPRAS!$B$3:$B$4997,">="&IF($C$4="",DATE(1900,1,1),$C$4),COMPRAS!$B$3:$B$4997,"<="&IF($F$4="",DATE(2999,12,31),$F$4)),0) -> 9601.75 | Q17: =IF(N17<>"",SUMIFS(COMPRAS!$O$3:$O$4997,COMPRAS!$D$3:$D$4997,N17,COMPRAS!$B$3:$B$4997,">="&IF($C$4="",DATE(1900,1,1),$C$4),COMPRAS!$B$3:$B$4997,"<="&IF($F$4="",DATE(2999,12,31),$F$4)),0) -> 43626.4 | S17: =PRODUCTOS!A18 -> C8021 | T17: =PRODUCTOS!B18 -> COCOCHAS DE BACALAO (COD) | U17: =IF(S17<>"",SUMIFS(COMPRAS!$J$3:$J$4997,COMPRAS!$G$3:$G$4997,S17,COMPRAS!$B$3:$B$4997,">="&IF($C$4="",DATE(1900,1,1),$C$4),COMPRAS!$B$3:$B$4997,"<="&IF($F$4="",DATE(2999,12,31),$F$4)),0) -> 0 | V17: =IF(S17<>"",SUMIFS(COMPRAS!$O$3:$O$4997,COMPRAS!$G$3:$G$4997,S17,COMPRAS!$B$3:$B$4997,">="&IF($C$4="",DATE(1900,1,1),$C$4),COMPRAS!$B$3:$B$4997,"<="&IF($F$4="",DATE(2999,12,31),$F$4)),0) -> 0 | Y17: =IF($X$2="TODOS",U17,IF(S17<>"",SUMIFS(COMPRAS!$J$3:$J$4997,COMPRAS!$G$3:$G$4997,S17,COMPRAS!$D$3:$D$4997,$X$2,COMPRAS!$B$3:$B$4997,">="&IF($C$4="",DATE(1900,1,1),$C$4),COMPRAS!$B$3:$B$4997,"<="&IF($F$4="",DATE(2999,12,31),$F$4)),0)) -> 0 | Z17: =IF($X$2="TODOS",V17,IF(S17<>"",SUMIFS(COMPRAS!$O$3:$O$4997,COMPRAS!$G$3:$G$4997,S17,COMPRAS!$D$3:$D$4997,$X$2,COMPRAS!$B$3:$B$4997,">="&IF($C$4="",DATE(1900,1,1),$C$4),COMPRAS!$B$3:$B$4997,"<="&IF($F$4="",DATE(2999,12,31),$F$4)),0)) -> 0
A18: 12 | B18: =IFERROR(INDEX($O$2:$O$206,MATCH(LARGE($P$2:$P$206,12),$P$2:$P$206,0)),"") -> LURDES MARIÑO, S.L. | C18: =IFERROR(LARGE($P$2:$P$206,12),0) -> 1215 | E18: 12 | F18: =IFERROR(INDEX($O$2:$O$206,MATCH(LARGE($Q$2:$Q$206,12),$Q$2:$Q$206,0)),"") -> FURIC MAREE | G18: =IFERROR(LARGE($Q$2:$Q$206,12),0) -> 14000.16 | N18: =PROVEEDORES!A19 -> 50164 | O18: =PROVEEDORES!B19 -> ABRGO NORTE S.L. | P18: =IF(N18<>"",SUMIFS(COMPRAS!$J$3:$J$4997,COMPRAS!$D$3:$D$4997,N18,COMPRAS!$B$3:$B$4997,">="&IF($C$4="",DATE(1900,1,1),$C$4),COMPRAS!$B$3:$B$4997,"<="&IF($F$4="",DATE(2999,12,31),$F$4)),0) -> 240 | Q18: =IF(N18<>"",SUMIFS(COMPRAS!$O$3:$O$4997,COMPRAS!$D$3:$D$4997,N18,COMPRAS!$B$3:$B$4997,">="&IF($C$4="",DATE(1900,1,1),$C$4),COMPRAS!$B$3:$B$4997,"<="&IF($F$4="",DATE(2999,12,31),$F$4)),0) -> 2027.5 | S18: =PRODUCTOS!A19 -> C1546 | T18: =PRODUCTOS!B19 -> BERTORELLA ROCA (FOR) | U18: =IF(S18<>"",SUMIFS(COMPRAS!$J$3:$J$4997,COMPRAS!$G$3:$G$4997,S18,COMPRAS!$B$3:$B$4997,">="&IF($C$4="",DATE(1900,1,1),$C$4),COMPRAS!$B$3:$B$4997,"<="&IF($F$4="",DATE(2999,12,31),$F$4)),0) -> 444.75 | V18: =IF(S18<>"",SUMIFS(COMPRAS!$O$3:$O$4997,COMPRAS!$G$3:$G$4997,S18,COMPRAS!$B$3:$B$4997,">="&IF($C$4="",DATE(1900,1,1),$C$4),COMPRAS!$B$3:$B$4997,"<="&IF($F$4="",DATE(2999,12,31),$F$4)),0) -> 1315.29 | Y18: =IF($X$2="TODOS",U18,IF(S18<>"",SUMIFS(COMPRAS!$J$3:$J$4997,COMPRAS!$G$3:$G$4997,S18,COMPRAS!$D$3:$D$4997,$X$2,COMPRAS!$B$3:$B$4997,">="&IF($C$4="",DATE(1900,1,1),$C$4),COMPRAS!$B$3:$B$4997,"<="&IF($F$4="",DATE(2999,12,31),$F$4)),0)) -> 444.75 | Z18: =IF($X$2="TODOS",V18,IF(S18<>"",SUMIFS(COMPRAS!$O$3:$O$4997,COMPRAS!$G$3:$G$4997,S18,COMPRAS!$D$3:$D$4997,$X$2,COMPRAS!$B$3:$B$4997,">="&IF($C$4="",DATE(1900,1,1),$C$4),COMPRAS!$B$3:$B$4997,"<="&IF($F$4="",DATE(2999,12,31),$F$4)),0)) -> 1315.29
A19: 13 | B19: =IFERROR(INDEX($O$2:$O$206,MATCH(LARGE($P$2:$P$206,13),$P$2:$P$206,0)),"") -> PESCADOS ILLANES S.L. | C19: =IFERROR(LARGE($P$2:$P$206,13),0) -> 1083.6 | E19: 13 | F19: =IFERROR(INDEX($O$2:$O$206,MATCH(LARGE($Q$2:$Q$206,13),$Q$2:$Q$206,0)),"") -> PACO MOINELO | G19: =IFERROR(LARGE($Q$2:$Q$206,13),0) -> 10973.989 | N19: =PROVEEDORES!A20 -> 50190 | O19: =PROVEEDORES!B20 -> PEIXES E MARISCOS ANEIROS S.L. | P19: =IF(N19<>"",SUMIFS(COMPRAS!$J$3:$J$4997,COMPRAS!$D$3:$D$4997,N19,COMPRAS!$B$3:$B$4997,">="&IF($C$4="",DATE(1900,1,1),$C$4),COMPRAS!$B$3:$B$4997,"<="&IF($F$4="",DATE(2999,12,31),$F$4)),0) -> 0 | Q19: =IF(N19<>"",SUMIFS(COMPRAS!$O$3:$O$4997,COMPRAS!$D$3:$D$4997,N19,COMPRAS!$B$3:$B$4997,">="&IF($C$4="",DATE(1900,1,1),$C$4),COMPRAS!$B$3:$B$4997,"<="&IF($F$4="",DATE(2999,12,31),$F$4)),0) -> 0 | S19: =PRODUCTOS!A20 -> C1545 | T19: =PRODUCTOS!B20 -> BERTORELLA (GFB) | U19: =IF(S19<>"",SUMIFS(COMPRAS!$J$3:$J$4997,COMPRAS!$G$3:$G$4997,S19,COMPRAS!$B$3:$B$4997,">="&IF($C$4="",DATE(1900,1,1),$C$4),COMPRAS!$B$3:$B$4997,"<="&IF($F$4="",DATE(2999,12,31),$F$4)),0) -> 1068.5 | V19: =IF(S19<>"",SUMIFS(COMPRAS!$O$3:$O$4997,COMPRAS!$G$3:$G$4997,S19,COMPRAS!$B$3:$B$4997,">="&IF($C$4="",DATE(1900,1,1),$C$4),COMPRAS!$B$3:$B$4997,"<="&IF($F$4="",DATE(2999,12,31),$F$4)),0) -> 3366.663 | Y19: =IF($X$2="TODOS",U19,IF(S19<>"",SUMIFS(COMPRAS!$J$3:$J$4997,COMPRAS!$G$3:$G$4997,S19,COMPRAS!$D$3:$D$4997,$X$2,COMPRAS!$B$3:$B$4997,">="&IF($C$4="",DATE(1900,1,1),$C$4),COMPRAS!$B$3:$B$4997,"<="&IF($F$4="",DATE(2999,12,31),$F$4)),0)) -> 1068.5 | Z19: =IF($X$2="TODOS",V19,IF(S19<>"",SUMIFS(COMPRAS!$O$3:$O$4997,COMPRAS!$G$3:$G$4997,S19,COMPRAS!$D$3:$D$4997,$X$2,COMPRAS!$B$3:$B$4997,">="&IF($C$4="",DATE(1900,1,1),$C$4),COMPRAS!$B$3:$B$4997,"<="&IF($F$4="",DATE(2999,12,31),$F$4)),0)) -> 3366.663
A20: 14 | B20: =IFERROR(INDEX($O$2:$O$206,MATCH(LARGE($P$2:$P$206,14),$P$2:$P$206,0)),"") -> ANGELPESCA S.L. | C20: =IFERROR(LARGE($P$2:$P$206,14),0) -> 1030 | E20: 14 | F20: =IFERROR(INDEX($O$2:$O$206,MATCH(LARGE($Q$2:$Q$206,14),$Q$2:$Q$206,0)),"") -> PESCADO Y MARISCOS ADELAIDA S.L. | G20: =IFERROR(LARGE($Q$2:$Q$206,14),0) -> 5474.4725 | N20: =PROVEEDORES!A21 -> 50196 | O20: =PROVEEDORES!B21 -> PORTABALES S.L. | P20: =IF(N20<>"",SUMIFS(COMPRAS!$J$3:$J$4997,COMPRAS!$D$3:$D$4997,N20,COMPRAS!$B$3:$B$4997,">="&IF($C$4="",DATE(1900,1,1),$C$4),COMPRAS!$B$3:$B$4997,"<="&IF($F$4="",DATE(2999,12,31),$F$4)),0) -> 10 | Q20: =IF(N20<>"",SUMIFS(COMPRAS!$O$3:$O$4997,COMPRAS!$D$3:$D$4997,N20,COMPRAS!$B$3:$B$4997,">="&IF($C$4="",DATE(1900,1,1),$C$4),COMPRAS!$B$3:$B$4997,"<="&IF($F$4="",DATE(2999,12,31),$F$4)),0) -> 30 | S20: =PRODUCTOS!A21 -> C365 | T20: =PRODUCTOS!B21 -> BESUGO (BSR) | U20: =IF(S20<>"",SUMIFS(COMPRAS!$J$3:$J$4997,COMPRAS!$G$3:$G$4997,S20,COMPRAS!$B$3:$B$4997,">="&IF($C$4="",DATE(1900,1,1),$C$4),COMPRAS!$B$3:$B$4997,"<="&IF($F$4="",DATE(2999,12,31),$F$4)),0) -> 358.1 | V20: =IF(S20<>"",SUMIFS(COMPRAS!$O$3:$O$4997,COMPRAS!$G$3:$G$4997,S20,COMPRAS!$B$3:$B$4997,">="&IF($C$4="",DATE(1900,1,1),$C$4),COMPRAS!$B$3:$B$4997,"<="&IF($F$4="",DATE(2999,12,31),$F$4)),0) -> 11163.798 | Y20: =IF($X$2="TODOS",U20,IF(S20<>"",SUMIFS(COMPRAS!$J$3:$J$4997,COMPRAS!$G$3:$G$4997,S20,COMPRAS!$D$3:$D$4997,$X$2,COMPRAS!$B$3:$B$4997,">="&IF($C$4="",DATE(1900,1,1),$C$4),COMPRAS!$B$3:$B$4997,"<="&IF($F$4="",DATE(2999,12,31),$F$4)),0)) -> 358.1 | Z20: =IF($X$2="TODOS",V20,IF(S20<>"",SUMIFS(COMPRAS!$O$3:$O$4997,COMPRAS!$G$3:$G$4997,S20,COMPRAS!$D$3:$D$4997,$X$2,COMPRAS!$B$3:$B$4997,">="&IF($C$4="",DATE(1900,1,1),$C$4),COMPRAS!$B$3:$B$4997,"<="&IF($F$4="",DATE(2999,12,31),$F$4)),0)) -> 11163.798
A21: 15 | B21: =IFERROR(INDEX($O$2:$O$206,MATCH(LARGE($P$2:$P$206,15),$P$2:$P$206,0)),"") -> PESCADO Y MARISCOS ADELAIDA S.L. | C21: =IFERROR(LARGE($P$2:$P$206,15),0) -> 937.74 | E21: 15 | F21: =IFERROR(INDEX($O$2:$O$206,MATCH(LARGE($Q$2:$Q$206,15),$Q$2:$Q$206,0)),"") -> PESCADOS ILLANES S.L. | G21: =IFERROR(LARGE($Q$2:$Q$206,15),0) -> 4802.8434 | N21: =PROVEEDORES!A22 -> 50201 | O21: =PROVEEDORES!B22 -> PESCADOS MANUELA GARCIA S.L | P21: =IF(N21<>"",SUMIFS(COMPRAS!$J$3:$J$4997,COMPRAS!$D$3:$D$4997,N21,COMPRAS!$B$3:$B$4997,">="&IF($C$4="",DATE(1900,1,1),$C$4),COMPRAS!$B$3:$B$4997,"<="&IF($F$4="",DATE(2999,12,31),$F$4)),0) -> 0 | Q21: =IF(N21<>"",SUMIFS(COMPRAS!$O$3:$O$4997,COMPRAS!$D$3:$D$4997,N21,COMPRAS!$B$3:$B$4997,">="&IF($C$4="",DATE(1900,1,1),$C$4),COMPRAS!$B$3:$B$4997,"<="&IF($F$4="",DATE(2999,12,31),$F$4)),0) -> 0 | S21: =PRODUCTOS!A22 -> C562 | T21: =PRODUCTOS!B22 -> BICUDO/ALIGOTE (SBA) | U21: =IF(S21<>"",SUMIFS(COMPRAS!$J$3:$J$4997,COMPRAS!$G$3:$G$4997,S21,COMPRAS!$B$3:$B$4997,">="&IF($C$4="",DATE(1900,1,1),$C$4),COMPRAS!$B$3:$B$4997,"<="&IF($F$4="",DATE(2999,12,31),$F$4)),0) -> 64.85 | V21: =IF(S21<>"",SUMIFS(COMPRAS!$O$3:$O$4997,COMPRAS!$G$3:$G$4997,S21,COMPRAS!$B$3:$B$4997,">="&IF($C$4="",DATE(1900,1,1),$C$4),COMPRAS!$B$3:$B$4997,"<="&IF($F$4="",DATE(2999,12,31),$F$4)),0) -> 398.1621 | Y21: =IF($X$2="TODOS",U21,IF(S21<>"",SUMIFS(COMPRAS!$J$3:$J$4997,COMPRAS!$G$3:$G$4997,S21,COMPRAS!$D$3:$D$4997,$X$2,COMPRAS!$B$3:$B$4997,">="&IF($C$4="",DATE(1900,1,1),$C$4),COMPRAS!$B$3:$B$4997,"<="&IF($F$4="",DATE(2999,12,31),$F$4)),0)) -> 64.85 | Z21: =IF($X$2="TODOS",V21,IF(S21<>"",SUMIFS(COMPRAS!$O$3:$O$4997,COMPRAS!$G$3:$G$4997,S21,COMPRAS!$D$3:$D$4997,$X$2,COMPRAS!$B$3:$B$4997,">="&IF($C$4="",DATE(1900,1,1),$C$4),COMPRAS!$B$3:$B$4997,"<="&IF($F$4="",DATE(2999,12,31),$F$4)),0)) -> 398.1621
N22: =PROVEEDORES!A23 -> 50207 | O22: =PROVEEDORES!B23 -> MARLEDICIA S.L | P22: =IF(N22<>"",SUMIFS(COMPRAS!$J$3:$J$4997,COMPRAS!$D$3:$D$4997,N22,COMPRAS!$B$3:$B$4997,">="&IF($C$4="",DATE(1900,1,1),$C$4),COMPRAS!$B$3:$B$4997,"<="&IF($F$4="",DATE(2999,12,31),$F$4)),0) -> 11.5 | Q22: =IF(N22<>"",SUMIFS(COMPRAS!$O$3:$O$4997,COMPRAS!$D$3:$D$4997,N22,COMPRAS!$B$3:$B$4997,">="&IF($C$4="",DATE(1900,1,1),$C$4),COMPRAS!$B$3:$B$4997,"<="&IF($F$4="",DATE(2999,12,31),$F$4)),0) -> 39.882 | S22: =PRODUCTOS!A23 -> C601 | T22: =PRODUCTOS!B23 -> BOGAVANTE CANADIENSE CHIX (LBA) | U22: =IF(S22<>"",SUMIFS(COMPRAS!$J$3:$J$4997,COMPRAS!$G$3:$G$4997,S22,COMPRAS!$B$3:$B$4997,">="&IF($C$4="",DATE(1900,1,1),$C$4),COMPRAS!$B$3:$B$4997,"<="&IF($F$4="",DATE(2999,12,31),$F$4)),0) -> 0 | V22: =IF(S22<>"",SUMIFS(COMPRAS!$O$3:$O$4997,COMPRAS!$G$3:$G$4997,S22,COMPRAS!$B$3:$B$4997,">="&IF($C$4="",DATE(1900,1,1),$C$4),COMPRAS!$B$3:$B$4997,"<="&IF($F$4="",DATE(2999,12,31),$F$4)),0) -> 0 | Y22: =IF($X$2="TODOS",U22,IF(S22<>"",SUMIFS(COMPRAS!$J$3:$J$4997,COMPRAS!$G$3:$G$4997,S22,COMPRAS!$D$3:$D$4997,$X$2,COMPRAS!$B$3:$B$4997,">="&IF($C$4="",DATE(1900,1,1),$C$4),COMPRAS!$B$3:$B$4997,"<="&IF($F$4="",DATE(2999,12,31),$F$4)),0)) -> 0 | Z22: =IF($X$2="TODOS",V22,IF(S22<>"",SUMIFS(COMPRAS!$O$3:$O$4997,COMPRAS!$G$3:$G$4997,S22,COMPRAS!$D$3:$D$4997,$X$2,COMPRAS!$B$3:$B$4997,">="&IF($C$4="",DATE(1900,1,1),$C$4),COMPRAS!$B$3:$B$4997,"<="&IF($F$4="",DATE(2999,12,31),$F$4)),0)) -> 0
N23: =PROVEEDORES!A24 -> 50213 | O23: =PROVEEDORES!B24 -> PESCADOS OCEANO ATLANTICO S.L. | P23: =IF(N23<>"",SUMIFS(COMPRAS!$J$3:$J$4997,COMPRAS!$D$3:$D$4997,N23,COMPRAS!$B$3:$B$4997,">="&IF($C$4="",DATE(1900,1,1),$C$4),COMPRAS!$B$3:$B$4997,"<="&IF($F$4="",DATE(2999,12,31),$F$4)),0) -> 36 | Q23: =IF(N23<>"",SUMIFS(COMPRAS!$O$3:$O$4997,COMPRAS!$D$3:$D$4997,N23,COMPRAS!$B$3:$B$4997,">="&IF($C$4="",DATE(1900,1,1),$C$4),COMPRAS!$B$3:$B$4997,"<="&IF($F$4="",DATE(2999,12,31),$F$4)),0) -> 108 | S23: =PRODUCTOS!A24 -> C3979 | T23: =PRODUCTOS!B24 -> BONITO DEL NORTE 5/7 | U23: =IF(S23<>"",SUMIFS(COMPRAS!$J$3:$J$4997,COMPRAS!$G$3:$G$4997,S23,COMPRAS!$B$3:$B$4997,">="&IF($C$4="",DATE(1900,1,1),$C$4),COMPRAS!$B$3:$B$4997,"<="&IF($F$4="",DATE(2999,12,31),$F$4)),0) -> 898.25 | V23: =IF(S23<>"",SUMIFS(COMPRAS!$O$3:$O$4997,COMPRAS!$G$3:$G$4997,S23,COMPRAS!$B$3:$B$4997,">="&IF($C$4="",DATE(1900,1,1),$C$4),COMPRAS!$B$3:$B$4997,"<="&IF($F$4="",DATE(2999,12,31),$F$4)),0) -> 3933.4642 | Y23: =IF($X$2="TODOS",U23,IF(S23<>"",SUMIFS(COMPRAS!$J$3:$J$4997,COMPRAS!$G$3:$G$4997,S23,COMPRAS!$D$3:$D$4997,$X$2,COMPRAS!$B$3:$B$4997,">="&IF($C$4="",DATE(1900,1,1),$C$4),COMPRAS!$B$3:$B$4997,"<="&IF($F$4="",DATE(2999,12,31),$F$4)),0)) -> 898.25 | Z23: =IF($X$2="TODOS",V23,IF(S23<>"",SUMIFS(COMPRAS!$O$3:$O$4997,COMPRAS!$G$3:$G$4997,S23,COMPRAS!$D$3:$D$4997,$X$2,COMPRAS!$B$3:$B$4997,">="&IF($C$4="",DATE(1900,1,1),$C$4),COMPRAS!$B$3:$B$4997,"<="&IF($F$4="",DATE(2999,12,31),$F$4)),0)) -> 3933.4642
A24: TOP 15 PRODUCTOS -- MAS KILOS COMPRADOS | E24: TOP 15 PRODUCTOS -- MAS IMPORTE COMPRADO | N24: =PROVEEDORES!A25 -> 50218 | O24: =PROVEEDORES!B25 -> ACERGA | P24: =IF(N24<>"",SUMIFS(COMPRAS!$J$3:$J$4997,COMPRAS!$D$3:$D$4997,N24,COMPRAS!$B$3:$B$4997,">="&IF($C$4="",DATE(1900,1,1),$C$4),COMPRAS!$B$3:$B$4997,"<="&IF($F$4="",DATE(2999,12,31),$F$4)),0) -> 13166 | Q24: =IF(N24<>"",SUMIFS(COMPRAS!$O$3:$O$4997,COMPRAS!$D$3:$D$4997,N24,COMPRAS!$B$3:$B$4997,">="&IF($C$4="",DATE(1900,1,1),$C$4),COMPRAS!$B$3:$B$4997,"<="&IF($F$4="",DATE(2999,12,31),$F$4)),0) -> 20065.787 | S24: =PRODUCTOS!A25 -> C397 | T24: =PRODUCTOS!B25 -> BONITO DEL NORTE 5/7 | U24: =IF(S24<>"",SUMIFS(COMPRAS!$J$3:$J$4997,COMPRAS!$G$3:$G$4997,S24,COMPRAS!$B$3:$B$4997,">="&IF($C$4="",DATE(1900,1,1),$C$4),COMPRAS!$B$3:$B$4997,"<="&IF($F$4="",DATE(2999,12,31),$F$4)),0) -> 3944.05 | V24: =IF(S24<>"",SUMIFS(COMPRAS!$O$3:$O$4997,COMPRAS!$G$3:$G$4997,S24,COMPRAS!$B$3:$B$4997,">="&IF($C$4="",DATE(1900,1,1),$C$4),COMPRAS!$B$3:$B$4997,"<="&IF($F$4="",DATE(2999,12,31),$F$4)),0) -> 19023.43 | Y24: =IF($X$2="TODOS",U24,IF(S24<>"",SUMIFS(COMPRAS!$J$3:$J$4997,COMPRAS!$G$3:$G$4997,S24,COMPRAS!$D$3:$D$4997,$X$2,COMPRAS!$B$3:$B$4997,">="&IF($C$4="",DATE(1900,1,1),$C$4),COMPRAS!$B$3:$B$4997,"<="&IF($F$4="",DATE(2999,12,31),$F$4)),0)) -> 3944.05 | Z24: =IF($X$2="TODOS",V24,IF(S24<>"",SUMIFS(COMPRAS!$O$3:$O$4997,COMPRAS!$G$3:$G$4997,S24,COMPRAS!$D$3:$D$4997,$X$2,COMPRAS!$B$3:$B$4997,">="&IF($C$4="",DATE(1900,1,1),$C$4),COMPRAS!$B$3:$B$4997,"<="&IF($F$4="",DATE(2999,12,31),$F$4)),0)) -> 19023.43
A25: # | B25: Producto | C25: Kilos | E25: # | F25: Producto | G25: Importe | N25: =PROVEEDORES!A26 -> 50227 | O25: =PROVEEDORES!B26 -> BRISAMAR | P25: =IF(N25<>"",SUMIFS(COMPRAS!$J$3:$J$4997,COMPRAS!$D$3:$D$4997,N25,COMPRAS!$B$3:$B$4997,">="&IF($C$4="",DATE(1900,1,1),$C$4),COMPRAS!$B$3:$B$4997,"<="&IF($F$4="",DATE(2999,12,31),$F$4)),0) -> 0 | Q25: =IF(N25<>"",SUMIFS(COMPRAS!$O$3:$O$4997,COMPRAS!$D$3:$D$4997,N25,COMPRAS!$B$3:$B$4997,">="&IF($C$4="",DATE(1900,1,1),$C$4),COMPRAS!$B$3:$B$4997,"<="&IF($F$4="",DATE(2999,12,31),$F$4)),0) -> 0 | S25: =PRODUCTOS!A26 -> C387 | T25: =PRODUCTOS!B26 -> BOQUERON/ BOCARTE/ ANCHOA (ANE) | U25: =IF(S25<>"",SUMIFS(COMPRAS!$J$3:$J$4997,COMPRAS!$G$3:$G$4997,S25,COMPRAS!$B$3:$B$4997,">="&IF($C$4="",DATE(1900,1,1),$C$4),COMPRAS!$B$3:$B$4997,"<="&IF($F$4="",DATE(2999,12,31),$F$4)),0) -> 48607 | V25: =IF(S25<>"",SUMIFS(COMPRAS!$O$3:$O$4997,COMPRAS!$G$3:$G$4997,S25,COMPRAS!$B$3:$B$4997,">="&IF($C$4="",DATE(1900,1,1),$C$4),COMPRAS!$B$3:$B$4997,"<="&IF($F$4="",DATE(2999,12,31),$F$4)),0) -> 74198.663 | Y25: =IF($X$2="TODOS",U25,IF(S25<>"",SUMIFS(COMPRAS!$J$3:$J$4997,COMPRAS!$G$3:$G$4997,S25,COMPRAS!$D$3:$D$4997,$X$2,COMPRAS!$B$3:$B$4997,">="&IF($C$4="",DATE(1900,1,1),$C$4),COMPRAS!$B$3:$B$4997,"<="&IF($F$4="",DATE(2999,12,31),$F$4)),0)) -> 48607 | Z25: =IF($X$2="TODOS",V25,IF(S25<>"",SUMIFS(COMPRAS!$O$3:$O$4997,COMPRAS!$G$3:$G$4997,S25,COMPRAS!$D$3:$D$4997,$X$2,COMPRAS!$B$3:$B$4997,">="&IF($C$4="",DATE(1900,1,1),$C$4),COMPRAS!$B$3:$B$4997,"<="&IF($F$4="",DATE(2999,12,31),$F$4)),0)) -> 74198.663
A26: 1 | B26: =IFERROR(INDEX($T$2:$T$231,MATCH(LARGE($U$2:$U$231,1),$U$2:$U$231,0)),"") -> BOQUERON/ BOCARTE/ ANCHOA (ANE) | C26: =IFERROR(LARGE($U$2:$U$231,1),0) -> 48607 | E26: 1 | F26: =IFERROR(INDEX($T$2:$T$231,MATCH(LARGE($V$2:$V$231,1),$V$2:$V$231,0)),"") -> BOQUERON/ BOCARTE/ ANCHOA (ANE) | G26: =IFERROR(LARGE($V$2:$V$231,1),0) -> 74198.663 | N26: =PROVEEDORES!A27 -> 50229 | O26: =PROVEEDORES!B27 -> DA LONXA O PRATO | P26: =IF(N26<>"",SUMIFS(COMPRAS!$J$3:$J$4997,COMPRAS!$D$3:$D$4997,N26,COMPRAS!$B$3:$B$4997,">="&IF($C$4="",DATE(1900,1,1),$C$4),COMPRAS!$B$3:$B$4997,"<="&IF($F$4="",DATE(2999,12,31),$F$4)),0) -> 0 | Q26: =IF(N26<>"",SUMIFS(COMPRAS!$O$3:$O$4997,COMPRAS!$D$3:$D$4997,N26,COMPRAS!$B$3:$B$4997,">="&IF($C$4="",DATE(1900,1,1),$C$4),COMPRAS!$B$3:$B$4997,"<="&IF($F$4="",DATE(2999,12,31),$F$4)),0) -> 0 | S26: =PRODUCTOS!A27 -> C822 | T26: =PRODUCTOS!B27 -> BUEY FRANCES (CRE) | U26: =IF(S26<>"",SUMIFS(COMPRAS!$J$3:$J$4997,COMPRAS!$G$3:$G$4997,S26,COMPRAS!$B$3:$B$4997,">="&IF($C$4="",DATE(1900,1,1),$C$4),COMPRAS!$B$3:$B$4997,"<="&IF($F$4="",DATE(2999,12,31),$F$4)),0) -> 0 | V26: =IF(S26<>"",SUMIFS(COMPRAS!$O$3:$O$4997,COMPRAS!$G$3:$G$4997,S26,COMPRAS!$B$3:$B$4997,">="&IF($C$4="",DATE(1900,1,1),$C$4),COMPRAS!$B$3:$B$4997,"<="&IF($F$4="",DATE(2999,12,31),$F$4)),0) -> 0 | Y26: =IF($X$2="TODOS",U26,IF(S26<>"",SUMIFS(COMPRAS!$J$3:$J$4997,COMPRAS!$G$3:$G$4997,S26,COMPRAS!$D$3:$D$4997,$X$2,COMPRAS!$B$3:$B$4997,">="&IF($C$4="",DATE(1900,1,1),$C$4),COMPRAS!$B$3:$B$4997,"<="&IF($F$4="",DATE(2999,12,31),$F$4)),0)) -> 0 | Z26: =IF($X$2="TODOS",V26,IF(S26<>"",SUMIFS(COMPRAS!$O$3:$O$4997,COMPRAS!$G$3:$G$4997,S26,COMPRAS!$D$3:$D$4997,$X$2,COMPRAS!$B$3:$B$4997,">="&IF($C$4="",DATE(1900,1,1),$C$4),COMPRAS!$B$3:$B$4997,"<="&IF($F$4="",DATE(2999,12,31),$F$4)),0)) -> 0
A27: 2 | B27: =IFERROR(INDEX($T$2:$T$231,MATCH(LARGE($U$2:$U$231,2),$U$2:$U$231,0)),"") -> LIRIO/ BACALADILLA/ PERLA (WHB) | C27: =IFERROR(LARGE($U$2:$U$231,2),0) -> 32511.65 | E27: 2 | F27: =IFERROR(INDEX($T$2:$T$231,MATCH(LARGE($V$2:$V$231,2),$V$2:$V$231,0)),"") -> LIRIO/ BACALADILLA/ PERLA (WHB) | G27: =IFERROR(LARGE($V$2:$V$231,2),0) -> 57717.359 | N27: =PROVEEDORES!A28 -> 50231 | O27: =PROVEEDORES!B28 -> PESCADOS ERNESTO Y MARIA S.L. | P27: =IF(N27<>"",SUMIFS(COMPRAS!$J$3:$J$4997,COMPRAS!$D$3:$D$4997,N27,COMPRAS!$B$3:$B$4997,">="&IF($C$4="",DATE(1900,1,1),$C$4),COMPRAS!$B$3:$B$4997,"<="&IF($F$4="",DATE(2999,12,31),$F$4)),0) -> 0 | Q27: =IF(N27<>"",SUMIFS(COMPRAS!$O$3:$O$4997,COMPRAS!$D$3:$D$4997,N27,COMPRAS!$B$3:$B$4997,">="&IF($C$4="",DATE(1900,1,1),$C$4),COMPRAS!$B$3:$B$4997,"<="&IF($F$4="",DATE(2999,12,31),$F$4)),0) -> 0 | S27: =PRODUCTOS!A28 -> C395 | T27: =PRODUCTOS!B28 -> CABALL/ SARDA/ VERDEL (MAC) | U27: =IF(S27<>"",SUMIFS(COMPRAS!$J$3:$J$4997,COMPRAS!$G$3:$G$4997,S27,COMPRAS!$B$3:$B$4997,">="&IF($C$4="",DATE(1900,1,1),$C$4),COMPRAS!$B$3:$B$4997,"<="&IF($F$4="",DATE(2999,12,31),$F$4)),0) -> 3290.95 | V27: =IF(S27<>"",SUMIFS(COMPRAS!$O$3:$O$4997,COMPRAS!$G$3:$G$4997,S27,COMPRAS!$B$3:$B$4997,">="&IF($C$4="",DATE(1900,1,1),$C$4),COMPRAS!$B$3:$B$4997,"<="&IF($F$4="",DATE(2999,12,31),$F$4)),0) -> 12989.67 | Y27: =IF($X$2="TODOS",U27,IF(S27<>"",SUMIFS(COMPRAS!$J$3:$J$4997,COMPRAS!$G$3:$G$4997,S27,COMPRAS!$D$3:$D$4997,$X$2,COMPRAS!$B$3:$B$4997,">="&IF($C$4="",DATE(1900,1,1),$C$4),COMPRAS!$B$3:$B$4997,"<="&IF($F$4="",DATE(2999,12,31),$F$4)),0)) -> 3290.95 | Z27: =IF($X$2="TODOS",V27,IF(S27<>"",SUMIFS(COMPRAS!$O$3:$O$4997,COMPRAS!$G$3:$G$4997,S27,COMPRAS!$D$3:$D$4997,$X$2,COMPRAS!$B$3:$B$4997,">="&IF($C$4="",DATE(1900,1,1),$C$4),COMPRAS!$B$3:$B$4997,"<="&IF($F$4="",DATE(2999,12,31),$F$4)),0)) -> 12989.67
A28: 3 | B28: =IFERROR(INDEX($T$2:$T$231,MATCH(LARGE($U$2:$U$231,3),$U$2:$U$231,0)),"") -> RAPE BLANCO RASCO (MON) | C28: =IFERROR(LARGE($U$2:$U$231,3),0) -> 7149.7 | E28: 3 | F28: =IFERROR(INDEX($T$2:$T$231,MATCH(LARGE($V$2:$V$231,3),$V$2:$V$231,0)),"") -> RAPE BLANCO RASCO (MON) | G28: =IFERROR(LARGE($V$2:$V$231,3),0) -> 47464.017 | N28: =PROVEEDORES!A29 -> 50232 | O28: =PROVEEDORES!B29 -> XESTION NOVA LONXA RIVEIRA S.L. | P28: =IF(N28<>"",SUMIFS(COMPRAS!$J$3:$J$4997,COMPRAS!$D$3:$D$4997,N28,COMPRAS!$B$3:$B$4997,">="&IF($C$4="",DATE(1900,1,1),$C$4),COMPRAS!$B$3:$B$4997,"<="&IF($F$4="",DATE(2999,12,31),$F$4)),0) -> 41663.771 | Q28: =IF(N28<>"",SUMIFS(COMPRAS!$O$3:$O$4997,COMPRAS!$D$3:$D$4997,N28,COMPRAS!$B$3:$B$4997,">="&IF($C$4="",DATE(1900,1,1),$C$4),COMPRAS!$B$3:$B$4997,"<="&IF($F$4="",DATE(2999,12,31),$F$4)),0) -> 101872.87 | S28: =PRODUCTOS!A29 -> C2550 | T28: =PRODUCTOS!B29 -> CABRACHO/ ESCARAPOTE (RSE) | U28: =IF(S28<>"",SUMIFS(COMPRAS!$J$3:$J$4997,COMPRAS!$G$3:$G$4997,S28,COMPRAS!$B$3:$B$4997,">="&IF($C$4="",DATE(1900,1,1),$C$4),COMPRAS!$B$3:$B$4997,"<="&IF($F$4="",DATE(2999,12,31),$F$4)),0) -> 382.5 | V28: =IF(S28<>"",SUMIFS(COMPRAS!$O$3:$O$4997,COMPRAS!$G$3:$G$4997,S28,COMPRAS!$B$3:$B$4997,">="&IF($C$4="",DATE(1900,1,1),$C$4),COMPRAS!$B$3:$B$4997,"<="&IF($F$4="",DATE(2999,12,31),$F$4)),0) -> 3663.7762 | Y28: =IF($X$2="TODOS",U28,IF(S28<>"",SUMIFS(COMPRAS!$J$3:$J$4997,COMPRAS!$G$3:$G$4997,S28,COMPRAS!$D$3:$D$4997,$X$2,COMPRAS!$B$3:$B$4997,">="&IF($C$4="",DATE(1900,1,1),$C$4),COMPRAS!$B$3:$B$4997,"<="&IF($F$4="",DATE(2999,12,31),$F$4)),0)) -> 382.5 | Z28: =IF($X$2="TODOS",V28,IF(S28<>"",SUMIFS(COMPRAS!$O$3:$O$4997,COMPRAS!$G$3:$G$4997,S28,COMPRAS!$D$3:$D$4997,$X$2,COMPRAS!$B$3:$B$4997,">="&IF($C$4="",DATE(1900,1,1),$C$4),COMPRAS!$B$3:$B$4997,"<="&IF($F$4="",DATE(2999,12,31),$F$4)),0)) -> 3663.7762
A29: 4 | B29: =IFERROR(INDEX($T$2:$T$231,MATCH(LARGE($U$2:$U$231,4),$U$2:$U$231,0)),"") -> MERLUZA EUROPEA/ FINA DIA | C29: =IFERROR(LARGE($U$2:$U$231,4),0) -> 5733.75 | E29: 4 | F29: =IFERROR(INDEX($T$2:$T$231,MATCH(LARGE($V$2:$V$231,4),$V$2:$V$231,0)),"") -> BONITO DEL NORTE 5/7 | G29: =IFERROR(LARGE($V$2:$V$231,4),0) -> 19023.43 | N29: =PROVEEDORES!A30 -> 50233 | O29: =PROVEEDORES!B30 -> ANGELPESCA S.L. | P29: =IF(N29<>"",SUMIFS(COMPRAS!$J$3:$J$4997,COMPRAS!$D$3:$D$4997,N29,COMPRAS!$B$3:$B$4997,">="&IF($C$4="",DATE(1900,1,1),$C$4),COMPRAS!$B$3:$B$4997,"<="&IF($F$4="",DATE(2999,12,31),$F$4)),0) -> 1030 | Q29: =IF(N29<>"",SUMIFS(COMPRAS!$O$3:$O$4997,COMPRAS!$D$3:$D$4997,N29,COMPRAS!$B$3:$B$4997,">="&IF($C$4="",DATE(1900,1,1),$C$4),COMPRAS!$B$3:$B$4997,"<="&IF($F$4="",DATE(2999,12,31),$F$4)),0) -> 1871.86 | S29: =PRODUCTOS!A30 -> C2552 | T29: =PRODUCTOS!B30 -> CABRACHO DE FONDO (TJX) | U29: =IF(S29<>"",SUMIFS(COMPRAS!$J$3:$J$4997,COMPRAS!$G$3:$G$4997,S29,COMPRAS!$B$3:$B$4997,">="&IF($C$4="",DATE(1900,1,1),$C$4),COMPRAS!$B$3:$B$4997,"<="&IF($F$4="",DATE(2999,12,31),$F$4)),0) -> 28.3 | V29: =IF(S29<>"",SUMIFS(COMPRAS!$O$3:$O$4997,COMPRAS!$G$3:$G$4997,S29,COMPRAS!$B$3:$B$4997,">="&IF($C$4="",DATE(1900,1,1),$C$4),COMPRAS!$B$3:$B$4997,"<="&IF($F$4="",DATE(2999,12,31),$F$4)),0) -> 144.33 | Y29: =IF($X$2="TODOS",U29,IF(S29<>"",SUMIFS(COMPRAS!$J$3:$J$4997,COMPRAS!$G$3:$G$4997,S29,COMPRAS!$D$3:$D$4997,$X$2,COMPRAS!$B$3:$B$4997,">="&IF($C$4="",DATE(1900,1,1),$C$4),COMPRAS!$B$3:$B$4997,"<="&IF($F$4="",DATE(2999,12,31),$F$4)),0)) -> 28.3 | Z29: =IF($X$2="TODOS",V29,IF(S29<>"",SUMIFS(COMPRAS!$O$3:$O$4997,COMPRAS!$G$3:$G$4997,S29,COMPRAS!$D$3:$D$4997,$X$2,COMPRAS!$B$3:$B$4997,">="&IF($C$4="",DATE(1900,1,1),$C$4),COMPRAS!$B$3:$B$4997,"<="&IF($F$4="",DATE(2999,12,31),$F$4)),0)) -> 144.33
A30: 5 | B30: =IFERROR(INDEX($T$2:$T$231,MATCH(LARGE($U$2:$U$231,5),$U$2:$U$231,0)),"") -> VARIADO PEQUEÑO | C30: =IFERROR(LARGE($U$2:$U$231,5),0) -> 4046.25 | E30: 5 | F30: =IFERROR(INDEX($T$2:$T$231,MATCH(LARGE($V$2:$V$231,5),$V$2:$V$231,0)),"") -> MERLUZA EUROPEA VOLANTA ALTURA | G30: =IFERROR(LARGE($V$2:$V$231,5),0) -> 16611.44 | N30: =PROVEEDORES!A31 -> 50235 | O30: =PROVEEDORES!B31 -> MANUEL CEBREIRA MELLA | P30: =IF(N30<>"",SUMIFS(COMPRAS!$J$3:$J$4997,COMPRAS!$D$3:$D$4997,N30,COMPRAS!$B$3:$B$4997,">="&IF($C$4="",DATE(1900,1,1),$C$4),COMPRAS!$B$3:$B$4997,"<="&IF($F$4="",DATE(2999,12,31),$F$4)),0) -> 0 | Q30: =IF(N30<>"",SUMIFS(COMPRAS!$O$3:$O$4997,COMPRAS!$D$3:$D$4997,N30,COMPRAS!$B$3:$B$4997,">="&IF($C$4="",DATE(1900,1,1),$C$4),COMPRAS!$B$3:$B$4997,"<="&IF($F$4="",DATE(2999,12,31),$F$4)),0) -> 0 | S30: =PRODUCTOS!A31 -> C255 | T30: =PRODUCTOS!B31 -> CABRAS/ GALLINETA (BRF) | U30: =IF(S30<>"",SUMIFS(COMPRAS!$J$3:$J$4997,COMPRAS!$G$3:$G$4997,S30,COMPRAS!$B$3:$B$4997,">="&IF($C$4="",DATE(1900,1,1),$C$4),COMPRAS!$B$3:$B$4997,"<="&IF($F$4="",DATE(2999,12,31),$F$4)),0) -> 1265.3 | V30: =IF(S30<>"",SUMIFS(COMPRAS!$O$3:$O$4997,COMPRAS!$G$3:$G$4997,S30,COMPRAS!$B$3:$B$4997,">="&IF($C$4="",DATE(1900,1,1),$C$4),COMPRAS!$B$3:$B$4997,"<="&IF($F$4="",DATE(2999,12,31),$F$4)),0) -> 8640.443 | Y30: =IF($X$2="TODOS",U30,IF(S30<>"",SUMIFS(COMPRAS!$J$3:$J$4997,COMPRAS!$G$3:$G$4997,S30,COMPRAS!$D$3:$D$4997,$X$2,COMPRAS!$B$3:$B$4997,">="&IF($C$4="",DATE(1900,1,1),$C$4),COMPRAS!$B$3:$B$4997,"<="&IF($F$4="",DATE(2999,12,31),$F$4)),0)) -> 1265.3 | Z30: =IF($X$2="TODOS",V30,IF(S30<>"",SUMIFS(COMPRAS!$O$3:$O$4997,COMPRAS!$G$3:$G$4997,S30,COMPRAS!$D$3:$D$4997,$X$2,COMPRAS!$B$3:$B$4997,">="&IF($C$4="",DATE(1900,1,1),$C$4),COMPRAS!$B$3:$B$4997,"<="&IF($F$4="",DATE(2999,12,31),$F$4)),0)) -> 8640.443
A31: 6 | B31: =IFERROR(INDEX($T$2:$T$231,MATCH(LARGE($U$2:$U$231,6),$U$2:$U$231,0)),"") -> BONITO DEL NORTE 5/7 | C31: =IFERROR(LARGE($U$2:$U$231,6),0) -> 3944.05 | E31: 6 | F31: =IFERROR(INDEX($T$2:$T$231,MATCH(LARGE($V$2:$V$231,6),$V$2:$V$231,0)),"") -> MERLUZA EUROPEA/ FINA DIA | G31: =IFERROR(LARGE($V$2:$V$231,6),0) -> 16382.407 | N31: =PROVEEDORES!A32 -> 50236 | O31: =PROVEEDORES!B32 -> CASIMIRO PEREZ RODRIGUEZ | P31: =IF(N31<>"",SUMIFS(COMPRAS!$J$3:$J$4997,COMPRAS!$D$3:$D$4997,N31,COMPRAS!$B$3:$B$4997,">="&IF($C$4="",DATE(1900,1,1),$C$4),COMPRAS!$B$3:$B$4997,"<="&IF($F$4="",DATE(2999,12,31),$F$4)),0) -> 0 | Q31: =IF(N31<>"",SUMIFS(COMPRAS!$O$3:$O$4997,COMPRAS!$D$3:$D$4997,N31,COMPRAS!$B$3:$B$4997,">="&IF($C$4="",DATE(1900,1,1),$C$4),COMPRAS!$B$3:$B$4997,"<="&IF($F$4="",DATE(2999,12,31),$F$4)),0) -> 0 | S31: =PRODUCTOS!A32 -> C258 | T31: =PRODUCTOS!B32 -> CABRILLAS/ SERRANO (CBR) | U31: =IF(S31<>"",SUMIFS(COMPRAS!$J$3:$J$4997,COMPRAS!$G$3:$G$4997,S31,COMPRAS!$B$3:$B$4997,">="&IF($C$4="",DATE(1900,1,1),$C$4),COMPRAS!$B$3:$B$4997,"<="&IF($F$4="",DATE(2999,12,31),$F$4)),0) -> 0 | V31: =IF(S31<>"",SUMIFS(COMPRAS!$O$3:$O$4997,COMPRAS!$G$3:$G$4997,S31,COMPRAS!$B$3:$B$4997,">="&IF($C$4="",DATE(1900,1,1),$C$4),COMPRAS!$B$3:$B$4997,"<="&IF($F$4="",DATE(2999,12,31),$F$4)),0) -> 0 | Y31: =IF($X$2="TODOS",U31,IF(S31<>"",SUMIFS(COMPRAS!$J$3:$J$4997,COMPRAS!$G$3:$G$4997,S31,COMPRAS!$D$3:$D$4997,$X$2,COMPRAS!$B$3:$B$4997,">="&IF($C$4="",DATE(1900,1,1),$C$4),COMPRAS!$B$3:$B$4997,"<="&IF($F$4="",DATE(2999,12,31),$F$4)),0)) -> 0 | Z31: =IF($X$2="TODOS",V31,IF(S31<>"",SUMIFS(COMPRAS!$O$3:$O$4997,COMPRAS!$G$3:$G$4997,S31,COMPRAS!$D$3:$D$4997,$X$2,COMPRAS!$B$3:$B$4997,">="&IF($C$4="",DATE(1900,1,1),$C$4),COMPRAS!$B$3:$B$4997,"<="&IF($F$4="",DATE(2999,12,31),$F$4)),0)) -> 0
A32: 7 | B32: =IFERROR(INDEX($T$2:$T$231,MATCH(LARGE($U$2:$U$231,7),$U$2:$U$231,0)),"") -> MERLUZA EUROPEA ARRASTRE (HKE) | C32: =IFERROR(LARGE($U$2:$U$231,7),0) -> 3583.45 | E32: 7 | F32: =IFERROR(INDEX($T$2:$T$231,MATCH(LARGE($V$2:$V$231,7),$V$2:$V$231,0)),"") -> LUBINA RIA/ ROBALIZA (BSS) | G32: =IFERROR(LARGE($V$2:$V$231,7),0) -> 16171.083 | N32: =PROVEEDORES!A33 -> 50509 | O32: =PROVEEDORES!B33 -> AZORFISK UNIPERSONAL LDA | P32: =IF(N32<>"",SUMIFS(COMPRAS!$J$3:$J$4997,COMPRAS!$D$3:$D$4997,N32,COMPRAS!$B$3:$B$4997,">="&IF($C$4="",DATE(1900,1,1),$C$4),COMPRAS!$B$3:$B$4997,"<="&IF($F$4="",DATE(2999,12,31),$F$4)),0) -> 479.4 | Q32: =IF(N32<>"",SUMIFS(COMPRAS!$O$3:$O$4997,COMPRAS!$D$3:$D$4997,N32,COMPRAS!$B$3:$B$4997,">="&IF($C$4="",DATE(1900,1,1),$C$4),COMPRAS!$B$3:$B$4997,"<="&IF($F$4="",DATE(2999,12,31),$F$4)),0) -> 14685.925 | S32: =PRODUCTOS!A33 -> C710 | T32: =PRODUCTOS!B33 -> CALAAMR COMUN (SQR) | U32: =IF(S32<>"",SUMIFS(COMPRAS!$J$3:$J$4997,COMPRAS!$G$3:$G$4997,S32,COMPRAS!$B$3:$B$4997,">="&IF($C$4="",DATE(1900,1,1),$C$4),COMPRAS!$B$3:$B$4997,"<="&IF($F$4="",DATE(2999,12,31),$F$4)),0) -> 113.7 | V32: =IF(S32<>"",SUMIFS(COMPRAS!$O$3:$O$4997,COMPRAS!$G$3:$G$4997,S32,COMPRAS!$B$3:$B$4997,">="&IF($C$4="",DATE(1900,1,1),$C$4),COMPRAS!$B$3:$B$4997,"<="&IF($F$4="",DATE(2999,12,31),$F$4)),0) -> 1882.135 | Y32: =IF($X$2="TODOS",U32,IF(S32<>"",SUMIFS(COMPRAS!$J$3:$J$4997,COMPRAS!$G$3:$G$4997,S32,COMPRAS!$D$3:$D$4997,$X$2,COMPRAS!$B$3:$B$4997,">="&IF($C$4="",DATE(1900,1,1),$C$4),COMPRAS!$B$3:$B$4997,"<="&IF($F$4="",DATE(2999,12,31),$F$4)),0)) -> 113.7 | Z32: =IF($X$2="TODOS",V32,IF(S32<>"",SUMIFS(COMPRAS!$O$3:$O$4997,COMPRAS!$G$3:$G$4997,S32,COMPRAS!$D$3:$D$4997,$X$2,COMPRAS!$B$3:$B$4997,">="&IF($C$4="",DATE(1900,1,1),$C$4),COMPRAS!$B$3:$B$4997,"<="&IF($F$4="",DATE(2999,12,31),$F$4)),0)) -> 1882.135
A33: 8 | B33: =IFERROR(INDEX($T$2:$T$231,MATCH(LARGE($U$2:$U$231,8),$U$2:$U$231,0)),"") -> CABALL/ SARDA/ VERDEL (MAC) | C33: =IFERROR(LARGE($U$2:$U$231,8),0) -> 3290.95 | E33: 8 | F33: =IFERROR(INDEX($T$2:$T$231,MATCH(LARGE($V$2:$V$231,8),$V$2:$V$231,0)),"") -> MERLUZA EUROPEA PINCHO COSTA 800 | G33: =IFERROR(LARGE($V$2:$V$231,8),0) -> 13944.356 | N33: =PROVEEDORES!A34 -> 50510 | O33: =PROVEEDORES!B34 -> PETACA CHICO S.L. | P33: =IF(N33<>"",SUMIFS(COMPRAS!$J$3:$J$4997,COMPRAS!$D$3:$D$4997,N33,COMPRAS!$B$3:$B$4997,">="&IF($C$4="",DATE(1900,1,1),$C$4),COMPRAS!$B$3:$B$4997,"<="&IF($F$4="",DATE(2999,12,31),$F$4)),0) -> 126.7 | Q33: =IF(N33<>"",SUMIFS(COMPRAS!$O$3:$O$4997,COMPRAS!$D$3:$D$4997,N33,COMPRAS!$B$3:$B$4997,">="&IF($C$4="",DATE(1900,1,1),$C$4),COMPRAS!$B$3:$B$4997,"<="&IF($F$4="",DATE(2999,12,31),$F$4)),0) -> 2416.09 | S33: =PRODUCTOS!A34 -> C730 | T33: =PRODUCTOS!B34 -> CALAMAR PATAGONICO (SQP) | U33: =IF(S33<>"",SUMIFS(COMPRAS!$J$3:$J$4997,COMPRAS!$G$3:$G$4997,S33,COMPRAS!$B$3:$B$4997,">="&IF($C$4="",DATE(1900,1,1),$C$4),COMPRAS!$B$3:$B$4997,"<="&IF($F$4="",DATE(2999,12,31),$F$4)),0) -> 0 | V33: =IF(S33<>"",SUMIFS(COMPRAS!$O$3:$O$4997,COMPRAS!$G$3:$G$4997,S33,COMPRAS!$B$3:$B$4997,">="&IF($C$4="",DATE(1900,1,1),$C$4),COMPRAS!$B$3:$B$4997,"<="&IF($F$4="",DATE(2999,12,31),$F$4)),0) -> 0 | Y33: =IF($X$2="TODOS",U33,IF(S33<>"",SUMIFS(COMPRAS!$J$3:$J$4997,COMPRAS!$G$3:$G$4997,S33,COMPRAS!$D$3:$D$4997,$X$2,COMPRAS!$B$3:$B$4997,">="&IF($C$4="",DATE(1900,1,1),$C$4),COMPRAS!$B$3:$B$4997,"<="&IF($F$4="",DATE(2999,12,31),$F$4)),0)) -> 0 | Z33: =IF($X$2="TODOS",V33,IF(S33<>"",SUMIFS(COMPRAS!$O$3:$O$4997,COMPRAS!$G$3:$G$4997,S33,COMPRAS!$D$3:$D$4997,$X$2,COMPRAS!$B$3:$B$4997,">="&IF($C$4="",DATE(1900,1,1),$C$4),COMPRAS!$B$3:$B$4997,"<="&IF($F$4="",DATE(2999,12,31),$F$4)),0)) -> 0
A34: 9 | B34: =IFERROR(INDEX($T$2:$T$231,MATCH(LARGE($U$2:$U$231,9),$U$2:$U$231,0)),"") -> MERLUZA EUROPEA PINCHO COSTA 800 | C34: =IFERROR(LARGE($U$2:$U$231,9),0) -> 2398.55 | E34: 9 | F34: =IFERROR(INDEX($T$2:$T$231,MATCH(LARGE($V$2:$V$231,9),$V$2:$V$231,0)),"") -> MERLUZA EUROPEA PINCHO COSTA | G34: =IFERROR(LARGE($V$2:$V$231,9),0) -> 13017.643 | N34: =PROVEEDORES!A35 -> 50511 | O34: =PROVEEDORES!B35 -> PESCADO JAMARDO S.L | P34: =IF(N34<>"",SUMIFS(COMPRAS!$J$3:$J$4997,COMPRAS!$D$3:$D$4997,N34,COMPRAS!$B$3:$B$4997,">="&IF($C$4="",DATE(1900,1,1),$C$4),COMPRAS!$B$3:$B$4997,"<="&IF($F$4="",DATE(2999,12,31),$F$4)),0) -> 0 | Q34: =IF(N34<>"",SUMIFS(COMPRAS!$O$3:$O$4997,COMPRAS!$D$3:$D$4997,N34,COMPRAS!$B$3:$B$4997,">="&IF($C$4="",DATE(1900,1,1),$C$4),COMPRAS!$B$3:$B$4997,"<="&IF($F$4="",DATE(2999,12,31),$F$4)),0) -> 0 | S34: =PRODUCTOS!A35 -> C720 | T34: =PRODUCTOS!B35 -> CALAMAR VETADO/ FORBES (SQF) | U34: =IF(S34<>"",SUMIFS(COMPRAS!$J$3:$J$4997,COMPRAS!$G$3:$G$4997,S34,COMPRAS!$B$3:$B$4997,">="&IF($C$4="",DATE(1900,1,1),$C$4),COMPRAS!$B$3:$B$4997,"<="&IF($F$4="",DATE(2999,12,31),$F$4)),0) -> 59.7 | V34: =IF(S34<>"",SUMIFS(COMPRAS!$O$3:$O$4997,COMPRAS!$G$3:$G$4997,S34,COMPRAS!$B$3:$B$4997,">="&IF($C$4="",DATE(1900,1,1),$C$4),COMPRAS!$B$3:$B$4997,"<="&IF($F$4="",DATE(2999,12,31),$F$4)),0) -> 1008.2 | Y34: =IF($X$2="TODOS",U34,IF(S34<>"",SUMIFS(COMPRAS!$J$3:$J$4997,COMPRAS!$G$3:$G$4997,S34,COMPRAS!$D$3:$D$4997,$X$2,COMPRAS!$B$3:$B$4997,">="&IF($C$4="",DATE(1900,1,1),$C$4),COMPRAS!$B$3:$B$4997,"<="&IF($F$4="",DATE(2999,12,31),$F$4)),0)) -> 59.7 | Z34: =IF($X$2="TODOS",V34,IF(S34<>"",SUMIFS(COMPRAS!$O$3:$O$4997,COMPRAS!$G$3:$G$4997,S34,COMPRAS!$D$3:$D$4997,$X$2,COMPRAS!$B$3:$B$4997,">="&IF($C$4="",DATE(1900,1,1),$C$4),COMPRAS!$B$3:$B$4997,"<="&IF($F$4="",DATE(2999,12,31),$F$4)),0)) -> 1008.2
A35: 10 | B35: =IFERROR(INDEX($T$2:$T$231,MATCH(LARGE($U$2:$U$231,10),$U$2:$U$231,0)),"") -> RAPE NEGRO (ANK) | C35: =IFERROR(LARGE($U$2:$U$231,10),0) -> 2166.3 | E35: 10 | F35: =IFERROR(INDEX($T$2:$T$231,MATCH(LARGE($V$2:$V$231,10),$V$2:$V$231,0)),"") -> CABALL/ SARDA/ VERDEL (MAC) | G35: =IFERROR(LARGE($V$2:$V$231,10),0) -> 12989.67 | N35: =PROVEEDORES!A36 -> 50512 | O35: =PROVEEDORES!B36 -> MAR IMPORT VENTA S.L. | P35: =IF(N35<>"",SUMIFS(COMPRAS!$J$3:$J$4997,COMPRAS!$D$3:$D$4997,N35,COMPRAS!$B$3:$B$4997,">="&IF($C$4="",DATE(1900,1,1),$C$4),COMPRAS!$B$3:$B$4997,"<="&IF($F$4="",DATE(2999,12,31),$F$4)),0) -> 0 | Q35: =IF(N35<>"",SUMIFS(COMPRAS!$O$3:$O$4997,COMPRAS!$D$3:$D$4997,N35,COMPRAS!$B$3:$B$4997,">="&IF($C$4="",DATE(1900,1,1),$C$4),COMPRAS!$B$3:$B$4997,"<="&IF($F$4="",DATE(2999,12,31),$F$4)),0) -> 0 | S35: =PRODUCTOS!A36 -> C823 | T35: =PRODUCTOS!B36 -> CENTOLLA/ CENTOLLO (SCR) | U35: =IF(S35<>"",SUMIFS(COMPRAS!$J$3:$J$4997,COMPRAS!$G$3:$G$4997,S35,COMPRAS!$B$3:$B$4997,">="&IF($C$4="",DATE(1900,1,1),$C$4),COMPRAS!$B$3:$B$4997,"<="&IF($F$4="",DATE(2999,12,31),$F$4)),0) -> 0 | V35: =IF(S35<>"",SUMIFS(COMPRAS!$O$3:$O$4997,COMPRAS!$G$3:$G$4997,S35,COMPRAS!$B$3:$B$4997,">="&IF($C$4="",DATE(1900,1,1),$C$4),COMPRAS!$B$3:$B$4997,"<="&IF($F$4="",DATE(2999,12,31),$F$4)),0) -> 0 | Y35: =IF($X$2="TODOS",U35,IF(S35<>"",SUMIFS(COMPRAS!$J$3:$J$4997,COMPRAS!$G$3:$G$4997,S35,COMPRAS!$D$3:$D$4997,$X$2,COMPRAS!$B$3:$B$4997,">="&IF($C$4="",DATE(1900,1,1),$C$4),COMPRAS!$B$3:$B$4997,"<="&IF($F$4="",DATE(2999,12,31),$F$4)),0)) -> 0 | Z35: =IF($X$2="TODOS",V35,IF(S35<>"",SUMIFS(COMPRAS!$O$3:$O$4997,COMPRAS!$G$3:$G$4997,S35,COMPRAS!$D$3:$D$4997,$X$2,COMPRAS!$B$3:$B$4997,">="&IF($C$4="",DATE(1900,1,1),$C$4),COMPRAS!$B$3:$B$4997,"<="&IF($F$4="",DATE(2999,12,31),$F$4)),0)) -> 0
A36: 11 | B36: =IFERROR(INDEX($T$2:$T$231,MATCH(LARGE($U$2:$U$231,11),$U$2:$U$231,0)),"") -> MERLUZA EUROPEA PINCHO COSTA | C36: =IFERROR(LARGE($U$2:$U$231,11),0) -> 2084.85 | E36: 11 | F36: =IFERROR(INDEX($T$2:$T$231,MATCH(LARGE($V$2:$V$231,11),$V$2:$V$231,0)),"") -> RAPE BLANCO DIA (MON) | G36: =IFERROR(LARGE($V$2:$V$231,11),0) -> 11377.292 | N36: =PROVEEDORES!A37 -> 50513 | O36: =PROVEEDORES!B37 -> SUBASTAS CEBREIRA S.L. | P36: =IF(N36<>"",SUMIFS(COMPRAS!$J$3:$J$4997,COMPRAS!$D$3:$D$4997,N36,COMPRAS!$B$3:$B$4997,">="&IF($C$4="",DATE(1900,1,1),$C$4),COMPRAS!$B$3:$B$4997,"<="&IF($F$4="",DATE(2999,12,31),$F$4)),0) -> 0 | Q36: =IF(N36<>"",SUMIFS(COMPRAS!$O$3:$O$4997,COMPRAS!$D$3:$D$4997,N36,COMPRAS!$B$3:$B$4997,">="&IF($C$4="",DATE(1900,1,1),$C$4),COMPRAS!$B$3:$B$4997,"<="&IF($F$4="",DATE(2999,12,31),$F$4)),0) -> 0 | S36: =PRODUCTOS!A37 -> C396 | T36: =PRODUCTOS!B37 -> CHICHARRO/ JUREL/ XURELO (HOM) | U36: =IF(S36<>"",SUMIFS(COMPRAS!$J$3:$J$4997,COMPRAS!$G$3:$G$4997,S36,COMPRAS!$B$3:$B$4997,">="&IF($C$4="",DATE(1900,1,1),$C$4),COMPRAS!$B$3:$B$4997,"<="&IF($F$4="",DATE(2999,12,31),$F$4)),0) -> 728.1 | V36: =IF(S36<>"",SUMIFS(COMPRAS!$O$3:$O$4997,COMPRAS!$G$3:$G$4997,S36,COMPRAS!$B$3:$B$4997,">="&IF($C$4="",DATE(1900,1,1),$C$4),COMPRAS!$B$3:$B$4997,"<="&IF($F$4="",DATE(2999,12,31),$F$4)),0) -> 1233.6198 | Y36: =IF($X$2="TODOS",U36,IF(S36<>"",SUMIFS(COMPRAS!$J$3:$J$4997,COMPRAS!$G$3:$G$4997,S36,COMPRAS!$D$3:$D$4997,$X$2,COMPRAS!$B$3:$B$4997,">="&IF($C$4="",DATE(1900,1,1),$C$4),COMPRAS!$B$3:$B$4997,"<="&IF($F$4="",DATE(2999,12,31),$F$4)),0)) -> 728.1 | Z36: =IF($X$2="TODOS",V36,IF(S36<>"",SUMIFS(COMPRAS!$O$3:$O$4997,COMPRAS!$G$3:$G$4997,S36,COMPRAS!$D$3:$D$4997,$X$2,COMPRAS!$B$3:$B$4997,">="&IF($C$4="",DATE(1900,1,1),$C$4),COMPRAS!$B$3:$B$4997,"<="&IF($F$4="",DATE(2999,12,31),$F$4)),0)) -> 1233.6198
A37: 12 | B37: =IFERROR(INDEX($T$2:$T$231,MATCH(LARGE($U$2:$U$231,12),$U$2:$U$231,0)),"") -> CONGRIO 10+ (COE) | C37: =IFERROR(LARGE($U$2:$U$231,12),0) -> 1969 | E37: 12 | F37: =IFERROR(INDEX($T$2:$T$231,MATCH(LARGE($V$2:$V$231,12),$V$2:$V$231,0)),"") -> MERLUZA EUROPEA ARRASTRE (HKE) | G37: =IFERROR(LARGE($V$2:$V$231,12),0) -> 11270.299 | N37: =PROVEEDORES!A38 -> 50514 | O37: =PROVEEDORES!B38 -> PESCADO Y MARISCOS ADELAIDA S.L. | P37: =IF(N37<>"",SUMIFS(COMPRAS!$J$3:$J$4997,COMPRAS!$D$3:$D$4997,N37,COMPRAS!$B$3:$B$4997,">="&IF($C$4="",DATE(1900,1,1),$C$4),COMPRAS!$B$3:$B$4997,"<="&IF($F$4="",DATE(2999,12,31),$F$4)),0) -> 937.74 | Q37: =IF(N37<>"",SUMIFS(COMPRAS!$O$3:$O$4997,COMPRAS!$D$3:$D$4997,N37,COMPRAS!$B$3:$B$4997,">="&IF($C$4="",DATE(1900,1,1),$C$4),COMPRAS!$B$3:$B$4997,"<="&IF($F$4="",DATE(2999,12,31),$F$4)),0) -> 5474.4725 | S37: =PRODUCTOS!A38 -> C4301 | T37: =PRODUCTOS!B38 -> CHOPAS (BRB) | U37: =IF(S37<>"",SUMIFS(COMPRAS!$J$3:$J$4997,COMPRAS!$G$3:$G$4997,S37,COMPRAS!$B$3:$B$4997,">="&IF($C$4="",DATE(1900,1,1),$C$4),COMPRAS!$B$3:$B$4997,"<="&IF($F$4="",DATE(2999,12,31),$F$4)),0) -> 0 | V37: =IF(S37<>"",SUMIFS(COMPRAS!$O$3:$O$4997,COMPRAS!$G$3:$G$4997,S37,COMPRAS!$B$3:$B$4997,">="&IF($C$4="",DATE(1900,1,1),$C$4),COMPRAS!$B$3:$B$4997,"<="&IF($F$4="",DATE(2999,12,31),$F$4)),0) -> 0 | Y37: =IF($X$2="TODOS",U37,IF(S37<>"",SUMIFS(COMPRAS!$J$3:$J$4997,COMPRAS!$G$3:$G$4997,S37,COMPRAS!$D$3:$D$4997,$X$2,COMPRAS!$B$3:$B$4997,">="&IF($C$4="",DATE(1900,1,1),$C$4),COMPRAS!$B$3:$B$4997,"<="&IF($F$4="",DATE(2999,12,31),$F$4)),0)) -> 0 | Z37: =IF($X$2="TODOS",V37,IF(S37<>"",SUMIFS(COMPRAS!$O$3:$O$4997,COMPRAS!$G$3:$G$4997,S37,COMPRAS!$D$3:$D$4997,$X$2,COMPRAS!$B$3:$B$4997,">="&IF($C$4="",DATE(1900,1,1),$C$4),COMPRAS!$B$3:$B$4997,"<="&IF($F$4="",DATE(2999,12,31),$F$4)),0)) -> 0
A38: 13 | B38: =IFERROR(INDEX($T$2:$T$231,MATCH(LARGE($U$2:$U$231,13),$U$2:$U$231,0)),"") -> RAYA SPP (SKA) | C38: =IFERROR(LARGE($U$2:$U$231,13),0) -> 1919.75 | E38: 13 | F38: =IFERROR(INDEX($T$2:$T$231,MATCH(LARGE($V$2:$V$231,13),$V$2:$V$231,0)),"") -> BESUGO (BSR) | G38: =IFERROR(LARGE($V$2:$V$231,13),0) -> 11163.798 | N38: =PROVEEDORES!A39 -> 50515 | O38: =PROVEEDORES!B39 -> PESCADOS CHEMAER S.L. | P38: =IF(N38<>"",SUMIFS(COMPRAS!$J$3:$J$4997,COMPRAS!$D$3:$D$4997,N38,COMPRAS!$B$3:$B$4997,">="&IF($C$4="",DATE(1900,1,1),$C$4),COMPRAS!$B$3:$B$4997,"<="&IF($F$4="",DATE(2999,12,31),$F$4)),0) -> 0 | Q38: =IF(N38<>"",SUMIFS(COMPRAS!$O$3:$O$4997,COMPRAS!$D$3:$D$4997,N38,COMPRAS!$B$3:$B$4997,">="&IF($C$4="",DATE(1900,1,1),$C$4),COMPRAS!$B$3:$B$4997,"<="&IF($F$4="",DATE(2999,12,31),$F$4)),0) -> 0 | S38: =PRODUCTOS!A39 -> C2008 | T38: =PRODUCTOS!B39 -> CIGALAS EN COLAS | U38: =IF(S38<>"",SUMIFS(COMPRAS!$J$3:$J$4997,COMPRAS!$G$3:$G$4997,S38,COMPRAS!$B$3:$B$4997,">="&IF($C$4="",DATE(1900,1,1),$C$4),COMPRAS!$B$3:$B$4997,"<="&IF($F$4="",DATE(2999,12,31),$F$4)),0) -> 0 | V38: =IF(S38<>"",SUMIFS(COMPRAS!$O$3:$O$4997,COMPRAS!$G$3:$G$4997,S38,COMPRAS!$B$3:$B$4997,">="&IF($C$4="",DATE(1900,1,1),$C$4),COMPRAS!$B$3:$B$4997,"<="&IF($F$4="",DATE(2999,12,31),$F$4)),0) -> 0 | Y38: =IF($X$2="TODOS",U38,IF(S38<>"",SUMIFS(COMPRAS!$J$3:$J$4997,COMPRAS!$G$3:$G$4997,S38,COMPRAS!$D$3:$D$4997,$X$2,COMPRAS!$B$3:$B$4997,">="&IF($C$4="",DATE(1900,1,1),$C$4),COMPRAS!$B$3:$B$4997,"<="&IF($F$4="",DATE(2999,12,31),$F$4)),0)) -> 0 | Z38: =IF($X$2="TODOS",V38,IF(S38<>"",SUMIFS(COMPRAS!$O$3:$O$4997,COMPRAS!$G$3:$G$4997,S38,COMPRAS!$D$3:$D$4997,$X$2,COMPRAS!$B$3:$B$4997,">="&IF($C$4="",DATE(1900,1,1),$C$4),COMPRAS!$B$3:$B$4997,"<="&IF($F$4="",DATE(2999,12,31),$F$4)),0)) -> 0
A39: 14 | B39: =IFERROR(INDEX($T$2:$T$231,MATCH(LARGE($U$2:$U$231,14),$U$2:$U$231,0)),"") -> MERLUZA EUROPEA VOLANTA ALTURA | C39: =IFERROR(LARGE($U$2:$U$231,14),0) -> 1914.5 | E39: 14 | F39: =IFERROR(INDEX($T$2:$T$231,MATCH(LARGE($V$2:$V$231,14),$V$2:$V$231,0)),"") -> SAN MARTIÑOS/ SAN PEDROS (JOD) | G39: =IFERROR(LARGE($V$2:$V$231,14),0) -> 10363.49 | N39: =PROVEEDORES!A40 -> 50516 | O39: =PROVEEDORES!B40 -> PESLEIRAS S.L. | P39: =IF(N39<>"",SUMIFS(COMPRAS!$J$3:$J$4997,COMPRAS!$D$3:$D$4997,N39,COMPRAS!$B$3:$B$4997,">="&IF($C$4="",DATE(1900,1,1),$C$4),COMPRAS!$B$3:$B$4997,"<="&IF($F$4="",DATE(2999,12,31),$F$4)),0) -> 0 | Q39: =IF(N39<>"",SUMIFS(COMPRAS!$O$3:$O$4997,COMPRAS!$D$3:$D$4997,N39,COMPRAS!$B$3:$B$4997,">="&IF($C$4="",DATE(1900,1,1),$C$4),COMPRAS!$B$3:$B$4997,"<="&IF($F$4="",DATE(2999,12,31),$F$4)),0) -> 0 | S39: =PRODUCTOS!A40 -> C2101 | T39: =PRODUCTOS!B40 -> CIGALA "1" (NEP) | U39: =IF(S39<>"",SUMIFS(COMPRAS!$J$3:$J$4997,COMPRAS!$G$3:$G$4997,S39,COMPRAS!$B$3:$B$4997,">="&IF($C$4="",DATE(1900,1,1),$C$4),COMPRAS!$B$3:$B$4997,"<="&IF($F$4="",DATE(2999,12,31),$F$4)),0) -> 0 | V39: =IF(S39<>"",SUMIFS(COMPRAS!$O$3:$O$4997,COMPRAS!$G$3:$G$4997,S39,COMPRAS!$B$3:$B$4997,">="&IF($C$4="",DATE(1900,1,1),$C$4),COMPRAS!$B$3:$B$4997,"<="&IF($F$4="",DATE(2999,12,31),$F$4)),0) -> 0 | Y39: =IF($X$2="TODOS",U39,IF(S39<>"",SUMIFS(COMPRAS!$J$3:$J$4997,COMPRAS!$G$3:$G$4997,S39,COMPRAS!$D$3:$D$4997,$X$2,COMPRAS!$B$3:$B$4997,">="&IF($C$4="",DATE(1900,1,1),$C$4),COMPRAS!$B$3:$B$4997,"<="&IF($F$4="",DATE(2999,12,31),$F$4)),0)) -> 0 | Z39: =IF($X$2="TODOS",V39,IF(S39<>"",SUMIFS(COMPRAS!$O$3:$O$4997,COMPRAS!$G$3:$G$4997,S39,COMPRAS!$D$3:$D$4997,$X$2,COMPRAS!$B$3:$B$4997,">="&IF($C$4="",DATE(1900,1,1),$C$4),COMPRAS!$B$3:$B$4997,"<="&IF($F$4="",DATE(2999,12,31),$F$4)),0)) -> 0
A40: 15 | B40: =IFERROR(INDEX($T$2:$T$231,MATCH(LARGE($U$2:$U$231,15),$U$2:$U$231,0)),"") -> RAPE BLANCO DIA (MON) | C40: =IFERROR(LARGE($U$2:$U$231,15),0) -> 1902.75 | E40: 15 | F40: =IFERROR(INDEX($T$2:$T$231,MATCH(LARGE($V$2:$V$231,15),$V$2:$V$231,0)),"") -> RAPE NEGRO (ANK) | G40: =IFERROR(LARGE($V$2:$V$231,15),0) -> 10128.467 | N40: =PROVEEDORES!A41 -> 50517 | O40: =PROVEEDORES!B41 -> VELOMAR S.L. | P40: =IF(N40<>"",SUMIFS(COMPRAS!$J$3:$J$4997,COMPRAS!$D$3:$D$4997,N40,COMPRAS!$B$3:$B$4997,">="&IF($C$4="",DATE(1900,1,1),$C$4),COMPRAS!$B$3:$B$4997,"<="&IF($F$4="",DATE(2999,12,31),$F$4)),0) -> 0 | Q40: =IF(N40<>"",SUMIFS(COMPRAS!$O$3:$O$4997,COMPRAS!$D$3:$D$4997,N40,COMPRAS!$B$3:$B$4997,">="&IF($C$4="",DATE(1900,1,1),$C$4),COMPRAS!$B$3:$B$4997,"<="&IF($F$4="",DATE(2999,12,31),$F$4)),0) -> 0 | S40: =PRODUCTOS!A41 -> C2004 | T40: =PRODUCTOS!B41 -> CIGALA "2" (NEP) | U40: =IF(S40<>"",SUMIFS(COMPRAS!$J$3:$J$4997,COMPRAS!$G$3:$G$4997,S40,COMPRAS!$B$3:$B$4997,">="&IF($C$4="",DATE(1900,1,1),$C$4),COMPRAS!$B$3:$B$4997,"<="&IF($F$4="",DATE(2999,12,31),$F$4)),0) -> 0 | V40: =IF(S40<>"",SUMIFS(COMPRAS!$O$3:$O$4997,COMPRAS!$G$3:$G$4997,S40,COMPRAS!$B$3:$B$4997,">="&IF($C$4="",DATE(1900,1,1),$C$4),COMPRAS!$B$3:$B$4997,"<="&IF($F$4="",DATE(2999,12,31),$F$4)),0) -> 0 | Y40: =IF($X$2="TODOS",U40,IF(S40<>"",SUMIFS(COMPRAS!$J$3:$J$4997,COMPRAS!$G$3:$G$4997,S40,COMPRAS!$D$3:$D$4997,$X$2,COMPRAS!$B$3:$B$4997,">="&IF($C$4="",DATE(1900,1,1),$C$4),COMPRAS!$B$3:$B$4997,"<="&IF($F$4="",DATE(2999,12,31),$F$4)),0)) -> 0 | Z40: =IF($X$2="TODOS",V40,IF(S40<>"",SUMIFS(COMPRAS!$O$3:$O$4997,COMPRAS!$G$3:$G$4997,S40,COMPRAS!$D$3:$D$4997,$X$2,COMPRAS!$B$3:$B$4997,">="&IF($C$4="",DATE(1900,1,1),$C$4),COMPRAS!$B$3:$B$4997,"<="&IF($F$4="",DATE(2999,12,31),$F$4)),0)) -> 0
N41: =PROVEEDORES!A42 -> 50518 | O41: =PROVEEDORES!B42 -> NOVOMA DE CELEIRO S.L | P41: =IF(N41<>"",SUMIFS(COMPRAS!$J$3:$J$4997,COMPRAS!$D$3:$D$4997,N41,COMPRAS!$B$3:$B$4997,">="&IF($C$4="",DATE(1900,1,1),$C$4),COMPRAS!$B$3:$B$4997,"<="&IF($F$4="",DATE(2999,12,31),$F$4)),0) -> 0 | Q41: =IF(N41<>"",SUMIFS(COMPRAS!$O$3:$O$4997,COMPRAS!$D$3:$D$4997,N41,COMPRAS!$B$3:$B$4997,">="&IF($C$4="",DATE(1900,1,1),$C$4),COMPRAS!$B$3:$B$4997,"<="&IF($F$4="",DATE(2999,12,31),$F$4)),0) -> 0 | S41: =PRODUCTOS!A42 -> C2104 | T41: =PRODUCTOS!B42 -> CIGALA "3P" (NEP) | U41: =IF(S41<>"",SUMIFS(COMPRAS!$J$3:$J$4997,COMPRAS!$G$3:$G$4997,S41,COMPRAS!$B$3:$B$4997,">="&IF($C$4="",DATE(1900,1,1),$C$4),COMPRAS!$B$3:$B$4997,"<="&IF($F$4="",DATE(2999,12,31),$F$4)),0) -> 48 | V41: =IF(S41<>"",SUMIFS(COMPRAS!$O$3:$O$4997,COMPRAS!$G$3:$G$4997,S41,COMPRAS!$B$3:$B$4997,">="&IF($C$4="",DATE(1900,1,1),$C$4),COMPRAS!$B$3:$B$4997,"<="&IF($F$4="",DATE(2999,12,31),$F$4)),0) -> 840 | Y41: =IF($X$2="TODOS",U41,IF(S41<>"",SUMIFS(COMPRAS!$J$3:$J$4997,COMPRAS!$G$3:$G$4997,S41,COMPRAS!$D$3:$D$4997,$X$2,COMPRAS!$B$3:$B$4997,">="&IF($C$4="",DATE(1900,1,1),$C$4),COMPRAS!$B$3:$B$4997,"<="&IF($F$4="",DATE(2999,12,31),$F$4)),0)) -> 48 | Z41: =IF($X$2="TODOS",V41,IF(S41<>"",SUMIFS(COMPRAS!$O$3:$O$4997,COMPRAS!$G$3:$G$4997,S41,COMPRAS!$D$3:$D$4997,$X$2,COMPRAS!$B$3:$B$4997,">="&IF($C$4="",DATE(1900,1,1),$C$4),COMPRAS!$B$3:$B$4997,"<="&IF($F$4="",DATE(2999,12,31),$F$4)),0)) -> 840
N42: =PROVEEDORES!A43 -> 50519 | O42: =PROVEEDORES!B43 -> SANTIAGO MONTENEGRO CAMPOS S.L. | P42: =IF(N42<>"",SUMIFS(COMPRAS!$J$3:$J$4997,COMPRAS!$D$3:$D$4997,N42,COMPRAS!$B$3:$B$4997,">="&IF($C$4="",DATE(1900,1,1),$C$4),COMPRAS!$B$3:$B$4997,"<="&IF($F$4="",DATE(2999,12,31),$F$4)),0) -> 0 | Q42: =IF(N42<>"",SUMIFS(COMPRAS!$O$3:$O$4997,COMPRAS!$D$3:$D$4997,N42,COMPRAS!$B$3:$B$4997,">="&IF($C$4="",DATE(1900,1,1),$C$4),COMPRAS!$B$3:$B$4997,"<="&IF($F$4="",DATE(2999,12,31),$F$4)),0) -> 0 | S42: =PRODUCTOS!A43 -> C2105 | T42: =PRODUCTOS!B43 -> CIGALA "3X" (NEP) | U42: =IF(S42<>"",SUMIFS(COMPRAS!$J$3:$J$4997,COMPRAS!$G$3:$G$4997,S42,COMPRAS!$B$3:$B$4997,">="&IF($C$4="",DATE(1900,1,1),$C$4),COMPRAS!$B$3:$B$4997,"<="&IF($F$4="",DATE(2999,12,31),$F$4)),0) -> 0 | V42: =IF(S42<>"",SUMIFS(COMPRAS!$O$3:$O$4997,COMPRAS!$G$3:$G$4997,S42,COMPRAS!$B$3:$B$4997,">="&IF($C$4="",DATE(1900,1,1),$C$4),COMPRAS!$B$3:$B$4997,"<="&IF($F$4="",DATE(2999,12,31),$F$4)),0) -> 0 | Y42: =IF($X$2="TODOS",U42,IF(S42<>"",SUMIFS(COMPRAS!$J$3:$J$4997,COMPRAS!$G$3:$G$4997,S42,COMPRAS!$D$3:$D$4997,$X$2,COMPRAS!$B$3:$B$4997,">="&IF($C$4="",DATE(1900,1,1),$C$4),COMPRAS!$B$3:$B$4997,"<="&IF($F$4="",DATE(2999,12,31),$F$4)),0)) -> 0 | Z42: =IF($X$2="TODOS",V42,IF(S42<>"",SUMIFS(COMPRAS!$O$3:$O$4997,COMPRAS!$G$3:$G$4997,S42,COMPRAS!$D$3:$D$4997,$X$2,COMPRAS!$B$3:$B$4997,">="&IF($C$4="",DATE(1900,1,1),$C$4),COMPRAS!$B$3:$B$4997,"<="&IF($F$4="",DATE(2999,12,31),$F$4)),0)) -> 0
A43: QUE LE COMPRAMOS A CADA PROVEEDOR | N43: =PROVEEDORES!A44 -> 50520 | O43: =PROVEEDORES!B44 -> GRUPO ENVIMAR NW S.L. | P43: =IF(N43<>"",SUMIFS(COMPRAS!$J$3:$J$4997,COMPRAS!$D$3:$D$4997,N43,COMPRAS!$B$3:$B$4997,">="&IF($C$4="",DATE(1900,1,1),$C$4),COMPRAS!$B$3:$B$4997,"<="&IF($F$4="",DATE(2999,12,31),$F$4)),0) -> 0 | Q43: =IF(N43<>"",SUMIFS(COMPRAS!$O$3:$O$4997,COMPRAS!$D$3:$D$4997,N43,COMPRAS!$B$3:$B$4997,">="&IF($C$4="",DATE(1900,1,1),$C$4),COMPRAS!$B$3:$B$4997,"<="&IF($F$4="",DATE(2999,12,31),$F$4)),0) -> 0 | S43: =PRODUCTOS!A44 -> C2103 | T43: =PRODUCTOS!B44 -> CIGALA "3" (NEP) | U43: =IF(S43<>"",SUMIFS(COMPRAS!$J$3:$J$4997,COMPRAS!$G$3:$G$4997,S43,COMPRAS!$B$3:$B$4997,">="&IF($C$4="",DATE(1900,1,1),$C$4),COMPRAS!$B$3:$B$4997,"<="&IF($F$4="",DATE(2999,12,31),$F$4)),0) -> 20 | V43: =IF(S43<>"",SUMIFS(COMPRAS!$O$3:$O$4997,COMPRAS!$G$3:$G$4997,S43,COMPRAS!$B$3:$B$4997,">="&IF($C$4="",DATE(1900,1,1),$C$4),COMPRAS!$B$3:$B$4997,"<="&IF($F$4="",DATE(2999,12,31),$F$4)),0) -> 360 | Y43: =IF($X$2="TODOS",U43,IF(S43<>"",SUMIFS(COMPRAS!$J$3:$J$4997,COMPRAS!$G$3:$G$4997,S43,COMPRAS!$D$3:$D$4997,$X$2,COMPRAS!$B$3:$B$4997,">="&IF($C$4="",DATE(1900,1,1),$C$4),COMPRAS!$B$3:$B$4997,"<="&IF($F$4="",DATE(2999,12,31),$F$4)),0)) -> 20 | Z43: =IF($X$2="TODOS",V43,IF(S43<>"",SUMIFS(COMPRAS!$O$3:$O$4997,COMPRAS!$G$3:$G$4997,S43,COMPRAS!$D$3:$D$4997,$X$2,COMPRAS!$B$3:$B$4997,">="&IF($C$4="",DATE(1900,1,1),$C$4),COMPRAS!$B$3:$B$4997,"<="&IF($F$4="",DATE(2999,12,31),$F$4)),0)) -> 360
N44: =PROVEEDORES!A45 -> 50521 | O44: =PROVEEDORES!B45 -> SUBASTAS DE ATLANTICO S.L | P44: =IF(N44<>"",SUMIFS(COMPRAS!$J$3:$J$4997,COMPRAS!$D$3:$D$4997,N44,COMPRAS!$B$3:$B$4997,">="&IF($C$4="",DATE(1900,1,1),$C$4),COMPRAS!$B$3:$B$4997,"<="&IF($F$4="",DATE(2999,12,31),$F$4)),0) -> 9861.3 | Q44: =IF(N44<>"",SUMIFS(COMPRAS!$O$3:$O$4997,COMPRAS!$D$3:$D$4997,N44,COMPRAS!$B$3:$B$4997,">="&IF($C$4="",DATE(1900,1,1),$C$4),COMPRAS!$B$3:$B$4997,"<="&IF($F$4="",DATE(2999,12,31),$F$4)),0) -> 24987.662 | S44: =PRODUCTOS!A45 -> C2100 | T44: =PRODUCTOS!B45 -> CIGALA "0" (NEP) | U44: =IF(S44<>"",SUMIFS(COMPRAS!$J$3:$J$4997,COMPRAS!$G$3:$G$4997,S44,COMPRAS!$B$3:$B$4997,">="&IF($C$4="",DATE(1900,1,1),$C$4),COMPRAS!$B$3:$B$4997,"<="&IF($F$4="",DATE(2999,12,31),$F$4)),0) -> 0 | V44: =IF(S44<>"",SUMIFS(COMPRAS!$O$3:$O$4997,COMPRAS!$G$3:$G$4997,S44,COMPRAS!$B$3:$B$4997,">="&IF($C$4="",DATE(1900,1,1),$C$4),COMPRAS!$B$3:$B$4997,"<="&IF($F$4="",DATE(2999,12,31),$F$4)),0) -> 0 | Y44: =IF($X$2="TODOS",U44,IF(S44<>"",SUMIFS(COMPRAS!$J$3:$J$4997,COMPRAS!$G$3:$G$4997,S44,COMPRAS!$D$3:$D$4997,$X$2,COMPRAS!$B$3:$B$4997,">="&IF($C$4="",DATE(1900,1,1),$C$4),COMPRAS!$B$3:$B$4997,"<="&IF($F$4="",DATE(2999,12,31),$F$4)),0)) -> 0 | Z44: =IF($X$2="TODOS",V44,IF(S44<>"",SUMIFS(COMPRAS!$O$3:$O$4997,COMPRAS!$G$3:$G$4997,S44,COMPRAS!$D$3:$D$4997,$X$2,COMPRAS!$B$3:$B$4997,">="&IF($C$4="",DATE(1900,1,1),$C$4),COMPRAS!$B$3:$B$4997,"<="&IF($F$4="",DATE(2999,12,31),$F$4)),0)) -> 0
A45: Elige un proveedor: | B45: -- TODOS LOS PROVEEDORES -- | N45: =PROVEEDORES!A46 -> 50525 | O45: =PROVEEDORES!B46 -> FURIC MAREE | P45: =IF(N45<>"",SUMIFS(COMPRAS!$J$3:$J$4997,COMPRAS!$D$3:$D$4997,N45,COMPRAS!$B$3:$B$4997,">="&IF($C$4="",DATE(1900,1,1),$C$4),COMPRAS!$B$3:$B$4997,"<="&IF($F$4="",DATE(2999,12,31),$F$4)),0) -> 649.4 | Q45: =IF(N45<>"",SUMIFS(COMPRAS!$O$3:$O$4997,COMPRAS!$D$3:$D$4997,N45,COMPRAS!$B$3:$B$4997,">="&IF($C$4="",DATE(1900,1,1),$C$4),COMPRAS!$B$3:$B$4997,"<="&IF($F$4="",DATE(2999,12,31),$F$4)),0) -> 14000.16 | S45: =PRODUCTOS!A46 -> C410 | T45: =PRODUCTOS!B46 -> CINTAS/ PEZ CINTA (CBC) | U45: =IF(S45<>"",SUMIFS(COMPRAS!$J$3:$J$4997,COMPRAS!$G$3:$G$4997,S45,COMPRAS!$B$3:$B$4997,">="&IF($C$4="",DATE(1900,1,1),$C$4),COMPRAS!$B$3:$B$4997,"<="&IF($F$4="",DATE(2999,12,31),$F$4)),0) -> 595.85 | V45: =IF(S45<>"",SUMIFS(COMPRAS!$O$3:$O$4997,COMPRAS!$G$3:$G$4997,S45,COMPRAS!$B$3:$B$4997,">="&IF($C$4="",DATE(1900,1,1),$C$4),COMPRAS!$B$3:$B$4997,"<="&IF($F$4="",DATE(2999,12,31),$F$4)),0) -> 1436.7242 | Y45: =IF($X$2="TODOS",U45,IF(S45<>"",SUMIFS(COMPRAS!$J$3:$J$4997,COMPRAS!$G$3:$G$4997,S45,COMPRAS!$D$3:$D$4997,$X$2,COMPRAS!$B$3:$B$4997,">="&IF($C$4="",DATE(1900,1,1),$C$4),COMPRAS!$B$3:$B$4997,"<="&IF($F$4="",DATE(2999,12,31),$F$4)),0)) -> 595.85 | Z45: =IF($X$2="TODOS",V45,IF(S45<>"",SUMIFS(COMPRAS!$O$3:$O$4997,COMPRAS!$G$3:$G$4997,S45,COMPRAS!$D$3:$D$4997,$X$2,COMPRAS!$B$3:$B$4997,">="&IF($C$4="",DATE(1900,1,1),$C$4),COMPRAS!$B$3:$B$4997,"<="&IF($F$4="",DATE(2999,12,31),$F$4)),0)) -> 1436.7242
A46: Y tambien un articulo (opcional): | B46: -- TODOS LOS ARTICULOS -- | F46: (vacio = todos los articulos de ese proveedor) | N46: =PROVEEDORES!A47 -> 50523 | O46: =PROVEEDORES!B47 -> URK-EXPORT B.V | P46: =IF(N46<>"",SUMIFS(COMPRAS!$J$3:$J$4997,COMPRAS!$D$3:$D$4997,N46,COMPRAS!$B$3:$B$4997,">="&IF($C$4="",DATE(1900,1,1),$C$4),COMPRAS!$B$3:$B$4997,"<="&IF($F$4="",DATE(2999,12,31),$F$4)),0) -> 0 | Q46: =IF(N46<>"",SUMIFS(COMPRAS!$O$3:$O$4997,COMPRAS!$D$3:$D$4997,N46,COMPRAS!$B$3:$B$4997,">="&IF($C$4="",DATE(1900,1,1),$C$4),COMPRAS!$B$3:$B$4997,"<="&IF($F$4="",DATE(2999,12,31),$F$4)),0) -> 0 | S46: =PRODUCTOS!A47 -> C250 | T46: =PRODUCTOS!B47 -> CONGRIO 10+ (COE) | U46: =IF(S46<>"",SUMIFS(COMPRAS!$J$3:$J$4997,COMPRAS!$G$3:$G$4997,S46,COMPRAS!$B$3:$B$4997,">="&IF($C$4="",DATE(1900,1,1),$C$4),COMPRAS!$B$3:$B$4997,"<="&IF($F$4="",DATE(2999,12,31),$F$4)),0) -> 1969 | V46: =IF(S46<>"",SUMIFS(COMPRAS!$O$3:$O$4997,COMPRAS!$G$3:$G$4997,S46,COMPRAS!$B$3:$B$4997,">="&IF($C$4="",DATE(1900,1,1),$C$4),COMPRAS!$B$3:$B$4997,"<="&IF($F$4="",DATE(2999,12,31),$F$4)),0) -> 7145.9182 | Y46: =IF($X$2="TODOS",U46,IF(S46<>"",SUMIFS(COMPRAS!$J$3:$J$4997,COMPRAS!$G$3:$G$4997,S46,COMPRAS!$D$3:$D$4997,$X$2,COMPRAS!$B$3:$B$4997,">="&IF($C$4="",DATE(1900,1,1),$C$4),COMPRAS!$B$3:$B$4997,"<="&IF($F$4="",DATE(2999,12,31),$F$4)),0)) -> 1969 | Z46: =IF($X$2="TODOS",V46,IF(S46<>"",SUMIFS(COMPRAS!$O$3:$O$4997,COMPRAS!$G$3:$G$4997,S46,COMPRAS!$D$3:$D$4997,$X$2,COMPRAS!$B$3:$B$4997,">="&IF($C$4="",DATE(1900,1,1),$C$4),COMPRAS!$B$3:$B$4997,"<="&IF($F$4="",DATE(2999,12,31),$F$4)),0)) -> 7145.9182
A47: TOP 10 PRODUCTOS COMPRADOS A ESTE PROVEEDOR | N47: =PROVEEDORES!A48 -> 50522 | O47: =PROVEEDORES!B48 -> CENOR QUEIJO CORUÑA | P47: =IF(N47<>"",SUMIFS(COMPRAS!$J$3:$J$4997,COMPRAS!$D$3:$D$4997,N47,COMPRAS!$B$3:$B$4997,">="&IF($C$4="",DATE(1900,1,1),$C$4),COMPRAS!$B$3:$B$4997,"<="&IF($F$4="",DATE(2999,12,31),$F$4)),0) -> 0 | Q47: =IF(N47<>"",SUMIFS(COMPRAS!$O$3:$O$4997,COMPRAS!$D$3:$D$4997,N47,COMPRAS!$B$3:$B$4997,">="&IF($C$4="",DATE(1900,1,1),$C$4),COMPRAS!$B$3:$B$4997,"<="&IF($F$4="",DATE(2999,12,31),$F$4)),0) -> 0 | S47: =PRODUCTOS!A48 -> C2507 | T47: =PRODUCTOS!B48 -> CONGRIO 7/10 (COE) | U47: =IF(S47<>"",SUMIFS(COMPRAS!$J$3:$J$4997,COMPRAS!$G$3:$G$4997,S47,COMPRAS!$B$3:$B$4997,">="&IF($C$4="",DATE(1900,1,1),$C$4),COMPRAS!$B$3:$B$4997,"<="&IF($F$4="",DATE(2999,12,31),$F$4)),0) -> 72.5 | V47: =IF(S47<>"",SUMIFS(COMPRAS!$O$3:$O$4997,COMPRAS!$G$3:$G$4997,S47,COMPRAS!$B$3:$B$4997,">="&IF($C$4="",DATE(1900,1,1),$C$4),COMPRAS!$B$3:$B$4997,"<="&IF($F$4="",DATE(2999,12,31),$F$4)),0) -> 198.45375 | Y47: =IF($X$2="TODOS",U47,IF(S47<>"",SUMIFS(COMPRAS!$J$3:$J$4997,COMPRAS!$G$3:$G$4997,S47,COMPRAS!$D$3:$D$4997,$X$2,COMPRAS!$B$3:$B$4997,">="&IF($C$4="",DATE(1900,1,1),$C$4),COMPRAS!$B$3:$B$4997,"<="&IF($F$4="",DATE(2999,12,31),$F$4)),0)) -> 72.5 | Z47: =IF($X$2="TODOS",V47,IF(S47<>"",SUMIFS(COMPRAS!$O$3:$O$4997,COMPRAS!$G$3:$G$4997,S47,COMPRAS!$D$3:$D$4997,$X$2,COMPRAS!$B$3:$B$4997,">="&IF($C$4="",DATE(1900,1,1),$C$4),COMPRAS!$B$3:$B$4997,"<="&IF($F$4="",DATE(2999,12,31),$F$4)),0)) -> 198.45375
A48: # | B48: Producto | C48: Kilos | D48: Importe | N48: =PROVEEDORES!A49 -> 50531 | O48: =PROVEEDORES!B49 -> SANCHEZ LOPEZ MIGUEL | P48: =IF(N48<>"",SUMIFS(COMPRAS!$J$3:$J$4997,COMPRAS!$D$3:$D$4997,N48,COMPRAS!$B$3:$B$4997,">="&IF($C$4="",DATE(1900,1,1),$C$4),COMPRAS!$B$3:$B$4997,"<="&IF($F$4="",DATE(2999,12,31),$F$4)),0) -> 386 | Q48: =IF(N48<>"",SUMIFS(COMPRAS!$O$3:$O$4997,COMPRAS!$D$3:$D$4997,N48,COMPRAS!$B$3:$B$4997,">="&IF($C$4="",DATE(1900,1,1),$C$4),COMPRAS!$B$3:$B$4997,"<="&IF($F$4="",DATE(2999,12,31),$F$4)),0) -> 1288.6 | S48: =PRODUCTOS!A49 -> C2505 | T48: =PRODUCTOS!B49 -> CONGRIO 5/07 (COE) | U48: =IF(S48<>"",SUMIFS(COMPRAS!$J$3:$J$4997,COMPRAS!$G$3:$G$4997,S48,COMPRAS!$B$3:$B$4997,">="&IF($C$4="",DATE(1900,1,1),$C$4),COMPRAS!$B$3:$B$4997,"<="&IF($F$4="",DATE(2999,12,31),$F$4)),0) -> 22.75 | V48: =IF(S48<>"",SUMIFS(COMPRAS!$O$3:$O$4997,COMPRAS!$G$3:$G$4997,S48,COMPRAS!$B$3:$B$4997,">="&IF($C$4="",DATE(1900,1,1),$C$4),COMPRAS!$B$3:$B$4997,"<="&IF($F$4="",DATE(2999,12,31),$F$4)),0) -> 64.974 | Y48: =IF($X$2="TODOS",U48,IF(S48<>"",SUMIFS(COMPRAS!$J$3:$J$4997,COMPRAS!$G$3:$G$4997,S48,COMPRAS!$D$3:$D$4997,$X$2,COMPRAS!$B$3:$B$4997,">="&IF($C$4="",DATE(1900,1,1),$C$4),COMPRAS!$B$3:$B$4997,"<="&IF($F$4="",DATE(2999,12,31),$F$4)),0)) -> 22.75 | Z48: =IF($X$2="TODOS",V48,IF(S48<>"",SUMIFS(COMPRAS!$O$3:$O$4997,COMPRAS!$G$3:$G$4997,S48,COMPRAS!$D$3:$D$4997,$X$2,COMPRAS!$B$3:$B$4997,">="&IF($C$4="",DATE(1900,1,1),$C$4),COMPRAS!$B$3:$B$4997,"<="&IF($F$4="",DATE(2999,12,31),$F$4)),0)) -> 64.974
A49: 1 | B49: =IFERROR(INDEX($T$2:$T$231,MATCH(LARGE($Y$2:$Y$231,1),$Y$2:$Y$231,0)),"") -> BOQUERON/ BOCARTE/ ANCHOA (ANE) | C49: =IFERROR(LARGE($Y$2:$Y$231,1),0) -> 48607 | D49: =IFERROR(INDEX($Z$2:$Z$231,MATCH(LARGE($Y$2:$Y$231,1),$Y$2:$Y$231,0)),0) -> 74198.663 | N49: =PROVEEDORES!A50 -> 50532 | O49: =PROVEEDORES!B50 -> AITORPESCA S.L. | P49: =IF(N49<>"",SUMIFS(COMPRAS!$J$3:$J$4997,COMPRAS!$D$3:$D$4997,N49,COMPRAS!$B$3:$B$4997,">="&IF($C$4="",DATE(1900,1,1),$C$4),COMPRAS!$B$3:$B$4997,"<="&IF($F$4="",DATE(2999,12,31),$F$4)),0) -> 172 | Q49: =IF(N49<>"",SUMIFS(COMPRAS!$O$3:$O$4997,COMPRAS!$D$3:$D$4997,N49,COMPRAS!$B$3:$B$4997,">="&IF($C$4="",DATE(1900,1,1),$C$4),COMPRAS!$B$3:$B$4997,"<="&IF($F$4="",DATE(2999,12,31),$F$4)),0) -> 758.8 | S49: =PRODUCTOS!A50 -> C6530 | T49: =PRODUCTOS!B50 -> CORENO/ MENDO (WYT) | U49: =IF(S49<>"",SUMIFS(COMPRAS!$J$3:$J$4997,COMPRAS!$G$3:$G$4997,S49,COMPRAS!$B$3:$B$4997,">="&IF($C$4="",DATE(1900,1,1),$C$4),COMPRAS!$B$3:$B$4997,"<="&IF($F$4="",DATE(2999,12,31),$F$4)),0) -> 0 | V49: =IF(S49<>"",SUMIFS(COMPRAS!$O$3:$O$4997,COMPRAS!$G$3:$G$4997,S49,COMPRAS!$B$3:$B$4997,">="&IF($C$4="",DATE(1900,1,1),$C$4),COMPRAS!$B$3:$B$4997,"<="&IF($F$4="",DATE(2999,12,31),$F$4)),0) -> 0 | Y49: =IF($X$2="TODOS",U49,IF(S49<>"",SUMIFS(COMPRAS!$J$3:$J$4997,COMPRAS!$G$3:$G$4997,S49,COMPRAS!$D$3:$D$4997,$X$2,COMPRAS!$B$3:$B$4997,">="&IF($C$4="",DATE(1900,1,1),$C$4),COMPRAS!$B$3:$B$4997,"<="&IF($F$4="",DATE(2999,12,31),$F$4)),0)) -> 0 | Z49: =IF($X$2="TODOS",V49,IF(S49<>"",SUMIFS(COMPRAS!$O$3:$O$4997,COMPRAS!$G$3:$G$4997,S49,COMPRAS!$D$3:$D$4997,$X$2,COMPRAS!$B$3:$B$4997,">="&IF($C$4="",DATE(1900,1,1),$C$4),COMPRAS!$B$3:$B$4997,"<="&IF($F$4="",DATE(2999,12,31),$F$4)),0)) -> 0
A50: 2 | B50: =IFERROR(INDEX($T$2:$T$231,MATCH(LARGE($Y$2:$Y$231,2),$Y$2:$Y$231,0)),"") -> LIRIO/ BACALADILLA/ PERLA (WHB) | C50: =IFERROR(LARGE($Y$2:$Y$231,2),0) -> 32511.65 | D50: =IFERROR(INDEX($Z$2:$Z$231,MATCH(LARGE($Y$2:$Y$231,2),$Y$2:$Y$231,0)),0) -> 57717.359 | N50: =PROVEEDORES!A51 -> 50193 | O50: =PROVEEDORES!B51 -> FRANCISCO JAVIER ARROJO SOUTO | P50: =IF(N50<>"",SUMIFS(COMPRAS!$J$3:$J$4997,COMPRAS!$D$3:$D$4997,N50,COMPRAS!$B$3:$B$4997,">="&IF($C$4="",DATE(1900,1,1),$C$4),COMPRAS!$B$3:$B$4997,"<="&IF($F$4="",DATE(2999,12,31),$F$4)),0) -> 180 | Q50: =IF(N50<>"",SUMIFS(COMPRAS!$O$3:$O$4997,COMPRAS!$D$3:$D$4997,N50,COMPRAS!$B$3:$B$4997,">="&IF($C$4="",DATE(1900,1,1),$C$4),COMPRAS!$B$3:$B$4997,"<="&IF($F$4="",DATE(2999,12,31),$F$4)),0) -> 417.6 | S50: =PRODUCTOS!A51 -> C6301 | T50: =PRODUCTOS!B51 -> CORUXO/ SOLLO/ REMOL (BLL) | U50: =IF(S50<>"",SUMIFS(COMPRAS!$J$3:$J$4997,COMPRAS!$G$3:$G$4997,S50,COMPRAS!$B$3:$B$4997,">="&IF($C$4="",DATE(1900,1,1),$C$4),COMPRAS!$B$3:$B$4997,"<="&IF($F$4="",DATE(2999,12,31),$F$4)),0) -> 46.4 | V50: =IF(S50<>"",SUMIFS(COMPRAS!$O$3:$O$4997,COMPRAS!$G$3:$G$4997,S50,COMPRAS!$B$3:$B$4997,">="&IF($C$4="",DATE(1900,1,1),$C$4),COMPRAS!$B$3:$B$4997,"<="&IF($F$4="",DATE(2999,12,31),$F$4)),0) -> 1095.62 | Y50: =IF($X$2="TODOS",U50,IF(S50<>"",SUMIFS(COMPRAS!$J$3:$J$4997,COMPRAS!$G$3:$G$4997,S50,COMPRAS!$D$3:$D$4997,$X$2,COMPRAS!$B$3:$B$4997,">="&IF($C$4="",DATE(1900,1,1),$C$4),COMPRAS!$B$3:$B$4997,"<="&IF($F$4="",DATE(2999,12,31),$F$4)),0)) -> 46.4 | Z50: =IF($X$2="TODOS",V50,IF(S50<>"",SUMIFS(COMPRAS!$O$3:$O$4997,COMPRAS!$G$3:$G$4997,S50,COMPRAS!$D$3:$D$4997,$X$2,COMPRAS!$B$3:$B$4997,">="&IF($C$4="",DATE(1900,1,1),$C$4),COMPRAS!$B$3:$B$4997,"<="&IF($F$4="",DATE(2999,12,31),$F$4)),0)) -> 1095.62
A51: 3 | B51: =IFERROR(INDEX($T$2:$T$231,MATCH(LARGE($Y$2:$Y$231,3),$Y$2:$Y$231,0)),"") -> RAPE BLANCO RASCO (MON) | C51: =IFERROR(LARGE($Y$2:$Y$231,3),0) -> 7149.7 | D51: =IFERROR(INDEX($Z$2:$Z$231,MATCH(LARGE($Y$2:$Y$231,3),$Y$2:$Y$231,0)),0) -> 47464.017 | N51: =PROVEEDORES!A52 -> 50526 | O51: =PROVEEDORES!B52 -> BARROS PESCAGALICIA, S.L. | P51: =IF(N51<>"",SUMIFS(COMPRAS!$J$3:$J$4997,COMPRAS!$D$3:$D$4997,N51,COMPRAS!$B$3:$B$4997,">="&IF($C$4="",DATE(1900,1,1),$C$4),COMPRAS!$B$3:$B$4997,"<="&IF($F$4="",DATE(2999,12,31),$F$4)),0) -> 111 | Q51: =IF(N51<>"",SUMIFS(COMPRAS!$O$3:$O$4997,COMPRAS!$D$3:$D$4997,N51,COMPRAS!$B$3:$B$4997,">="&IF($C$4="",DATE(1900,1,1),$C$4),COMPRAS!$B$3:$B$4997,"<="&IF($F$4="",DATE(2999,12,31),$F$4)),0) -> 438.5 | S51: =PRODUCTOS!A52 -> C561 | T51: =PRODUCTOS!B52 -> DENTON (DEC) | U51: =IF(S51<>"",SUMIFS(COMPRAS!$J$3:$J$4997,COMPRAS!$G$3:$G$4997,S51,COMPRAS!$B$3:$B$4997,">="&IF($C$4="",DATE(1900,1,1),$C$4),COMPRAS!$B$3:$B$4997,"<="&IF($F$4="",DATE(2999,12,31),$F$4)),0) -> 0 | V51: =IF(S51<>"",SUMIFS(COMPRAS!$O$3:$O$4997,COMPRAS!$G$3:$G$4997,S51,COMPRAS!$B$3:$B$4997,">="&IF($C$4="",DATE(1900,1,1),$C$4),COMPRAS!$B$3:$B$4997,"<="&IF($F$4="",DATE(2999,12,31),$F$4)),0) -> 0 | Y51: =IF($X$2="TODOS",U51,IF(S51<>"",SUMIFS(COMPRAS!$J$3:$J$4997,COMPRAS!$G$3:$G$4997,S51,COMPRAS!$D$3:$D$4997,$X$2,COMPRAS!$B$3:$B$4997,">="&IF($C$4="",DATE(1900,1,1),$C$4),COMPRAS!$B$3:$B$4997,"<="&IF($F$4="",DATE(2999,12,31),$F$4)),0)) -> 0 | Z51: =IF($X$2="TODOS",V51,IF(S51<>"",SUMIFS(COMPRAS!$O$3:$O$4997,COMPRAS!$G$3:$G$4997,S51,COMPRAS!$D$3:$D$4997,$X$2,COMPRAS!$B$3:$B$4997,">="&IF($C$4="",DATE(1900,1,1),$C$4),COMPRAS!$B$3:$B$4997,"<="&IF($F$4="",DATE(2999,12,31),$F$4)),0)) -> 0
A52: 4 | B52: =IFERROR(INDEX($T$2:$T$231,MATCH(LARGE($Y$2:$Y$231,4),$Y$2:$Y$231,0)),"") -> MERLUZA EUROPEA/ FINA DIA | C52: =IFERROR(LARGE($Y$2:$Y$231,4),0) -> 5733.75 | D52: =IFERROR(INDEX($Z$2:$Z$231,MATCH(LARGE($Y$2:$Y$231,4),$Y$2:$Y$231,0)),0) -> 16382.407 | N52: =PROVEEDORES!A53 -> 50533 | O52: =PROVEEDORES!B53 -> LURDES MARIÑO, S.L. | P52: =IF(N52<>"",SUMIFS(COMPRAS!$J$3:$J$4997,COMPRAS!$D$3:$D$4997,N52,COMPRAS!$B$3:$B$4997,">="&IF($C$4="",DATE(1900,1,1),$C$4),COMPRAS!$B$3:$B$4997,"<="&IF($F$4="",DATE(2999,12,31),$F$4)),0) -> 1215 | Q52: =IF(N52<>"",SUMIFS(COMPRAS!$O$3:$O$4997,COMPRAS!$D$3:$D$4997,N52,COMPRAS!$B$3:$B$4997,">="&IF($C$4="",DATE(1900,1,1),$C$4),COMPRAS!$B$3:$B$4997,"<="&IF($F$4="",DATE(2999,12,31),$F$4)),0) -> 1701 | S52: =PRODUCTOS!A53 -> C3500 | T52: =PRODUCTOS!B53 -> DORADA SALVAJE (SBG) | U52: =IF(S52<>"",SUMIFS(COMPRAS!$J$3:$J$4997,COMPRAS!$G$3:$G$4997,S52,COMPRAS!$B$3:$B$4997,">="&IF($C$4="",DATE(1900,1,1),$C$4),COMPRAS!$B$3:$B$4997,"<="&IF($F$4="",DATE(2999,12,31),$F$4)),0) -> 0 | V52: =IF(S52<>"",SUMIFS(COMPRAS!$O$3:$O$4997,COMPRAS!$G$3:$G$4997,S52,COMPRAS!$B$3:$B$4997,">="&IF($C$4="",DATE(1900,1,1),$C$4),COMPRAS!$B$3:$B$4997,"<="&IF($F$4="",DATE(2999,12,31),$F$4)),0) -> 0 | Y52: =IF($X$2="TODOS",U52,IF(S52<>"",SUMIFS(COMPRAS!$J$3:$J$4997,COMPRAS!$G$3:$G$4997,S52,COMPRAS!$D$3:$D$4997,$X$2,COMPRAS!$B$3:$B$4997,">="&IF($C$4="",DATE(1900,1,1),$C$4),COMPRAS!$B$3:$B$4997,"<="&IF($F$4="",DATE(2999,12,31),$F$4)),0)) -> 0 | Z52: =IF($X$2="TODOS",V52,IF(S52<>"",SUMIFS(COMPRAS!$O$3:$O$4997,COMPRAS!$G$3:$G$4997,S52,COMPRAS!$D$3:$D$4997,$X$2,COMPRAS!$B$3:$B$4997,">="&IF($C$4="",DATE(1900,1,1),$C$4),COMPRAS!$B$3:$B$4997,"<="&IF($F$4="",DATE(2999,12,31),$F$4)),0)) -> 0
A53: 5 | B53: =IFERROR(INDEX($T$2:$T$231,MATCH(LARGE($Y$2:$Y$231,5),$Y$2:$Y$231,0)),"") -> VARIADO PEQUEÑO | C53: =IFERROR(LARGE($Y$2:$Y$231,5),0) -> 4046.25 | D53: =IFERROR(INDEX($Z$2:$Z$231,MATCH(LARGE($Y$2:$Y$231,5),$Y$2:$Y$231,0)),0) -> 2670.7653 | N53: =PROVEEDORES!A54 -> 0 | O53: =PROVEEDORES!B54 -> 0 | P53: =IF(N53<>"",SUMIFS(COMPRAS!$J$3:$J$4997,COMPRAS!$D$3:$D$4997,N53,COMPRAS!$B$3:$B$4997,">="&IF($C$4="",DATE(1900,1,1),$C$4),COMPRAS!$B$3:$B$4997,"<="&IF($F$4="",DATE(2999,12,31),$F$4)),0) -> 0 | Q53: =IF(N53<>"",SUMIFS(COMPRAS!$O$3:$O$4997,COMPRAS!$D$3:$D$4997,N53,COMPRAS!$B$3:$B$4997,">="&IF($C$4="",DATE(1900,1,1),$C$4),COMPRAS!$B$3:$B$4997,"<="&IF($F$4="",DATE(2999,12,31),$F$4)),0) -> 0 | S53: =PRODUCTOS!A54 -> C867 | T53: =PRODUCTOS!B54 -> ERIZO DE MAR (URM) | U53: =IF(S53<>"",SUMIFS(COMPRAS!$J$3:$J$4997,COMPRAS!$G$3:$G$4997,S53,COMPRAS!$B$3:$B$4997,">="&IF($C$4="",DATE(1900,1,1),$C$4),COMPRAS!$B$3:$B$4997,"<="&IF($F$4="",DATE(2999,12,31),$F$4)),0) -> 0 | V53: =IF(S53<>"",SUMIFS(COMPRAS!$O$3:$O$4997,COMPRAS!$G$3:$G$4997,S53,COMPRAS!$B$3:$B$4997,">="&IF($C$4="",DATE(1900,1,1),$C$4),COMPRAS!$B$3:$B$4997,"<="&IF($F$4="",DATE(2999,12,31),$F$4)),0) -> 0 | Y53: =IF($X$2="TODOS",U53,IF(S53<>"",SUMIFS(COMPRAS!$J$3:$J$4997,COMPRAS!$G$3:$G$4997,S53,COMPRAS!$D$3:$D$4997,$X$2,COMPRAS!$B$3:$B$4997,">="&IF($C$4="",DATE(1900,1,1),$C$4),COMPRAS!$B$3:$B$4997,"<="&IF($F$4="",DATE(2999,12,31),$F$4)),0)) -> 0 | Z53: =IF($X$2="TODOS",V53,IF(S53<>"",SUMIFS(COMPRAS!$O$3:$O$4997,COMPRAS!$G$3:$G$4997,S53,COMPRAS!$D$3:$D$4997,$X$2,COMPRAS!$B$3:$B$4997,">="&IF($C$4="",DATE(1900,1,1),$C$4),COMPRAS!$B$3:$B$4997,"<="&IF($F$4="",DATE(2999,12,31),$F$4)),0)) -> 0
A54: 6 | B54: =IFERROR(INDEX($T$2:$T$231,MATCH(LARGE($Y$2:$Y$231,6),$Y$2:$Y$231,0)),"") -> BONITO DEL NORTE 5/7 | C54: =IFERROR(LARGE($Y$2:$Y$231,6),0) -> 3944.05 | D54: =IFERROR(INDEX($Z$2:$Z$231,MATCH(LARGE($Y$2:$Y$231,6),$Y$2:$Y$231,0)),0) -> 19023.43 | N54: =PROVEEDORES!A55 -> 0 | O54: =PROVEEDORES!B55 -> 0 | P54: =IF(N54<>"",SUMIFS(COMPRAS!$J$3:$J$4997,COMPRAS!$D$3:$D$4997,N54,COMPRAS!$B$3:$B$4997,">="&IF($C$4="",DATE(1900,1,1),$C$4),COMPRAS!$B$3:$B$4997,"<="&IF($F$4="",DATE(2999,12,31),$F$4)),0) -> 0 | Q54: =IF(N54<>"",SUMIFS(COMPRAS!$O$3:$O$4997,COMPRAS!$D$3:$D$4997,N54,COMPRAS!$B$3:$B$4997,">="&IF($C$4="",DATE(1900,1,1),$C$4),COMPRAS!$B$3:$B$4997,"<="&IF($F$4="",DATE(2999,12,31),$F$4)),0) -> 0 | S54: =PRODUCTOS!A55 -> C2566 | T54: =PRODUCTOS!B55 -> ESCACHO/ ARETE/ RUBIO (GUR) | U54: =IF(S54<>"",SUMIFS(COMPRAS!$J$3:$J$4997,COMPRAS!$G$3:$G$4997,S54,COMPRAS!$B$3:$B$4997,">="&IF($C$4="",DATE(1900,1,1),$C$4),COMPRAS!$B$3:$B$4997,"<="&IF($F$4="",DATE(2999,12,31),$F$4)),0) -> 951.6 | V54: =IF(S54<>"",SUMIFS(COMPRAS!$O$3:$O$4997,COMPRAS!$G$3:$G$4997,S54,COMPRAS!$B$3:$B$4997,">="&IF($C$4="",DATE(1900,1,1),$C$4),COMPRAS!$B$3:$B$4997,"<="&IF($F$4="",DATE(2999,12,31),$F$4)),0) -> 472.75725 | Y54: =IF($X$2="TODOS",U54,IF(S54<>"",SUMIFS(COMPRAS!$J$3:$J$4997,COMPRAS!$G$3:$G$4997,S54,COMPRAS!$D$3:$D$4997,$X$2,COMPRAS!$B$3:$B$4997,">="&IF($C$4="",DATE(1900,1,1),$C$4),COMPRAS!$B$3:$B$4997,"<="&IF($F$4="",DATE(2999,12,31),$F$4)),0)) -> 951.6 | Z54: =IF($X$2="TODOS",V54,IF(S54<>"",SUMIFS(COMPRAS!$O$3:$O$4997,COMPRAS!$G$3:$G$4997,S54,COMPRAS!$D$3:$D$4997,$X$2,COMPRAS!$B$3:$B$4997,">="&IF($C$4="",DATE(1900,1,1),$C$4),COMPRAS!$B$3:$B$4997,"<="&IF($F$4="",DATE(2999,12,31),$F$4)),0)) -> 472.75725
A55: 7 | B55: =IFERROR(INDEX($T$2:$T$231,MATCH(LARGE($Y$2:$Y$231,7),$Y$2:$Y$231,0)),"") -> MERLUZA EUROPEA ARRASTRE (HKE) | C55: =IFERROR(LARGE($Y$2:$Y$231,7),0) -> 3583.45 | D55: =IFERROR(INDEX($Z$2:$Z$231,MATCH(LARGE($Y$2:$Y$231,7),$Y$2:$Y$231,0)),0) -> 11270.299 | N55: =PROVEEDORES!A56 -> 0 | O55: =PROVEEDORES!B56 -> 0 | P55: =IF(N55<>"",SUMIFS(COMPRAS!$J$3:$J$4997,COMPRAS!$D$3:$D$4997,N55,COMPRAS!$B$3:$B$4997,">="&IF($C$4="",DATE(1900,1,1),$C$4),COMPRAS!$B$3:$B$4997,"<="&IF($F$4="",DATE(2999,12,31),$F$4)),0) -> 0 | Q55: =IF(N55<>"",SUMIFS(COMPRAS!$O$3:$O$4997,COMPRAS!$D$3:$D$4997,N55,COMPRAS!$B$3:$B$4997,">="&IF($C$4="",DATE(1900,1,1),$C$4),COMPRAS!$B$3:$B$4997,"<="&IF($F$4="",DATE(2999,12,31),$F$4)),0) -> 0 | S55: =PRODUCTOS!A56 -> C495 | T55: =PRODUCTOS!B56 -> ESCARPON/ DRAGON | U55: =IF(S55<>"",SUMIFS(COMPRAS!$J$3:$J$4997,COMPRAS!$G$3:$G$4997,S55,COMPRAS!$B$3:$B$4997,">="&IF($C$4="",DATE(1900,1,1),$C$4),COMPRAS!$B$3:$B$4997,"<="&IF($F$4="",DATE(2999,12,31),$F$4)),0) -> 0 | V55: =IF(S55<>"",SUMIFS(COMPRAS!$O$3:$O$4997,COMPRAS!$G$3:$G$4997,S55,COMPRAS!$B$3:$B$4997,">="&IF($C$4="",DATE(1900,1,1),$C$4),COMPRAS!$B$3:$B$4997,"<="&IF($F$4="",DATE(2999,12,31),$F$4)),0) -> 0 | Y55: =IF($X$2="TODOS",U55,IF(S55<>"",SUMIFS(COMPRAS!$J$3:$J$4997,COMPRAS!$G$3:$G$4997,S55,COMPRAS!$D$3:$D$4997,$X$2,COMPRAS!$B$3:$B$4997,">="&IF($C$4="",DATE(1900,1,1),$C$4),COMPRAS!$B$3:$B$4997,"<="&IF($F$4="",DATE(2999,12,31),$F$4)),0)) -> 0 | Z55: =IF($X$2="TODOS",V55,IF(S55<>"",SUMIFS(COMPRAS!$O$3:$O$4997,COMPRAS!$G$3:$G$4997,S55,COMPRAS!$D$3:$D$4997,$X$2,COMPRAS!$B$3:$B$4997,">="&IF($C$4="",DATE(1900,1,1),$C$4),COMPRAS!$B$3:$B$4997,"<="&IF($F$4="",DATE(2999,12,31),$F$4)),0)) -> 0
A56: 8 | B56: =IFERROR(INDEX($T$2:$T$231,MATCH(LARGE($Y$2:$Y$231,8),$Y$2:$Y$231,0)),"") -> CABALL/ SARDA/ VERDEL (MAC) | C56: =IFERROR(LARGE($Y$2:$Y$231,8),0) -> 3290.95 | D56: =IFERROR(INDEX($Z$2:$Z$231,MATCH(LARGE($Y$2:$Y$231,8),$Y$2:$Y$231,0)),0) -> 12989.67 | N56: =PROVEEDORES!A57 -> 0 | O56: =PROVEEDORES!B57 -> 0 | P56: =IF(N56<>"",SUMIFS(COMPRAS!$J$3:$J$4997,COMPRAS!$D$3:$D$4997,N56,COMPRAS!$B$3:$B$4997,">="&IF($C$4="",DATE(1900,1,1),$C$4),COMPRAS!$B$3:$B$4997,"<="&IF($F$4="",DATE(2999,12,31),$F$4)),0) -> 0 | Q56: =IF(N56<>"",SUMIFS(COMPRAS!$O$3:$O$4997,COMPRAS!$D$3:$D$4997,N56,COMPRAS!$B$3:$B$4997,">="&IF($C$4="",DATE(1900,1,1),$C$4),COMPRAS!$B$3:$B$4997,"<="&IF($F$4="",DATE(2999,12,31),$F$4)),0) -> 0 | S56: =PRODUCTOS!A57 -> C214 | T56: =PRODUCTOS!B57 -> FANECA (BIB) | U56: =IF(S56<>"",SUMIFS(COMPRAS!$J$3:$J$4997,COMPRAS!$G$3:$G$4997,S56,COMPRAS!$B$3:$B$4997,">="&IF($C$4="",DATE(1900,1,1),$C$4),COMPRAS!$B$3:$B$4997,"<="&IF($F$4="",DATE(2999,12,31),$F$4)),0) -> 29.5 | V56: =IF(S56<>"",SUMIFS(COMPRAS!$O$3:$O$4997,COMPRAS!$G$3:$G$4997,S56,COMPRAS!$B$3:$B$4997,">="&IF($C$4="",DATE(1900,1,1),$C$4),COMPRAS!$B$3:$B$4997,"<="&IF($F$4="",DATE(2999,12,31),$F$4)),0) -> 37.577 | Y56: =IF($X$2="TODOS",U56,IF(S56<>"",SUMIFS(COMPRAS!$J$3:$J$4997,COMPRAS!$G$3:$G$4997,S56,COMPRAS!$D$3:$D$4997,$X$2,COMPRAS!$B$3:$B$4997,">="&IF($C$4="",DATE(1900,1,1),$C$4),COMPRAS!$B$3:$B$4997,"<="&IF($F$4="",DATE(2999,12,31),$F$4)),0)) -> 29.5 | Z56: =IF($X$2="TODOS",V56,IF(S56<>"",SUMIFS(COMPRAS!$O$3:$O$4997,COMPRAS!$G$3:$G$4997,S56,COMPRAS!$D$3:$D$4997,$X$2,COMPRAS!$B$3:$B$4997,">="&IF($C$4="",DATE(1900,1,1),$C$4),COMPRAS!$B$3:$B$4997,"<="&IF($F$4="",DATE(2999,12,31),$F$4)),0)) -> 37.577
A57: 9 | B57: =IFERROR(INDEX($T$2:$T$231,MATCH(LARGE($Y$2:$Y$231,9),$Y$2:$Y$231,0)),"") -> MERLUZA EUROPEA PINCHO COSTA 800 | C57: =IFERROR(LARGE($Y$2:$Y$231,9),0) -> 2398.55 | D57: =IFERROR(INDEX($Z$2:$Z$231,MATCH(LARGE($Y$2:$Y$231,9),$Y$2:$Y$231,0)),0) -> 13944.356 | N57: =PROVEEDORES!A58 -> 0 | O57: =PROVEEDORES!B58 -> 0 | P57: =IF(N57<>"",SUMIFS(COMPRAS!$J$3:$J$4997,COMPRAS!$D$3:$D$4997,N57,COMPRAS!$B$3:$B$4997,">="&IF($C$4="",DATE(1900,1,1),$C$4),COMPRAS!$B$3:$B$4997,"<="&IF($F$4="",DATE(2999,12,31),$F$4)),0) -> 0 | Q57: =IF(N57<>"",SUMIFS(COMPRAS!$O$3:$O$4997,COMPRAS!$D$3:$D$4997,N57,COMPRAS!$B$3:$B$4997,">="&IF($C$4="",DATE(1900,1,1),$C$4),COMPRAS!$B$3:$B$4997,"<="&IF($F$4="",DATE(2999,12,31),$F$4)),0) -> 0 | S57: =PRODUCTOS!A58 -> C420 | T57: =PRODUCTOS!B58 -> GALLANO/ REI (USI) | U57: =IF(S57<>"",SUMIFS(COMPRAS!$J$3:$J$4997,COMPRAS!$G$3:$G$4997,S57,COMPRAS!$B$3:$B$4997,">="&IF($C$4="",DATE(1900,1,1),$C$4),COMPRAS!$B$3:$B$4997,"<="&IF($F$4="",DATE(2999,12,31),$F$4)),0) -> 0 | V57: =IF(S57<>"",SUMIFS(COMPRAS!$O$3:$O$4997,COMPRAS!$G$3:$G$4997,S57,COMPRAS!$B$3:$B$4997,">="&IF($C$4="",DATE(1900,1,1),$C$4),COMPRAS!$B$3:$B$4997,"<="&IF($F$4="",DATE(2999,12,31),$F$4)),0) -> 0 | Y57: =IF($X$2="TODOS",U57,IF(S57<>"",SUMIFS(COMPRAS!$J$3:$J$4997,COMPRAS!$G$3:$G$4997,S57,COMPRAS!$D$3:$D$4997,$X$2,COMPRAS!$B$3:$B$4997,">="&IF($C$4="",DATE(1900,1,1),$C$4),COMPRAS!$B$3:$B$4997,"<="&IF($F$4="",DATE(2999,12,31),$F$4)),0)) -> 0 | Z57: =IF($X$2="TODOS",V57,IF(S57<>"",SUMIFS(COMPRAS!$O$3:$O$4997,COMPRAS!$G$3:$G$4997,S57,COMPRAS!$D$3:$D$4997,$X$2,COMPRAS!$B$3:$B$4997,">="&IF($C$4="",DATE(1900,1,1),$C$4),COMPRAS!$B$3:$B$4997,"<="&IF($F$4="",DATE(2999,12,31),$F$4)),0)) -> 0
A58: 10 | B58: =IFERROR(INDEX($T$2:$T$231,MATCH(LARGE($Y$2:$Y$231,10),$Y$2:$Y$231,0)),"") -> RAPE NEGRO (ANK) | C58: =IFERROR(LARGE($Y$2:$Y$231,10),0) -> 2166.3 | D58: =IFERROR(INDEX($Z$2:$Z$231,MATCH(LARGE($Y$2:$Y$231,10),$Y$2:$Y$231,0)),0) -> 10128.467 | N58: =PROVEEDORES!A59 -> 0 | O58: =PROVEEDORES!B59 -> 0 | P58: =IF(N58<>"",SUMIFS(COMPRAS!$J$3:$J$4997,COMPRAS!$D$3:$D$4997,N58,COMPRAS!$B$3:$B$4997,">="&IF($C$4="",DATE(1900,1,1),$C$4),COMPRAS!$B$3:$B$4997,"<="&IF($F$4="",DATE(2999,12,31),$F$4)),0) -> 0 | Q58: =IF(N58<>"",SUMIFS(COMPRAS!$O$3:$O$4997,COMPRAS!$D$3:$D$4997,N58,COMPRAS!$B$3:$B$4997,">="&IF($C$4="",DATE(1900,1,1),$C$4),COMPRAS!$B$3:$B$4997,"<="&IF($F$4="",DATE(2999,12,31),$F$4)),0) -> 0 | S58: =PRODUCTOS!A59 -> C269 | T58: =PRODUCTOS!B59 -> GALLINETA NORTE OCEANICA (FILETES) | U58: =IF(S58<>"",SUMIFS(COMPRAS!$J$3:$J$4997,COMPRAS!$G$3:$G$4997,S58,COMPRAS!$B$3:$B$4997,">="&IF($C$4="",DATE(1900,1,1),$C$4),COMPRAS!$B$3:$B$4997,"<="&IF($F$4="",DATE(2999,12,31),$F$4)),0) -> 0 | V58: =IF(S58<>"",SUMIFS(COMPRAS!$O$3:$O$4997,COMPRAS!$G$3:$G$4997,S58,COMPRAS!$B$3:$B$4997,">="&IF($C$4="",DATE(1900,1,1),$C$4),COMPRAS!$B$3:$B$4997,"<="&IF($F$4="",DATE(2999,12,31),$F$4)),0) -> 0 | Y58: =IF($X$2="TODOS",U58,IF(S58<>"",SUMIFS(COMPRAS!$J$3:$J$4997,COMPRAS!$G$3:$G$4997,S58,COMPRAS!$D$3:$D$4997,$X$2,COMPRAS!$B$3:$B$4997,">="&IF($C$4="",DATE(1900,1,1),$C$4),COMPRAS!$B$3:$B$4997,"<="&IF($F$4="",DATE(2999,12,31),$F$4)),0)) -> 0 | Z58: =IF($X$2="TODOS",V58,IF(S58<>"",SUMIFS(COMPRAS!$O$3:$O$4997,COMPRAS!$G$3:$G$4997,S58,COMPRAS!$D$3:$D$4997,$X$2,COMPRAS!$B$3:$B$4997,">="&IF($C$4="",DATE(1900,1,1),$C$4),COMPRAS!$B$3:$B$4997,"<="&IF($F$4="",DATE(2999,12,31),$F$4)),0)) -> 0
N59: =PROVEEDORES!A60 -> 0 | O59: =PROVEEDORES!B60 -> 0 | P59: =IF(N59<>"",SUMIFS(COMPRAS!$J$3:$J$4997,COMPRAS!$D$3:$D$4997,N59,COMPRAS!$B$3:$B$4997,">="&IF($C$4="",DATE(1900,1,1),$C$4),COMPRAS!$B$3:$B$4997,"<="&IF($F$4="",DATE(2999,12,31),$F$4)),0) -> 0 | Q59: =IF(N59<>"",SUMIFS(COMPRAS!$O$3:$O$4997,COMPRAS!$D$3:$D$4997,N59,COMPRAS!$B$3:$B$4997,">="&IF($C$4="",DATE(1900,1,1),$C$4),COMPRAS!$B$3:$B$4997,"<="&IF($F$4="",DATE(2999,12,31),$F$4)),0) -> 0 | S59: =PRODUCTOS!A60 -> C270 | T59: =PRODUCTOS!B60 -> GALLO | U59: =IF(S59<>"",SUMIFS(COMPRAS!$J$3:$J$4997,COMPRAS!$G$3:$G$4997,S59,COMPRAS!$B$3:$B$4997,">="&IF($C$4="",DATE(1900,1,1),$C$4),COMPRAS!$B$3:$B$4997,"<="&IF($F$4="",DATE(2999,12,31),$F$4)),0) -> 18.5 | V59: =IF(S59<>"",SUMIFS(COMPRAS!$O$3:$O$4997,COMPRAS!$G$3:$G$4997,S59,COMPRAS!$B$3:$B$4997,">="&IF($C$4="",DATE(1900,1,1),$C$4),COMPRAS!$B$3:$B$4997,"<="&IF($F$4="",DATE(2999,12,31),$F$4)),0) -> 112.71 | Y59: =IF($X$2="TODOS",U59,IF(S59<>"",SUMIFS(COMPRAS!$J$3:$J$4997,COMPRAS!$G$3:$G$4997,S59,COMPRAS!$D$3:$D$4997,$X$2,COMPRAS!$B$3:$B$4997,">="&IF($C$4="",DATE(1900,1,1),$C$4),COMPRAS!$B$3:$B$4997,"<="&IF($F$4="",DATE(2999,12,31),$F$4)),0)) -> 18.5 | Z59: =IF($X$2="TODOS",V59,IF(S59<>"",SUMIFS(COMPRAS!$O$3:$O$4997,COMPRAS!$G$3:$G$4997,S59,COMPRAS!$D$3:$D$4997,$X$2,COMPRAS!$B$3:$B$4997,">="&IF($C$4="",DATE(1900,1,1),$C$4),COMPRAS!$B$3:$B$4997,"<="&IF($F$4="",DATE(2999,12,31),$F$4)),0)) -> 112.71
N60: =PROVEEDORES!A61 -> 0 | O60: =PROVEEDORES!B61 -> 0 | P60: =IF(N60<>"",SUMIFS(COMPRAS!$J$3:$J$4997,COMPRAS!$D$3:$D$4997,N60,COMPRAS!$B$3:$B$4997,">="&IF($C$4="",DATE(1900,1,1),$C$4),COMPRAS!$B$3:$B$4997,"<="&IF($F$4="",DATE(2999,12,31),$F$4)),0) -> 0 | Q60: =IF(N60<>"",SUMIFS(COMPRAS!$O$3:$O$4997,COMPRAS!$D$3:$D$4997,N60,COMPRAS!$B$3:$B$4997,">="&IF($C$4="",DATE(1900,1,1),$C$4),COMPRAS!$B$3:$B$4997,"<="&IF($F$4="",DATE(2999,12,31),$F$4)),0) -> 0 | S60: =PRODUCTOS!A61 -> C271 | T60: =PRODUCTOS!B61 -> GALLO RIA/ RAPANTE/ MEIGA (MEG) | U60: =IF(S60<>"",SUMIFS(COMPRAS!$J$3:$J$4997,COMPRAS!$G$3:$G$4997,S60,COMPRAS!$B$3:$B$4997,">="&IF($C$4="",DATE(1900,1,1),$C$4),COMPRAS!$B$3:$B$4997,"<="&IF($F$4="",DATE(2999,12,31),$F$4)),0) -> 0 | V60: =IF(S60<>"",SUMIFS(COMPRAS!$O$3:$O$4997,COMPRAS!$G$3:$G$4997,S60,COMPRAS!$B$3:$B$4997,">="&IF($C$4="",DATE(1900,1,1),$C$4),COMPRAS!$B$3:$B$4997,"<="&IF($F$4="",DATE(2999,12,31),$F$4)),0) -> 0 | Y60: =IF($X$2="TODOS",U60,IF(S60<>"",SUMIFS(COMPRAS!$J$3:$J$4997,COMPRAS!$G$3:$G$4997,S60,COMPRAS!$D$3:$D$4997,$X$2,COMPRAS!$B$3:$B$4997,">="&IF($C$4="",DATE(1900,1,1),$C$4),COMPRAS!$B$3:$B$4997,"<="&IF($F$4="",DATE(2999,12,31),$F$4)),0)) -> 0 | Z60: =IF($X$2="TODOS",V60,IF(S60<>"",SUMIFS(COMPRAS!$O$3:$O$4997,COMPRAS!$G$3:$G$4997,S60,COMPRAS!$D$3:$D$4997,$X$2,COMPRAS!$B$3:$B$4997,">="&IF($C$4="",DATE(1900,1,1),$C$4),COMPRAS!$B$3:$B$4997,"<="&IF($F$4="",DATE(2999,12,31),$F$4)),0)) -> 0
A61: RESULTADO PARA ESOS FILTROS EXACTOS (proveedor + articulo + fechas) | N61: =PROVEEDORES!A62 -> 0 | O61: =PROVEEDORES!B62 -> 0 | P61: =IF(N61<>"",SUMIFS(COMPRAS!$J$3:$J$4997,COMPRAS!$D$3:$D$4997,N61,COMPRAS!$B$3:$B$4997,">="&IF($C$4="",DATE(1900,1,1),$C$4),COMPRAS!$B$3:$B$4997,"<="&IF($F$4="",DATE(2999,12,31),$F$4)),0) -> 0 | Q61: =IF(N61<>"",SUMIFS(COMPRAS!$O$3:$O$4997,COMPRAS!$D$3:$D$4997,N61,COMPRAS!$B$3:$B$4997,">="&IF($C$4="",DATE(1900,1,1),$C$4),COMPRAS!$B$3:$B$4997,"<="&IF($F$4="",DATE(2999,12,31),$F$4)),0) -> 0 | S61: =PRODUCTOS!A62 -> C5310 | T61: =PRODUCTOS!B62 -> GATA/ GALLUDO (QUB) | U61: =IF(S61<>"",SUMIFS(COMPRAS!$J$3:$J$4997,COMPRAS!$G$3:$G$4997,S61,COMPRAS!$B$3:$B$4997,">="&IF($C$4="",DATE(1900,1,1),$C$4),COMPRAS!$B$3:$B$4997,"<="&IF($F$4="",DATE(2999,12,31),$F$4)),0) -> 0 | V61: =IF(S61<>"",SUMIFS(COMPRAS!$O$3:$O$4997,COMPRAS!$G$3:$G$4997,S61,COMPRAS!$B$3:$B$4997,">="&IF($C$4="",DATE(1900,1,1),$C$4),COMPRAS!$B$3:$B$4997,"<="&IF($F$4="",DATE(2999,12,31),$F$4)),0) -> 0 | Y61: =IF($X$2="TODOS",U61,IF(S61<>"",SUMIFS(COMPRAS!$J$3:$J$4997,COMPRAS!$G$3:$G$4997,S61,COMPRAS!$D$3:$D$4997,$X$2,COMPRAS!$B$3:$B$4997,">="&IF($C$4="",DATE(1900,1,1),$C$4),COMPRAS!$B$3:$B$4997,"<="&IF($F$4="",DATE(2999,12,31),$F$4)),0)) -> 0 | Z61: =IF($X$2="TODOS",V61,IF(S61<>"",SUMIFS(COMPRAS!$O$3:$O$4997,COMPRAS!$G$3:$G$4997,S61,COMPRAS!$D$3:$D$4997,$X$2,COMPRAS!$B$3:$B$4997,">="&IF($C$4="",DATE(1900,1,1),$C$4),COMPRAS!$B$3:$B$4997,"<="&IF($F$4="",DATE(2999,12,31),$F$4)),0)) -> 0
A62: Total kilos comprados: | D62: =IF($X$2="TODOS",SUMIFS(COMPRAS!$J$3:$J$4997,COMPRAS!$G$3:$G$4997,$X$3,COMPRAS!$B$3:$B$4997,">="&IF($C$4="",DATE(1900,1,1),$C$4),COMPRAS!$B$3:$B$4997,"<="&IF($F$4="",DATE(2999,12,31),$F$4)),SUMIFS(COMPRAS!$J$3:$J$4997,COMPRAS!$D$3:$D$4997,$X$2,COMPRAS!$G$3:$G$4997,$X$3,COMPRAS!$B$3:$B$4997,">="&IF($C$4="",DATE(1900,1,1),$C$4),COMPRAS!$B$3:$B$4997,"<="&IF($F$4="",DATE(2999,12,31),$F$4))) -> 148467.76 | N62: =PROVEEDORES!A63 -> 0 | O62: =PROVEEDORES!B63 -> 0 | P62: =IF(N62<>"",SUMIFS(COMPRAS!$J$3:$J$4997,COMPRAS!$D$3:$D$4997,N62,COMPRAS!$B$3:$B$4997,">="&IF($C$4="",DATE(1900,1,1),$C$4),COMPRAS!$B$3:$B$4997,"<="&IF($F$4="",DATE(2999,12,31),$F$4)),0) -> 0 | Q62: =IF(N62<>"",SUMIFS(COMPRAS!$O$3:$O$4997,COMPRAS!$D$3:$D$4997,N62,COMPRAS!$B$3:$B$4997,">="&IF($C$4="",DATE(1900,1,1),$C$4),COMPRAS!$B$3:$B$4997,"<="&IF($F$4="",DATE(2999,12,31),$F$4)),0) -> 0 | S62: =PRODUCTOS!A63 -> C116 | T62: =PRODUCTOS!B63 -> HUEVAS DE MERLUZA | U62: =IF(S62<>"",SUMIFS(COMPRAS!$J$3:$J$4997,COMPRAS!$G$3:$G$4997,S62,COMPRAS!$B$3:$B$4997,">="&IF($C$4="",DATE(1900,1,1),$C$4),COMPRAS!$B$3:$B$4997,"<="&IF($F$4="",DATE(2999,12,31),$F$4)),0) -> 56.5 | V62: =IF(S62<>"",SUMIFS(COMPRAS!$O$3:$O$4997,COMPRAS!$G$3:$G$4997,S62,COMPRAS!$B$3:$B$4997,">="&IF($C$4="",DATE(1900,1,1),$C$4),COMPRAS!$B$3:$B$4997,"<="&IF($F$4="",DATE(2999,12,31),$F$4)),0) -> 771.12 | Y62: =IF($X$2="TODOS",U62,IF(S62<>"",SUMIFS(COMPRAS!$J$3:$J$4997,COMPRAS!$G$3:$G$4997,S62,COMPRAS!$D$3:$D$4997,$X$2,COMPRAS!$B$3:$B$4997,">="&IF($C$4="",DATE(1900,1,1),$C$4),COMPRAS!$B$3:$B$4997,"<="&IF($F$4="",DATE(2999,12,31),$F$4)),0)) -> 56.5 | Z62: =IF($X$2="TODOS",V62,IF(S62<>"",SUMIFS(COMPRAS!$O$3:$O$4997,COMPRAS!$G$3:$G$4997,S62,COMPRAS!$D$3:$D$4997,$X$2,COMPRAS!$B$3:$B$4997,">="&IF($C$4="",DATE(1900,1,1),$C$4),COMPRAS!$B$3:$B$4997,"<="&IF($F$4="",DATE(2999,12,31),$F$4)),0)) -> 771.12
A63: Total importe comprado: | D63: =IF($X$2="TODOS",SUMIFS(COMPRAS!$O$3:$O$4997,COMPRAS!$G$3:$G$4997,$X$3,COMPRAS!$B$3:$B$4997,">="&IF($C$4="",DATE(1900,1,1),$C$4),COMPRAS!$B$3:$B$4997,"<="&IF($F$4="",DATE(2999,12,31),$F$4)),SUMIFS(COMPRAS!$O$3:$O$4997,COMPRAS!$D$3:$D$4997,$X$2,COMPRAS!$G$3:$G$4997,$X$3,COMPRAS!$B$3:$B$4997,">="&IF($C$4="",DATE(1900,1,1),$C$4),COMPRAS!$B$3:$B$4997,"<="&IF($F$4="",DATE(2999,12,31),$F$4))) -> 483980.51 | N63: =PROVEEDORES!A64 -> 0 | O63: =PROVEEDORES!B64 -> 0 | P63: =IF(N63<>"",SUMIFS(COMPRAS!$J$3:$J$4997,COMPRAS!$D$3:$D$4997,N63,COMPRAS!$B$3:$B$4997,">="&IF($C$4="",DATE(1900,1,1),$C$4),COMPRAS!$B$3:$B$4997,"<="&IF($F$4="",DATE(2999,12,31),$F$4)),0) -> 0 | Q63: =IF(N63<>"",SUMIFS(COMPRAS!$O$3:$O$4997,COMPRAS!$D$3:$D$4997,N63,COMPRAS!$B$3:$B$4997,">="&IF($C$4="",DATE(1900,1,1),$C$4),COMPRAS!$B$3:$B$4997,"<="&IF($F$4="",DATE(2999,12,31),$F$4)),0) -> 0 | S63: =PRODUCTOS!A64 -> C3968 | T63: =PRODUCTOS!B64 -> JURELA BLANCA (HMY) | U63: =IF(S63<>"",SUMIFS(COMPRAS!$J$3:$J$4997,COMPRAS!$G$3:$G$4997,S63,COMPRAS!$B$3:$B$4997,">="&IF($C$4="",DATE(1900,1,1),$C$4),COMPRAS!$B$3:$B$4997,"<="&IF($F$4="",DATE(2999,12,31),$F$4)),0) -> 4.5 | V63: =IF(S63<>"",SUMIFS(COMPRAS!$O$3:$O$4997,COMPRAS!$G$3:$G$4997,S63,COMPRAS!$B$3:$B$4997,">="&IF($C$4="",DATE(1900,1,1),$C$4),COMPRAS!$B$3:$B$4997,"<="&IF($F$4="",DATE(2999,12,31),$F$4)),0) -> 35.343 | Y63: =IF($X$2="TODOS",U63,IF(S63<>"",SUMIFS(COMPRAS!$J$3:$J$4997,COMPRAS!$G$3:$G$4997,S63,COMPRAS!$D$3:$D$4997,$X$2,COMPRAS!$B$3:$B$4997,">="&IF($C$4="",DATE(1900,1,1),$C$4),COMPRAS!$B$3:$B$4997,"<="&IF($F$4="",DATE(2999,12,31),$F$4)),0)) -> 4.5 | Z63: =IF($X$2="TODOS",V63,IF(S63<>"",SUMIFS(COMPRAS!$O$3:$O$4997,COMPRAS!$G$3:$G$4997,S63,COMPRAS!$D$3:$D$4997,$X$2,COMPRAS!$B$3:$B$4997,">="&IF($C$4="",DATE(1900,1,1),$C$4),COMPRAS!$B$3:$B$4997,"<="&IF($F$4="",DATE(2999,12,31),$F$4)),0)) -> 35.343
A64: Numero de compras (lineas): | D64: =IF($X$2="TODOS",COUNTIFS(COMPRAS!$G$3:$G$4997,$X$3,COMPRAS!$B$3:$B$4997,">="&IF($C$4="",DATE(1900,1,1),$C$4),COMPRAS!$B$3:$B$4997,"<="&IF($F$4="",DATE(2999,12,31),$F$4)),COUNTIFS(COMPRAS!$D$3:$D$4997,$X$2,COMPRAS!$G$3:$G$4997,$X$3,COMPRAS!$B$3:$B$4997,">="&IF($C$4="",DATE(1900,1,1),$C$4),COMPRAS!$B$3:$B$4997,"<="&IF($F$4="",DATE(2999,12,31),$F$4))) -> 2086 | N64: =PROVEEDORES!A65 -> 0 | O64: =PROVEEDORES!B65 -> 0 | P64: =IF(N64<>"",SUMIFS(COMPRAS!$J$3:$J$4997,COMPRAS!$D$3:$D$4997,N64,COMPRAS!$B$3:$B$4997,">="&IF($C$4="",DATE(1900,1,1),$C$4),COMPRAS!$B$3:$B$4997,"<="&IF($F$4="",DATE(2999,12,31),$F$4)),0) -> 0 | Q64: =IF(N64<>"",SUMIFS(COMPRAS!$O$3:$O$4997,COMPRAS!$D$3:$D$4997,N64,COMPRAS!$B$3:$B$4997,">="&IF($C$4="",DATE(1900,1,1),$C$4),COMPRAS!$B$3:$B$4997,"<="&IF($F$4="",DATE(2999,12,31),$F$4)),0) -> 0 | S64: =PRODUCTOS!A65 -> C740 | T64: =PRODUCTOS!B65 -> CALAMAR CALIFORNIA | U64: =IF(S64<>"",SUMIFS(COMPRAS!$J$3:$J$4997,COMPRAS!$G$3:$G$4997,S64,COMPRAS!$B$3:$B$4997,">="&IF($C$4="",DATE(1900,1,1),$C$4),COMPRAS!$B$3:$B$4997,"<="&IF($F$4="",DATE(2999,12,31),$F$4)),0) -> 0 | V64: =IF(S64<>"",SUMIFS(COMPRAS!$O$3:$O$4997,COMPRAS!$G$3:$G$4997,S64,COMPRAS!$B$3:$B$4997,">="&IF($C$4="",DATE(1900,1,1),$C$4),COMPRAS!$B$3:$B$4997,"<="&IF($F$4="",DATE(2999,12,31),$F$4)),0) -> 0 | Y64: =IF($X$2="TODOS",U64,IF(S64<>"",SUMIFS(COMPRAS!$J$3:$J$4997,COMPRAS!$G$3:$G$4997,S64,COMPRAS!$D$3:$D$4997,$X$2,COMPRAS!$B$3:$B$4997,">="&IF($C$4="",DATE(1900,1,1),$C$4),COMPRAS!$B$3:$B$4997,"<="&IF($F$4="",DATE(2999,12,31),$F$4)),0)) -> 0 | Z64: =IF($X$2="TODOS",V64,IF(S64<>"",SUMIFS(COMPRAS!$O$3:$O$4997,COMPRAS!$G$3:$G$4997,S64,COMPRAS!$D$3:$D$4997,$X$2,COMPRAS!$B$3:$B$4997,">="&IF($C$4="",DATE(1900,1,1),$C$4),COMPRAS!$B$3:$B$4997,"<="&IF($F$4="",DATE(2999,12,31),$F$4)),0)) -> 0
A65: Precio medio pagado (EUR/kg): | D65: =IFERROR(D63/D62,0) -> 3.2598357 | N65: =PROVEEDORES!A66 -> 0 | O65: =PROVEEDORES!B66 -> 0 | P65: =IF(N65<>"",SUMIFS(COMPRAS!$J$3:$J$4997,COMPRAS!$D$3:$D$4997,N65,COMPRAS!$B$3:$B$4997,">="&IF($C$4="",DATE(1900,1,1),$C$4),COMPRAS!$B$3:$B$4997,"<="&IF($F$4="",DATE(2999,12,31),$F$4)),0) -> 0 | Q65: =IF(N65<>"",SUMIFS(COMPRAS!$O$3:$O$4997,COMPRAS!$D$3:$D$4997,N65,COMPRAS!$B$3:$B$4997,">="&IF($C$4="",DATE(1900,1,1),$C$4),COMPRAS!$B$3:$B$4997,"<="&IF($F$4="",DATE(2999,12,31),$F$4)),0) -> 0 | S65: =PRODUCTOS!A66 -> C7582 | T65: =PRODUCTOS!B66 -> PANPANO/ RUFO IMPERIO | U65: =IF(S65<>"",SUMIFS(COMPRAS!$J$3:$J$4997,COMPRAS!$G$3:$G$4997,S65,COMPRAS!$B$3:$B$4997,">="&IF($C$4="",DATE(1900,1,1),$C$4),COMPRAS!$B$3:$B$4997,"<="&IF($F$4="",DATE(2999,12,31),$F$4)),0) -> 0 | V65: =IF(S65<>"",SUMIFS(COMPRAS!$O$3:$O$4997,COMPRAS!$G$3:$G$4997,S65,COMPRAS!$B$3:$B$4997,">="&IF($C$4="",DATE(1900,1,1),$C$4),COMPRAS!$B$3:$B$4997,"<="&IF($F$4="",DATE(2999,12,31),$F$4)),0) -> 0 | Y65: =IF($X$2="TODOS",U65,IF(S65<>"",SUMIFS(COMPRAS!$J$3:$J$4997,COMPRAS!$G$3:$G$4997,S65,COMPRAS!$D$3:$D$4997,$X$2,COMPRAS!$B$3:$B$4997,">="&IF($C$4="",DATE(1900,1,1),$C$4),COMPRAS!$B$3:$B$4997,"<="&IF($F$4="",DATE(2999,12,31),$F$4)),0)) -> 0 | Z65: =IF($X$2="TODOS",V65,IF(S65<>"",SUMIFS(COMPRAS!$O$3:$O$4997,COMPRAS!$G$3:$G$4997,S65,COMPRAS!$D$3:$D$4997,$X$2,COMPRAS!$B$3:$B$4997,">="&IF($C$4="",DATE(1900,1,1),$C$4),COMPRAS!$B$3:$B$4997,"<="&IF($F$4="",DATE(2999,12,31),$F$4)),0)) -> 0
N66: =PROVEEDORES!A67 -> 0 | O66: =PROVEEDORES!B67 -> 0 | P66: =IF(N66<>"",SUMIFS(COMPRAS!$J$3:$J$4997,COMPRAS!$D$3:$D$4997,N66,COMPRAS!$B$3:$B$4997,">="&IF($C$4="",DATE(1900,1,1),$C$4),COMPRAS!$B$3:$B$4997,"<="&IF($F$4="",DATE(2999,12,31),$F$4)),0) -> 0 | Q66: =IF(N66<>"",SUMIFS(COMPRAS!$O$3:$O$4997,COMPRAS!$D$3:$D$4997,N66,COMPRAS!$B$3:$B$4997,">="&IF($C$4="",DATE(1900,1,1),$C$4),COMPRAS!$B$3:$B$4997,"<="&IF($F$4="",DATE(2999,12,31),$F$4)),0) -> 0 | S66: =PRODUCTOS!A67 -> C998 | T66: =PRODUCTOS!B67 -> JURELO MEDITERRANEO | U66: =IF(S66<>"",SUMIFS(COMPRAS!$J$3:$J$4997,COMPRAS!$G$3:$G$4997,S66,COMPRAS!$B$3:$B$4997,">="&IF($C$4="",DATE(1900,1,1),$C$4),COMPRAS!$B$3:$B$4997,"<="&IF($F$4="",DATE(2999,12,31),$F$4)),0) -> 47 | V66: =IF(S66<>"",SUMIFS(COMPRAS!$O$3:$O$4997,COMPRAS!$G$3:$G$4997,S66,COMPRAS!$B$3:$B$4997,">="&IF($C$4="",DATE(1900,1,1),$C$4),COMPRAS!$B$3:$B$4997,"<="&IF($F$4="",DATE(2999,12,31),$F$4)),0) -> 210.987 | Y66: =IF($X$2="TODOS",U66,IF(S66<>"",SUMIFS(COMPRAS!$J$3:$J$4997,COMPRAS!$G$3:$G$4997,S66,COMPRAS!$D$3:$D$4997,$X$2,COMPRAS!$B$3:$B$4997,">="&IF($C$4="",DATE(1900,1,1),$C$4),COMPRAS!$B$3:$B$4997,"<="&IF($F$4="",DATE(2999,12,31),$F$4)),0)) -> 47 | Z66: =IF($X$2="TODOS",V66,IF(S66<>"",SUMIFS(COMPRAS!$O$3:$O$4997,COMPRAS!$G$3:$G$4997,S66,COMPRAS!$D$3:$D$4997,$X$2,COMPRAS!$B$3:$B$4997,">="&IF($C$4="",DATE(1900,1,1),$C$4),COMPRAS!$B$3:$B$4997,"<="&IF($F$4="",DATE(2999,12,31),$F$4)),0)) -> 210.987
N67: =PROVEEDORES!A68 -> 0 | O67: =PROVEEDORES!B68 -> 0 | P67: =IF(N67<>"",SUMIFS(COMPRAS!$J$3:$J$4997,COMPRAS!$D$3:$D$4997,N67,COMPRAS!$B$3:$B$4997,">="&IF($C$4="",DATE(1900,1,1),$C$4),COMPRAS!$B$3:$B$4997,"<="&IF($F$4="",DATE(2999,12,31),$F$4)),0) -> 0 | Q67: =IF(N67<>"",SUMIFS(COMPRAS!$O$3:$O$4997,COMPRAS!$D$3:$D$4997,N67,COMPRAS!$B$3:$B$4997,">="&IF($C$4="",DATE(1900,1,1),$C$4),COMPRAS!$B$3:$B$4997,"<="&IF($F$4="",DATE(2999,12,31),$F$4)),0) -> 0 | S67: =PRODUCTOS!A68 -> C640 | T67: =PRODUCTOS!B68 -> LENGUADO RIA (SOL) | U67: =IF(S67<>"",SUMIFS(COMPRAS!$J$3:$J$4997,COMPRAS!$G$3:$G$4997,S67,COMPRAS!$B$3:$B$4997,">="&IF($C$4="",DATE(1900,1,1),$C$4),COMPRAS!$B$3:$B$4997,"<="&IF($F$4="",DATE(2999,12,31),$F$4)),0) -> 68.55 | V67: =IF(S67<>"",SUMIFS(COMPRAS!$O$3:$O$4997,COMPRAS!$G$3:$G$4997,S67,COMPRAS!$B$3:$B$4997,">="&IF($C$4="",DATE(1900,1,1),$C$4),COMPRAS!$B$3:$B$4997,"<="&IF($F$4="",DATE(2999,12,31),$F$4)),0) -> 2118.1626 | Y67: =IF($X$2="TODOS",U67,IF(S67<>"",SUMIFS(COMPRAS!$J$3:$J$4997,COMPRAS!$G$3:$G$4997,S67,COMPRAS!$D$3:$D$4997,$X$2,COMPRAS!$B$3:$B$4997,">="&IF($C$4="",DATE(1900,1,1),$C$4),COMPRAS!$B$3:$B$4997,"<="&IF($F$4="",DATE(2999,12,31),$F$4)),0)) -> 68.55 | Z67: =IF($X$2="TODOS",V67,IF(S67<>"",SUMIFS(COMPRAS!$O$3:$O$4997,COMPRAS!$G$3:$G$4997,S67,COMPRAS!$D$3:$D$4997,$X$2,COMPRAS!$B$3:$B$4997,">="&IF($C$4="",DATE(1900,1,1),$C$4),COMPRAS!$B$3:$B$4997,"<="&IF($F$4="",DATE(2999,12,31),$F$4)),0)) -> 2118.1626
N68: =PROVEEDORES!A69 -> 0 | O68: =PROVEEDORES!B69 -> 0 | P68: =IF(N68<>"",SUMIFS(COMPRAS!$J$3:$J$4997,COMPRAS!$D$3:$D$4997,N68,COMPRAS!$B$3:$B$4997,">="&IF($C$4="",DATE(1900,1,1),$C$4),COMPRAS!$B$3:$B$4997,"<="&IF($F$4="",DATE(2999,12,31),$F$4)),0) -> 0 | Q68: =IF(N68<>"",SUMIFS(COMPRAS!$O$3:$O$4997,COMPRAS!$D$3:$D$4997,N68,COMPRAS!$B$3:$B$4997,">="&IF($C$4="",DATE(1900,1,1),$C$4),COMPRAS!$B$3:$B$4997,"<="&IF($F$4="",DATE(2999,12,31),$F$4)),0) -> 0 | S68: =PRODUCTOS!A69 -> C221 | T68: =PRODUCTOS!B69 -> LIRIO/ BACALADILLA/ PERLA (WHB) | U68: =IF(S68<>"",SUMIFS(COMPRAS!$J$3:$J$4997,COMPRAS!$G$3:$G$4997,S68,COMPRAS!$B$3:$B$4997,">="&IF($C$4="",DATE(1900,1,1),$C$4),COMPRAS!$B$3:$B$4997,"<="&IF($F$4="",DATE(2999,12,31),$F$4)),0) -> 32511.65 | V68: =IF(S68<>"",SUMIFS(COMPRAS!$O$3:$O$4997,COMPRAS!$G$3:$G$4997,S68,COMPRAS!$B$3:$B$4997,">="&IF($C$4="",DATE(1900,1,1),$C$4),COMPRAS!$B$3:$B$4997,"<="&IF($F$4="",DATE(2999,12,31),$F$4)),0) -> 57717.359 | Y68: =IF($X$2="TODOS",U68,IF(S68<>"",SUMIFS(COMPRAS!$J$3:$J$4997,COMPRAS!$G$3:$G$4997,S68,COMPRAS!$D$3:$D$4997,$X$2,COMPRAS!$B$3:$B$4997,">="&IF($C$4="",DATE(1900,1,1),$C$4),COMPRAS!$B$3:$B$4997,"<="&IF($F$4="",DATE(2999,12,31),$F$4)),0)) -> 32511.65 | Z68: =IF($X$2="TODOS",V68,IF(S68<>"",SUMIFS(COMPRAS!$O$3:$O$4997,COMPRAS!$G$3:$G$4997,S68,COMPRAS!$D$3:$D$4997,$X$2,COMPRAS!$B$3:$B$4997,">="&IF($C$4="",DATE(1900,1,1),$C$4),COMPRAS!$B$3:$B$4997,"<="&IF($F$4="",DATE(2999,12,31),$F$4)),0)) -> 57717.359
N69: =PROVEEDORES!A70 -> 0 | O69: =PROVEEDORES!B70 -> 0 | P69: =IF(N69<>"",SUMIFS(COMPRAS!$J$3:$J$4997,COMPRAS!$D$3:$D$4997,N69,COMPRAS!$B$3:$B$4997,">="&IF($C$4="",DATE(1900,1,1),$C$4),COMPRAS!$B$3:$B$4997,"<="&IF($F$4="",DATE(2999,12,31),$F$4)),0) -> 0 | Q69: =IF(N69<>"",SUMIFS(COMPRAS!$O$3:$O$4997,COMPRAS!$D$3:$D$4997,N69,COMPRAS!$B$3:$B$4997,">="&IF($C$4="",DATE(1900,1,1),$C$4),COMPRAS!$B$3:$B$4997,"<="&IF($F$4="",DATE(2999,12,31),$F$4)),0) -> 0 | S69: =PRODUCTOS!A70 -> C220 | T69: =PRODUCTOS!B70 -> LIRIO EN FILETES | U69: =IF(S69<>"",SUMIFS(COMPRAS!$J$3:$J$4997,COMPRAS!$G$3:$G$4997,S69,COMPRAS!$B$3:$B$4997,">="&IF($C$4="",DATE(1900,1,1),$C$4),COMPRAS!$B$3:$B$4997,"<="&IF($F$4="",DATE(2999,12,31),$F$4)),0) -> 202 | V69: =IF(S69<>"",SUMIFS(COMPRAS!$O$3:$O$4997,COMPRAS!$G$3:$G$4997,S69,COMPRAS!$B$3:$B$4997,">="&IF($C$4="",DATE(1900,1,1),$C$4),COMPRAS!$B$3:$B$4997,"<="&IF($F$4="",DATE(2999,12,31),$F$4)),0) -> 893.8 | Y69: =IF($X$2="TODOS",U69,IF(S69<>"",SUMIFS(COMPRAS!$J$3:$J$4997,COMPRAS!$G$3:$G$4997,S69,COMPRAS!$D$3:$D$4997,$X$2,COMPRAS!$B$3:$B$4997,">="&IF($C$4="",DATE(1900,1,1),$C$4),COMPRAS!$B$3:$B$4997,"<="&IF($F$4="",DATE(2999,12,31),$F$4)),0)) -> 202 | Z69: =IF($X$2="TODOS",V69,IF(S69<>"",SUMIFS(COMPRAS!$O$3:$O$4997,COMPRAS!$G$3:$G$4997,S69,COMPRAS!$D$3:$D$4997,$X$2,COMPRAS!$B$3:$B$4997,">="&IF($C$4="",DATE(1900,1,1),$C$4),COMPRAS!$B$3:$B$4997,"<="&IF($F$4="",DATE(2999,12,31),$F$4)),0)) -> 893.8
N70: =PROVEEDORES!A71 -> 0 | O70: =PROVEEDORES!B71 -> 0 | P70: =IF(N70<>"",SUMIFS(COMPRAS!$J$3:$J$4997,COMPRAS!$D$3:$D$4997,N70,COMPRAS!$B$3:$B$4997,">="&IF($C$4="",DATE(1900,1,1),$C$4),COMPRAS!$B$3:$B$4997,"<="&IF($F$4="",DATE(2999,12,31),$F$4)),0) -> 0 | Q70: =IF(N70<>"",SUMIFS(COMPRAS!$O$3:$O$4997,COMPRAS!$D$3:$D$4997,N70,COMPRAS!$B$3:$B$4997,">="&IF($C$4="",DATE(1900,1,1),$C$4),COMPRAS!$B$3:$B$4997,"<="&IF($F$4="",DATE(2999,12,31),$F$4)),0) -> 0 | S70: =PRODUCTOS!A71 -> C336 | T70: =PRODUCTOS!B71 -> LUBINA RIA/ ROBALIZA (BSS) | U70: =IF(S70<>"",SUMIFS(COMPRAS!$J$3:$J$4997,COMPRAS!$G$3:$G$4997,S70,COMPRAS!$B$3:$B$4997,">="&IF($C$4="",DATE(1900,1,1),$C$4),COMPRAS!$B$3:$B$4997,"<="&IF($F$4="",DATE(2999,12,31),$F$4)),0) -> 867.14 | V70: =IF(S70<>"",SUMIFS(COMPRAS!$O$3:$O$4997,COMPRAS!$G$3:$G$4997,S70,COMPRAS!$B$3:$B$4997,">="&IF($C$4="",DATE(1900,1,1),$C$4),COMPRAS!$B$3:$B$4997,"<="&IF($F$4="",DATE(2999,12,31),$F$4)),0) -> 16171.083 | Y70: =IF($X$2="TODOS",U70,IF(S70<>"",SUMIFS(COMPRAS!$J$3:$J$4997,COMPRAS!$G$3:$G$4997,S70,COMPRAS!$D$3:$D$4997,$X$2,COMPRAS!$B$3:$B$4997,">="&IF($C$4="",DATE(1900,1,1),$C$4),COMPRAS!$B$3:$B$4997,"<="&IF($F$4="",DATE(2999,12,31),$F$4)),0)) -> 867.14 | Z70: =IF($X$2="TODOS",V70,IF(S70<>"",SUMIFS(COMPRAS!$O$3:$O$4997,COMPRAS!$G$3:$G$4997,S70,COMPRAS!$D$3:$D$4997,$X$2,COMPRAS!$B$3:$B$4997,">="&IF($C$4="",DATE(1900,1,1),$C$4),COMPRAS!$B$3:$B$4997,"<="&IF($F$4="",DATE(2999,12,31),$F$4)),0)) -> 16171.083
N71: =PROVEEDORES!A72 -> 0 | O71: =PROVEEDORES!B72 -> 0 | P71: =IF(N71<>"",SUMIFS(COMPRAS!$J$3:$J$4997,COMPRAS!$D$3:$D$4997,N71,COMPRAS!$B$3:$B$4997,">="&IF($C$4="",DATE(1900,1,1),$C$4),COMPRAS!$B$3:$B$4997,"<="&IF($F$4="",DATE(2999,12,31),$F$4)),0) -> 0 | Q71: =IF(N71<>"",SUMIFS(COMPRAS!$O$3:$O$4997,COMPRAS!$D$3:$D$4997,N71,COMPRAS!$B$3:$B$4997,">="&IF($C$4="",DATE(1900,1,1),$C$4),COMPRAS!$B$3:$B$4997,"<="&IF($F$4="",DATE(2999,12,31),$F$4)),0) -> 0 | S71: =PRODUCTOS!A72 -> C3110 | T71: =PRODUCTOS!B72 -> MACHOS/ REYES/ ALFONSINOS (BYS) | U71: =IF(S71<>"",SUMIFS(COMPRAS!$J$3:$J$4997,COMPRAS!$G$3:$G$4997,S71,COMPRAS!$B$3:$B$4997,">="&IF($C$4="",DATE(1900,1,1),$C$4),COMPRAS!$B$3:$B$4997,"<="&IF($F$4="",DATE(2999,12,31),$F$4)),0) -> 71.8 | V71: =IF(S71<>"",SUMIFS(COMPRAS!$O$3:$O$4997,COMPRAS!$G$3:$G$4997,S71,COMPRAS!$B$3:$B$4997,">="&IF($C$4="",DATE(1900,1,1),$C$4),COMPRAS!$B$3:$B$4997,"<="&IF($F$4="",DATE(2999,12,31),$F$4)),0) -> 1298.1965 | Y71: =IF($X$2="TODOS",U71,IF(S71<>"",SUMIFS(COMPRAS!$J$3:$J$4997,COMPRAS!$G$3:$G$4997,S71,COMPRAS!$D$3:$D$4997,$X$2,COMPRAS!$B$3:$B$4997,">="&IF($C$4="",DATE(1900,1,1),$C$4),COMPRAS!$B$3:$B$4997,"<="&IF($F$4="",DATE(2999,12,31),$F$4)),0)) -> 71.8 | Z71: =IF($X$2="TODOS",V71,IF(S71<>"",SUMIFS(COMPRAS!$O$3:$O$4997,COMPRAS!$G$3:$G$4997,S71,COMPRAS!$D$3:$D$4997,$X$2,COMPRAS!$B$3:$B$4997,">="&IF($C$4="",DATE(1900,1,1),$C$4),COMPRAS!$B$3:$B$4997,"<="&IF($F$4="",DATE(2999,12,31),$F$4)),0)) -> 1298.1965
N72: =PROVEEDORES!A73 -> 0 | O72: =PROVEEDORES!B73 -> 0 | P72: =IF(N72<>"",SUMIFS(COMPRAS!$J$3:$J$4997,COMPRAS!$D$3:$D$4997,N72,COMPRAS!$B$3:$B$4997,">="&IF($C$4="",DATE(1900,1,1),$C$4),COMPRAS!$B$3:$B$4997,"<="&IF($F$4="",DATE(2999,12,31),$F$4)),0) -> 0 | Q72: =IF(N72<>"",SUMIFS(COMPRAS!$O$3:$O$4997,COMPRAS!$D$3:$D$4997,N72,COMPRAS!$B$3:$B$4997,">="&IF($C$4="",DATE(1900,1,1),$C$4),COMPRAS!$B$3:$B$4997,"<="&IF($F$4="",DATE(2999,12,31),$F$4)),0) -> 0 | S72: =PRODUCTOS!A73 -> C755 | T72: =PRODUCTOS!B73 -> MARAGOTA/ PINTO (USB) | U72: =IF(S72<>"",SUMIFS(COMPRAS!$J$3:$J$4997,COMPRAS!$G$3:$G$4997,S72,COMPRAS!$B$3:$B$4997,">="&IF($C$4="",DATE(1900,1,1),$C$4),COMPRAS!$B$3:$B$4997,"<="&IF($F$4="",DATE(2999,12,31),$F$4)),0) -> 0 | V72: =IF(S72<>"",SUMIFS(COMPRAS!$O$3:$O$4997,COMPRAS!$G$3:$G$4997,S72,COMPRAS!$B$3:$B$4997,">="&IF($C$4="",DATE(1900,1,1),$C$4),COMPRAS!$B$3:$B$4997,"<="&IF($F$4="",DATE(2999,12,31),$F$4)),0) -> 0 | Y72: =IF($X$2="TODOS",U72,IF(S72<>"",SUMIFS(COMPRAS!$J$3:$J$4997,COMPRAS!$G$3:$G$4997,S72,COMPRAS!$D$3:$D$4997,$X$2,COMPRAS!$B$3:$B$4997,">="&IF($C$4="",DATE(1900,1,1),$C$4),COMPRAS!$B$3:$B$4997,"<="&IF($F$4="",DATE(2999,12,31),$F$4)),0)) -> 0 | Z72: =IF($X$2="TODOS",V72,IF(S72<>"",SUMIFS(COMPRAS!$O$3:$O$4997,COMPRAS!$G$3:$G$4997,S72,COMPRAS!$D$3:$D$4997,$X$2,COMPRAS!$B$3:$B$4997,">="&IF($C$4="",DATE(1900,1,1),$C$4),COMPRAS!$B$3:$B$4997,"<="&IF($F$4="",DATE(2999,12,31),$F$4)),0)) -> 0
N73: =PROVEEDORES!A74 -> 0 | O73: =PROVEEDORES!B74 -> 0 | P73: =IF(N73<>"",SUMIFS(COMPRAS!$J$3:$J$4997,COMPRAS!$D$3:$D$4997,N73,COMPRAS!$B$3:$B$4997,">="&IF($C$4="",DATE(1900,1,1),$C$4),COMPRAS!$B$3:$B$4997,"<="&IF($F$4="",DATE(2999,12,31),$F$4)),0) -> 0 | Q73: =IF(N73<>"",SUMIFS(COMPRAS!$O$3:$O$4997,COMPRAS!$D$3:$D$4997,N73,COMPRAS!$B$3:$B$4997,">="&IF($C$4="",DATE(1900,1,1),$C$4),COMPRAS!$B$3:$B$4997,"<="&IF($F$4="",DATE(2999,12,31),$F$4)),0) -> 0 | S73: =PRODUCTOS!A74 -> C1400 | T73: =PRODUCTOS!B74 -> MERLUZA AMERICANA/ CARIOCA BOSTON (HKS) | U73: =IF(S73<>"",SUMIFS(COMPRAS!$J$3:$J$4997,COMPRAS!$G$3:$G$4997,S73,COMPRAS!$B$3:$B$4997,">="&IF($C$4="",DATE(1900,1,1),$C$4),COMPRAS!$B$3:$B$4997,"<="&IF($F$4="",DATE(2999,12,31),$F$4)),0) -> 0 | V73: =IF(S73<>"",SUMIFS(COMPRAS!$O$3:$O$4997,COMPRAS!$G$3:$G$4997,S73,COMPRAS!$B$3:$B$4997,">="&IF($C$4="",DATE(1900,1,1),$C$4),COMPRAS!$B$3:$B$4997,"<="&IF($F$4="",DATE(2999,12,31),$F$4)),0) -> 0 | Y73: =IF($X$2="TODOS",U73,IF(S73<>"",SUMIFS(COMPRAS!$J$3:$J$4997,COMPRAS!$G$3:$G$4997,S73,COMPRAS!$D$3:$D$4997,$X$2,COMPRAS!$B$3:$B$4997,">="&IF($C$4="",DATE(1900,1,1),$C$4),COMPRAS!$B$3:$B$4997,"<="&IF($F$4="",DATE(2999,12,31),$F$4)),0)) -> 0 | Z73: =IF($X$2="TODOS",V73,IF(S73<>"",SUMIFS(COMPRAS!$O$3:$O$4997,COMPRAS!$G$3:$G$4997,S73,COMPRAS!$D$3:$D$4997,$X$2,COMPRAS!$B$3:$B$4997,">="&IF($C$4="",DATE(1900,1,1),$C$4),COMPRAS!$B$3:$B$4997,"<="&IF($F$4="",DATE(2999,12,31),$F$4)),0)) -> 0
N74: =PROVEEDORES!A75 -> 0 | O74: =PROVEEDORES!B75 -> 0 | P74: =IF(N74<>"",SUMIFS(COMPRAS!$J$3:$J$4997,COMPRAS!$D$3:$D$4997,N74,COMPRAS!$B$3:$B$4997,">="&IF($C$4="",DATE(1900,1,1),$C$4),COMPRAS!$B$3:$B$4997,"<="&IF($F$4="",DATE(2999,12,31),$F$4)),0) -> 0 | Q74: =IF(N74<>"",SUMIFS(COMPRAS!$O$3:$O$4997,COMPRAS!$D$3:$D$4997,N74,COMPRAS!$B$3:$B$4997,">="&IF($C$4="",DATE(1900,1,1),$C$4),COMPRAS!$B$3:$B$4997,"<="&IF($F$4="",DATE(2999,12,31),$F$4)),0) -> 0 | S74: =PRODUCTOS!A75 -> C1250 | T74: =PRODUCTOS!B75 -> MERLUZA DEL CABO (HKC) | U74: =IF(S74<>"",SUMIFS(COMPRAS!$J$3:$J$4997,COMPRAS!$G$3:$G$4997,S74,COMPRAS!$B$3:$B$4997,">="&IF($C$4="",DATE(1900,1,1),$C$4),COMPRAS!$B$3:$B$4997,"<="&IF($F$4="",DATE(2999,12,31),$F$4)),0) -> 0 | V74: =IF(S74<>"",SUMIFS(COMPRAS!$O$3:$O$4997,COMPRAS!$G$3:$G$4997,S74,COMPRAS!$B$3:$B$4997,">="&IF($C$4="",DATE(1900,1,1),$C$4),COMPRAS!$B$3:$B$4997,"<="&IF($F$4="",DATE(2999,12,31),$F$4)),0) -> 0 | Y74: =IF($X$2="TODOS",U74,IF(S74<>"",SUMIFS(COMPRAS!$J$3:$J$4997,COMPRAS!$G$3:$G$4997,S74,COMPRAS!$D$3:$D$4997,$X$2,COMPRAS!$B$3:$B$4997,">="&IF($C$4="",DATE(1900,1,1),$C$4),COMPRAS!$B$3:$B$4997,"<="&IF($F$4="",DATE(2999,12,31),$F$4)),0)) -> 0 | Z74: =IF($X$2="TODOS",V74,IF(S74<>"",SUMIFS(COMPRAS!$O$3:$O$4997,COMPRAS!$G$3:$G$4997,S74,COMPRAS!$D$3:$D$4997,$X$2,COMPRAS!$B$3:$B$4997,">="&IF($C$4="",DATE(1900,1,1),$C$4),COMPRAS!$B$3:$B$4997,"<="&IF($F$4="",DATE(2999,12,31),$F$4)),0)) -> 0
N75: =PROVEEDORES!A76 -> 0 | O75: =PROVEEDORES!B76 -> 0 | P75: =IF(N75<>"",SUMIFS(COMPRAS!$J$3:$J$4997,COMPRAS!$D$3:$D$4997,N75,COMPRAS!$B$3:$B$4997,">="&IF($C$4="",DATE(1900,1,1),$C$4),COMPRAS!$B$3:$B$4997,"<="&IF($F$4="",DATE(2999,12,31),$F$4)),0) -> 0 | Q75: =IF(N75<>"",SUMIFS(COMPRAS!$O$3:$O$4997,COMPRAS!$D$3:$D$4997,N75,COMPRAS!$B$3:$B$4997,">="&IF($C$4="",DATE(1900,1,1),$C$4),COMPRAS!$B$3:$B$4997,"<="&IF($F$4="",DATE(2999,12,31),$F$4)),0) -> 0 | S75: =PRODUCTOS!A76 -> C1730 | T75: =PRODUCTOS!B76 -> MERLUZA EUROPEA ARRASTRE (HKE) | U75: =IF(S75<>"",SUMIFS(COMPRAS!$J$3:$J$4997,COMPRAS!$G$3:$G$4997,S75,COMPRAS!$B$3:$B$4997,">="&IF($C$4="",DATE(1900,1,1),$C$4),COMPRAS!$B$3:$B$4997,"<="&IF($F$4="",DATE(2999,12,31),$F$4)),0) -> 3583.45 | V75: =IF(S75<>"",SUMIFS(COMPRAS!$O$3:$O$4997,COMPRAS!$G$3:$G$4997,S75,COMPRAS!$B$3:$B$4997,">="&IF($C$4="",DATE(1900,1,1),$C$4),COMPRAS!$B$3:$B$4997,"<="&IF($F$4="",DATE(2999,12,31),$F$4)),0) -> 11270.299 | Y75: =IF($X$2="TODOS",U75,IF(S75<>"",SUMIFS(COMPRAS!$J$3:$J$4997,COMPRAS!$G$3:$G$4997,S75,COMPRAS!$D$3:$D$4997,$X$2,COMPRAS!$B$3:$B$4997,">="&IF($C$4="",DATE(1900,1,1),$C$4),COMPRAS!$B$3:$B$4997,"<="&IF($F$4="",DATE(2999,12,31),$F$4)),0)) -> 3583.45 | Z75: =IF($X$2="TODOS",V75,IF(S75<>"",SUMIFS(COMPRAS!$O$3:$O$4997,COMPRAS!$G$3:$G$4997,S75,COMPRAS!$D$3:$D$4997,$X$2,COMPRAS!$B$3:$B$4997,">="&IF($C$4="",DATE(1900,1,1),$C$4),COMPRAS!$B$3:$B$4997,"<="&IF($F$4="",DATE(2999,12,31),$F$4)),0)) -> 11270.299
N76: =PROVEEDORES!A77 -> 0 | O76: =PROVEEDORES!B77 -> 0 | P76: =IF(N76<>"",SUMIFS(COMPRAS!$J$3:$J$4997,COMPRAS!$D$3:$D$4997,N76,COMPRAS!$B$3:$B$4997,">="&IF($C$4="",DATE(1900,1,1),$C$4),COMPRAS!$B$3:$B$4997,"<="&IF($F$4="",DATE(2999,12,31),$F$4)),0) -> 0 | Q76: =IF(N76<>"",SUMIFS(COMPRAS!$O$3:$O$4997,COMPRAS!$D$3:$D$4997,N76,COMPRAS!$B$3:$B$4997,">="&IF($C$4="",DATE(1900,1,1),$C$4),COMPRAS!$B$3:$B$4997,"<="&IF($F$4="",DATE(2999,12,31),$F$4)),0) -> 0 | S76: =PRODUCTOS!A77 -> C17308 | T76: =PRODUCTOS!B77 -> MERLUZA EUROPEA ARRASTRE (HKE) 800/1000 | U76: =IF(S76<>"",SUMIFS(COMPRAS!$J$3:$J$4997,COMPRAS!$G$3:$G$4997,S76,COMPRAS!$B$3:$B$4997,">="&IF($C$4="",DATE(1900,1,1),$C$4),COMPRAS!$B$3:$B$4997,"<="&IF($F$4="",DATE(2999,12,31),$F$4)),0) -> 0 | V76: =IF(S76<>"",SUMIFS(COMPRAS!$O$3:$O$4997,COMPRAS!$G$3:$G$4997,S76,COMPRAS!$B$3:$B$4997,">="&IF($C$4="",DATE(1900,1,1),$C$4),COMPRAS!$B$3:$B$4997,"<="&IF($F$4="",DATE(2999,12,31),$F$4)),0) -> 0 | Y76: =IF($X$2="TODOS",U76,IF(S76<>"",SUMIFS(COMPRAS!$J$3:$J$4997,COMPRAS!$G$3:$G$4997,S76,COMPRAS!$D$3:$D$4997,$X$2,COMPRAS!$B$3:$B$4997,">="&IF($C$4="",DATE(1900,1,1),$C$4),COMPRAS!$B$3:$B$4997,"<="&IF($F$4="",DATE(2999,12,31),$F$4)),0)) -> 0 | Z76: =IF($X$2="TODOS",V76,IF(S76<>"",SUMIFS(COMPRAS!$O$3:$O$4997,COMPRAS!$G$3:$G$4997,S76,COMPRAS!$D$3:$D$4997,$X$2,COMPRAS!$B$3:$B$4997,">="&IF($C$4="",DATE(1900,1,1),$C$4),COMPRAS!$B$3:$B$4997,"<="&IF($F$4="",DATE(2999,12,31),$F$4)),0)) -> 0
N77: =PROVEEDORES!A78 -> 0 | O77: =PROVEEDORES!B78 -> 0 | P77: =IF(N77<>"",SUMIFS(COMPRAS!$J$3:$J$4997,COMPRAS!$D$3:$D$4997,N77,COMPRAS!$B$3:$B$4997,">="&IF($C$4="",DATE(1900,1,1),$C$4),COMPRAS!$B$3:$B$4997,"<="&IF($F$4="",DATE(2999,12,31),$F$4)),0) -> 0 | Q77: =IF(N77<>"",SUMIFS(COMPRAS!$O$3:$O$4997,COMPRAS!$D$3:$D$4997,N77,COMPRAS!$B$3:$B$4997,">="&IF($C$4="",DATE(1900,1,1),$C$4),COMPRAS!$B$3:$B$4997,"<="&IF($F$4="",DATE(2999,12,31),$F$4)),0) -> 0 | S77: =PRODUCTOS!A78 -> C17301 | T77: =PRODUCTOS!B78 -> MERLUZA EUROPEA ARRASTRE (HKE) 1000/1250 | U77: =IF(S77<>"",SUMIFS(COMPRAS!$J$3:$J$4997,COMPRAS!$G$3:$G$4997,S77,COMPRAS!$B$3:$B$4997,">="&IF($C$4="",DATE(1900,1,1),$C$4),COMPRAS!$B$3:$B$4997,"<="&IF($F$4="",DATE(2999,12,31),$F$4)),0) -> 0 | V77: =IF(S77<>"",SUMIFS(COMPRAS!$O$3:$O$4997,COMPRAS!$G$3:$G$4997,S77,COMPRAS!$B$3:$B$4997,">="&IF($C$4="",DATE(1900,1,1),$C$4),COMPRAS!$B$3:$B$4997,"<="&IF($F$4="",DATE(2999,12,31),$F$4)),0) -> 0 | Y77: =IF($X$2="TODOS",U77,IF(S77<>"",SUMIFS(COMPRAS!$J$3:$J$4997,COMPRAS!$G$3:$G$4997,S77,COMPRAS!$D$3:$D$4997,$X$2,COMPRAS!$B$3:$B$4997,">="&IF($C$4="",DATE(1900,1,1),$C$4),COMPRAS!$B$3:$B$4997,"<="&IF($F$4="",DATE(2999,12,31),$F$4)),0)) -> 0 | Z77: =IF($X$2="TODOS",V77,IF(S77<>"",SUMIFS(COMPRAS!$O$3:$O$4997,COMPRAS!$G$3:$G$4997,S77,COMPRAS!$D$3:$D$4997,$X$2,COMPRAS!$B$3:$B$4997,">="&IF($C$4="",DATE(1900,1,1),$C$4),COMPRAS!$B$3:$B$4997,"<="&IF($F$4="",DATE(2999,12,31),$F$4)),0)) -> 0
... N206: =PROVEEDORES!A207 -> 0 | O206: =PROVEEDORES!B207 -> 0 | P206: =IF(N206<>"",SUMIFS(COMPRAS!$J$3:$J$4997,COMPRAS!$D$3:$D$4997,N206,COMPRAS!$B$3:$B$4997,">="&IF($C$4="",DATE(1900,1,1),$C$4),COMPRAS!$B$3:$B$4997,"<="&IF($F$4="",DATE(2999,12,31),$F$4)),0) -> 0 | Q206: =IF(N206<>"",SUMIFS(COMPRAS!$O$3:$O$4997,COMPRAS!$D$3:$D$4997,N206,COMPRAS!$B$3:$B$4997,">="&IF($C$4="",DATE(1900,1,1),$C$4),COMPRAS!$B$3:$B$4997,"<="&IF($F$4="",DATE(2999,12,31),$F$4)),0) -> 0 | S206: =PRODUCTOS!A207 -> 0 | T206: =PRODUCTOS!B207 -> 0 | U206: =IF(S206<>"",SUMIFS(COMPRAS!$J$3:$J$4997,COMPRAS!$G$3:$G$4997,S206,COMPRAS!$B$3:$B$4997,">="&IF($C$4="",DATE(1900,1,1),$C$4),COMPRAS!$B$3:$B$4997,"<="&IF($F$4="",DATE(2999,12,31),$F$4)),0) -> 0 | V206: =IF(S206<>"",SUMIFS(COMPRAS!$O$3:$O$4997,COMPRAS!$G$3:$G$4997,S206,COMPRAS!$B$3:$B$4997,">="&IF($C$4="",DATE(1900,1,1),$C$4),COMPRAS!$B$3:$B$4997,"<="&IF($F$4="",DATE(2999,12,31),$F$4)),0) -> 0 | Y206: =IF($X$2="TODOS",U206,IF(S206<>"",SUMIFS(COMPRAS!$J$3:$J$4997,COMPRAS!$G$3:$G$4997,S206,COMPRAS!$D$3:$D$4997,$X$2,COMPRAS!$B$3:$B$4997,">="&IF($C$4="",DATE(1900,1,1),$C$4),COMPRAS!$B$3:$B$4997,"<="&IF($F$4="",DATE(2999,12,31),$F$4)),0)) -> 0 | Z206: =IF($X$2="TODOS",V206,IF(S206<>"",SUMIFS(COMPRAS!$O$3:$O$4997,COMPRAS!$G$3:$G$4997,S206,COMPRAS!$D$3:$D$4997,$X$2,COMPRAS!$B$3:$B$4997,">="&IF($C$4="",DATE(1900,1,1),$C$4),COMPRAS!$B$3:$B$4997,"<="&IF($F$4="",DATE(2999,12,31),$F$4)),0)) -> 0
S207: =PRODUCTOS!A208 -> 0 | T207: =PRODUCTOS!B208 -> 0 | U207: =IF(S207<>"",SUMIFS(COMPRAS!$J$3:$J$4997,COMPRAS!$G$3:$G$4997,S207,COMPRAS!$B$3:$B$4997,">="&IF($C$4="",DATE(1900,1,1),$C$4),COMPRAS!$B$3:$B$4997,"<="&IF($F$4="",DATE(2999,12,31),$F$4)),0) -> 0 | V207: =IF(S207<>"",SUMIFS(COMPRAS!$O$3:$O$4997,COMPRAS!$G$3:$G$4997,S207,COMPRAS!$B$3:$B$4997,">="&IF($C$4="",DATE(1900,1,1),$C$4),COMPRAS!$B$3:$B$4997,"<="&IF($F$4="",DATE(2999,12,31),$F$4)),0) -> 0 | Y207: =IF($X$2="TODOS",U207,IF(S207<>"",SUMIFS(COMPRAS!$J$3:$J$4997,COMPRAS!$G$3:$G$4997,S207,COMPRAS!$D$3:$D$4997,$X$2,COMPRAS!$B$3:$B$4997,">="&IF($C$4="",DATE(1900,1,1),$C$4),COMPRAS!$B$3:$B$4997,"<="&IF($F$4="",DATE(2999,12,31),$F$4)),0)) -> 0 | Z207: =IF($X$2="TODOS",V207,IF(S207<>"",SUMIFS(COMPRAS!$O$3:$O$4997,COMPRAS!$G$3:$G$4997,S207,COMPRAS!$D$3:$D$4997,$X$2,COMPRAS!$B$3:$B$4997,">="&IF($C$4="",DATE(1900,1,1),$C$4),COMPRAS!$B$3:$B$4997,"<="&IF($F$4="",DATE(2999,12,31),$F$4)),0)) -> 0
S208: =PRODUCTOS!A209 -> 0 | T208: =PRODUCTOS!B209 -> 0 | U208: =IF(S208<>"",SUMIFS(COMPRAS!$J$3:$J$4997,COMPRAS!$G$3:$G$4997,S208,COMPRAS!$B$3:$B$4997,">="&IF($C$4="",DATE(1900,1,1),$C$4),COMPRAS!$B$3:$B$4997,"<="&IF($F$4="",DATE(2999,12,31),$F$4)),0) -> 0 | V208: =IF(S208<>"",SUMIFS(COMPRAS!$O$3:$O$4997,COMPRAS!$G$3:$G$4997,S208,COMPRAS!$B$3:$B$4997,">="&IF($C$4="",DATE(1900,1,1),$C$4),COMPRAS!$B$3:$B$4997,"<="&IF($F$4="",DATE(2999,12,31),$F$4)),0) -> 0 | Y208: =IF($X$2="TODOS",U208,IF(S208<>"",SUMIFS(COMPRAS!$J$3:$J$4997,COMPRAS!$G$3:$G$4997,S208,COMPRAS!$D$3:$D$4997,$X$2,COMPRAS!$B$3:$B$4997,">="&IF($C$4="",DATE(1900,1,1),$C$4),COMPRAS!$B$3:$B$4997,"<="&IF($F$4="",DATE(2999,12,31),$F$4)),0)) -> 0 | Z208: =IF($X$2="TODOS",V208,IF(S208<>"",SUMIFS(COMPRAS!$O$3:$O$4997,COMPRAS!$G$3:$G$4997,S208,COMPRAS!$D$3:$D$4997,$X$2,COMPRAS!$B$3:$B$4997,">="&IF($C$4="",DATE(1900,1,1),$C$4),COMPRAS!$B$3:$B$4997,"<="&IF($F$4="",DATE(2999,12,31),$F$4)),0)) -> 0
S209: =PRODUCTOS!A210 -> 0 | T209: =PRODUCTOS!B210 -> 0 | U209: =IF(S209<>"",SUMIFS(COMPRAS!$J$3:$J$4997,COMPRAS!$G$3:$G$4997,S209,COMPRAS!$B$3:$B$4997,">="&IF($C$4="",DATE(1900,1,1),$C$4),COMPRAS!$B$3:$B$4997,"<="&IF($F$4="",DATE(2999,12,31),$F$4)),0) -> 0 | V209: =IF(S209<>"",SUMIFS(COMPRAS!$O$3:$O$4997,COMPRAS!$G$3:$G$4997,S209,COMPRAS!$B$3:$B$4997,">="&IF($C$4="",DATE(1900,1,1),$C$4),COMPRAS!$B$3:$B$4997,"<="&IF($F$4="",DATE(2999,12,31),$F$4)),0) -> 0 | Y209: =IF($X$2="TODOS",U209,IF(S209<>"",SUMIFS(COMPRAS!$J$3:$J$4997,COMPRAS!$G$3:$G$4997,S209,COMPRAS!$D$3:$D$4997,$X$2,COMPRAS!$B$3:$B$4997,">="&IF($C$4="",DATE(1900,1,1),$C$4),COMPRAS!$B$3:$B$4997,"<="&IF($F$4="",DATE(2999,12,31),$F$4)),0)) -> 0 | Z209: =IF($X$2="TODOS",V209,IF(S209<>"",SUMIFS(COMPRAS!$O$3:$O$4997,COMPRAS!$G$3:$G$4997,S209,COMPRAS!$D$3:$D$4997,$X$2,COMPRAS!$B$3:$B$4997,">="&IF($C$4="",DATE(1900,1,1),$C$4),COMPRAS!$B$3:$B$4997,"<="&IF($F$4="",DATE(2999,12,31),$F$4)),0)) -> 0
S210: =PRODUCTOS!A211 -> 0 | T210: =PRODUCTOS!B211 -> 0 | U210: =IF(S210<>"",SUMIFS(COMPRAS!$J$3:$J$4997,COMPRAS!$G$3:$G$4997,S210,COMPRAS!$B$3:$B$4997,">="&IF($C$4="",DATE(1900,1,1),$C$4),COMPRAS!$B$3:$B$4997,"<="&IF($F$4="",DATE(2999,12,31),$F$4)),0) -> 0 | V210: =IF(S210<>"",SUMIFS(COMPRAS!$O$3:$O$4997,COMPRAS!$G$3:$G$4997,S210,COMPRAS!$B$3:$B$4997,">="&IF($C$4="",DATE(1900,1,1),$C$4),COMPRAS!$B$3:$B$4997,"<="&IF($F$4="",DATE(2999,12,31),$F$4)),0) -> 0 | Y210: =IF($X$2="TODOS",U210,IF(S210<>"",SUMIFS(COMPRAS!$J$3:$J$4997,COMPRAS!$G$3:$G$4997,S210,COMPRAS!$D$3:$D$4997,$X$2,COMPRAS!$B$3:$B$4997,">="&IF($C$4="",DATE(1900,1,1),$C$4),COMPRAS!$B$3:$B$4997,"<="&IF($F$4="",DATE(2999,12,31),$F$4)),0)) -> 0 | Z210: =IF($X$2="TODOS",V210,IF(S210<>"",SUMIFS(COMPRAS!$O$3:$O$4997,COMPRAS!$G$3:$G$4997,S210,COMPRAS!$D$3:$D$4997,$X$2,COMPRAS!$B$3:$B$4997,">="&IF($C$4="",DATE(1900,1,1),$C$4),COMPRAS!$B$3:$B$4997,"<="&IF($F$4="",DATE(2999,12,31),$F$4)),0)) -> 0
S211: =PRODUCTOS!A212 -> 0 | T211: =PRODUCTOS!B212 -> 0 | U211: =IF(S211<>"",SUMIFS(COMPRAS!$J$3:$J$4997,COMPRAS!$G$3:$G$4997,S211,COMPRAS!$B$3:$B$4997,">="&IF($C$4="",DATE(1900,1,1),$C$4),COMPRAS!$B$3:$B$4997,"<="&IF($F$4="",DATE(2999,12,31),$F$4)),0) -> 0 | V211: =IF(S211<>"",SUMIFS(COMPRAS!$O$3:$O$4997,COMPRAS!$G$3:$G$4997,S211,COMPRAS!$B$3:$B$4997,">="&IF($C$4="",DATE(1900,1,1),$C$4),COMPRAS!$B$3:$B$4997,"<="&IF($F$4="",DATE(2999,12,31),$F$4)),0) -> 0 | Y211: =IF($X$2="TODOS",U211,IF(S211<>"",SUMIFS(COMPRAS!$J$3:$J$4997,COMPRAS!$G$3:$G$4997,S211,COMPRAS!$D$3:$D$4997,$X$2,COMPRAS!$B$3:$B$4997,">="&IF($C$4="",DATE(1900,1,1),$C$4),COMPRAS!$B$3:$B$4997,"<="&IF($F$4="",DATE(2999,12,31),$F$4)),0)) -> 0 | Z211: =IF($X$2="TODOS",V211,IF(S211<>"",SUMIFS(COMPRAS!$O$3:$O$4997,COMPRAS!$G$3:$G$4997,S211,COMPRAS!$D$3:$D$4997,$X$2,COMPRAS!$B$3:$B$4997,">="&IF($C$4="",DATE(1900,1,1),$C$4),COMPRAS!$B$3:$B$4997,"<="&IF($F$4="",DATE(2999,12,31),$F$4)),0)) -> 0
S212: =PRODUCTOS!A213 -> 0 | T212: =PRODUCTOS!B213 -> 0 | U212: =IF(S212<>"",SUMIFS(COMPRAS!$J$3:$J$4997,COMPRAS!$G$3:$G$4997,S212,COMPRAS!$B$3:$B$4997,">="&IF($C$4="",DATE(1900,1,1),$C$4),COMPRAS!$B$3:$B$4997,"<="&IF($F$4="",DATE(2999,12,31),$F$4)),0) -> 0 | V212: =IF(S212<>"",SUMIFS(COMPRAS!$O$3:$O$4997,COMPRAS!$G$3:$G$4997,S212,COMPRAS!$B$3:$B$4997,">="&IF($C$4="",DATE(1900,1,1),$C$4),COMPRAS!$B$3:$B$4997,"<="&IF($F$4="",DATE(2999,12,31),$F$4)),0) -> 0 | Y212: =IF($X$2="TODOS",U212,IF(S212<>"",SUMIFS(COMPRAS!$J$3:$J$4997,COMPRAS!$G$3:$G$4997,S212,COMPRAS!$D$3:$D$4997,$X$2,COMPRAS!$B$3:$B$4997,">="&IF($C$4="",DATE(1900,1,1),$C$4),COMPRAS!$B$3:$B$4997,"<="&IF($F$4="",DATE(2999,12,31),$F$4)),0)) -> 0 | Z212: =IF($X$2="TODOS",V212,IF(S212<>"",SUMIFS(COMPRAS!$O$3:$O$4997,COMPRAS!$G$3:$G$4997,S212,COMPRAS!$D$3:$D$4997,$X$2,COMPRAS!$B$3:$B$4997,">="&IF($C$4="",DATE(1900,1,1),$C$4),COMPRAS!$B$3:$B$4997,"<="&IF($F$4="",DATE(2999,12,31),$F$4)),0)) -> 0
S213: =PRODUCTOS!A214 -> 0 | T213: =PRODUCTOS!B214 -> 0 | U213: =IF(S213<>"",SUMIFS(COMPRAS!$J$3:$J$4997,COMPRAS!$G$3:$G$4997,S213,COMPRAS!$B$3:$B$4997,">="&IF($C$4="",DATE(1900,1,1),$C$4),COMPRAS!$B$3:$B$4997,"<="&IF($F$4="",DATE(2999,12,31),$F$4)),0) -> 0 | V213: =IF(S213<>"",SUMIFS(COMPRAS!$O$3:$O$4997,COMPRAS!$G$3:$G$4997,S213,COMPRAS!$B$3:$B$4997,">="&IF($C$4="",DATE(1900,1,1),$C$4),COMPRAS!$B$3:$B$4997,"<="&IF($F$4="",DATE(2999,12,31),$F$4)),0) -> 0 | Y213: =IF($X$2="TODOS",U213,IF(S213<>"",SUMIFS(COMPRAS!$J$3:$J$4997,COMPRAS!$G$3:$G$4997,S213,COMPRAS!$D$3:$D$4997,$X$2,COMPRAS!$B$3:$B$4997,">="&IF($C$4="",DATE(1900,1,1),$C$4),COMPRAS!$B$3:$B$4997,"<="&IF($F$4="",DATE(2999,12,31),$F$4)),0)) -> 0 | Z213: =IF($X$2="TODOS",V213,IF(S213<>"",SUMIFS(COMPRAS!$O$3:$O$4997,COMPRAS!$G$3:$G$4997,S213,COMPRAS!$D$3:$D$4997,$X$2,COMPRAS!$B$3:$B$4997,">="&IF($C$4="",DATE(1900,1,1),$C$4),COMPRAS!$B$3:$B$4997,"<="&IF($F$4="",DATE(2999,12,31),$F$4)),0)) -> 0
S214: =PRODUCTOS!A215 -> 0 | T214: =PRODUCTOS!B215 -> 0 | U214: =IF(S214<>"",SUMIFS(COMPRAS!$J$3:$J$4997,COMPRAS!$G$3:$G$4997,S214,COMPRAS!$B$3:$B$4997,">="&IF($C$4="",DATE(1900,1,1),$C$4),COMPRAS!$B$3:$B$4997,"<="&IF($F$4="",DATE(2999,12,31),$F$4)),0) -> 0 | V214: =IF(S214<>"",SUMIFS(COMPRAS!$O$3:$O$4997,COMPRAS!$G$3:$G$4997,S214,COMPRAS!$B$3:$B$4997,">="&IF($C$4="",DATE(1900,1,1),$C$4),COMPRAS!$B$3:$B$4997,"<="&IF($F$4="",DATE(2999,12,31),$F$4)),0) -> 0 | Y214: =IF($X$2="TODOS",U214,IF(S214<>"",SUMIFS(COMPRAS!$J$3:$J$4997,COMPRAS!$G$3:$G$4997,S214,COMPRAS!$D$3:$D$4997,$X$2,COMPRAS!$B$3:$B$4997,">="&IF($C$4="",DATE(1900,1,1),$C$4),COMPRAS!$B$3:$B$4997,"<="&IF($F$4="",DATE(2999,12,31),$F$4)),0)) -> 0 | Z214: =IF($X$2="TODOS",V214,IF(S214<>"",SUMIFS(COMPRAS!$O$3:$O$4997,COMPRAS!$G$3:$G$4997,S214,COMPRAS!$D$3:$D$4997,$X$2,COMPRAS!$B$3:$B$4997,">="&IF($C$4="",DATE(1900,1,1),$C$4),COMPRAS!$B$3:$B$4997,"<="&IF($F$4="",DATE(2999,12,31),$F$4)),0)) -> 0
S215: =PRODUCTOS!A216 -> 0 | T215: =PRODUCTOS!B216 -> 0 | U215: =IF(S215<>"",SUMIFS(COMPRAS!$J$3:$J$4997,COMPRAS!$G$3:$G$4997,S215,COMPRAS!$B$3:$B$4997,">="&IF($C$4="",DATE(1900,1,1),$C$4),COMPRAS!$B$3:$B$4997,"<="&IF($F$4="",DATE(2999,12,31),$F$4)),0) -> 0 | V215: =IF(S215<>"",SUMIFS(COMPRAS!$O$3:$O$4997,COMPRAS!$G$3:$G$4997,S215,COMPRAS!$B$3:$B$4997,">="&IF($C$4="",DATE(1900,1,1),$C$4),COMPRAS!$B$3:$B$4997,"<="&IF($F$4="",DATE(2999,12,31),$F$4)),0) -> 0 | Y215: =IF($X$2="TODOS",U215,IF(S215<>"",SUMIFS(COMPRAS!$J$3:$J$4997,COMPRAS!$G$3:$G$4997,S215,COMPRAS!$D$3:$D$4997,$X$2,COMPRAS!$B$3:$B$4997,">="&IF($C$4="",DATE(1900,1,1),$C$4),COMPRAS!$B$3:$B$4997,"<="&IF($F$4="",DATE(2999,12,31),$F$4)),0)) -> 0 | Z215: =IF($X$2="TODOS",V215,IF(S215<>"",SUMIFS(COMPRAS!$O$3:$O$4997,COMPRAS!$G$3:$G$4997,S215,COMPRAS!$D$3:$D$4997,$X$2,COMPRAS!$B$3:$B$4997,">="&IF($C$4="",DATE(1900,1,1),$C$4),COMPRAS!$B$3:$B$4997,"<="&IF($F$4="",DATE(2999,12,31),$F$4)),0)) -> 0
S216: =PRODUCTOS!A217 -> 0 | T216: =PRODUCTOS!B217 -> 0 | U216: =IF(S216<>"",SUMIFS(COMPRAS!$J$3:$J$4997,COMPRAS!$G$3:$G$4997,S216,COMPRAS!$B$3:$B$4997,">="&IF($C$4="",DATE(1900,1,1),$C$4),COMPRAS!$B$3:$B$4997,"<="&IF($F$4="",DATE(2999,12,31),$F$4)),0) -> 0 | V216: =IF(S216<>"",SUMIFS(COMPRAS!$O$3:$O$4997,COMPRAS!$G$3:$G$4997,S216,COMPRAS!$B$3:$B$4997,">="&IF($C$4="",DATE(1900,1,1),$C$4),COMPRAS!$B$3:$B$4997,"<="&IF($F$4="",DATE(2999,12,31),$F$4)),0) -> 0 | Y216: =IF($X$2="TODOS",U216,IF(S216<>"",SUMIFS(COMPRAS!$J$3:$J$4997,COMPRAS!$G$3:$G$4997,S216,COMPRAS!$D$3:$D$4997,$X$2,COMPRAS!$B$3:$B$4997,">="&IF($C$4="",DATE(1900,1,1),$C$4),COMPRAS!$B$3:$B$4997,"<="&IF($F$4="",DATE(2999,12,31),$F$4)),0)) -> 0 | Z216: =IF($X$2="TODOS",V216,IF(S216<>"",SUMIFS(COMPRAS!$O$3:$O$4997,COMPRAS!$G$3:$G$4997,S216,COMPRAS!$D$3:$D$4997,$X$2,COMPRAS!$B$3:$B$4997,">="&IF($C$4="",DATE(1900,1,1),$C$4),COMPRAS!$B$3:$B$4997,"<="&IF($F$4="",DATE(2999,12,31),$F$4)),0)) -> 0
S217: =PRODUCTOS!A218 -> 0 | T217: =PRODUCTOS!B218 -> 0 | U217: =IF(S217<>"",SUMIFS(COMPRAS!$J$3:$J$4997,COMPRAS!$G$3:$G$4997,S217,COMPRAS!$B$3:$B$4997,">="&IF($C$4="",DATE(1900,1,1),$C$4),COMPRAS!$B$3:$B$4997,"<="&IF($F$4="",DATE(2999,12,31),$F$4)),0) -> 0 | V217: =IF(S217<>"",SUMIFS(COMPRAS!$O$3:$O$4997,COMPRAS!$G$3:$G$4997,S217,COMPRAS!$B$3:$B$4997,">="&IF($C$4="",DATE(1900,1,1),$C$4),COMPRAS!$B$3:$B$4997,"<="&IF($F$4="",DATE(2999,12,31),$F$4)),0) -> 0 | Y217: =IF($X$2="TODOS",U217,IF(S217<>"",SUMIFS(COMPRAS!$J$3:$J$4997,COMPRAS!$G$3:$G$4997,S217,COMPRAS!$D$3:$D$4997,$X$2,COMPRAS!$B$3:$B$4997,">="&IF($C$4="",DATE(1900,1,1),$C$4),COMPRAS!$B$3:$B$4997,"<="&IF($F$4="",DATE(2999,12,31),$F$4)),0)) -> 0 | Z217: =IF($X$2="TODOS",V217,IF(S217<>"",SUMIFS(COMPRAS!$O$3:$O$4997,COMPRAS!$G$3:$G$4997,S217,COMPRAS!$D$3:$D$4997,$X$2,COMPRAS!$B$3:$B$4997,">="&IF($C$4="",DATE(1900,1,1),$C$4),COMPRAS!$B$3:$B$4997,"<="&IF($F$4="",DATE(2999,12,31),$F$4)),0)) -> 0
S218: =PRODUCTOS!A219 -> 0 | T218: =PRODUCTOS!B219 -> 0 | U218: =IF(S218<>"",SUMIFS(COMPRAS!$J$3:$J$4997,COMPRAS!$G$3:$G$4997,S218,COMPRAS!$B$3:$B$4997,">="&IF($C$4="",DATE(1900,1,1),$C$4),COMPRAS!$B$3:$B$4997,"<="&IF($F$4="",DATE(2999,12,31),$F$4)),0) -> 0 | V218: =IF(S218<>"",SUMIFS(COMPRAS!$O$3:$O$4997,COMPRAS!$G$3:$G$4997,S218,COMPRAS!$B$3:$B$4997,">="&IF($C$4="",DATE(1900,1,1),$C$4),COMPRAS!$B$3:$B$4997,"<="&IF($F$4="",DATE(2999,12,31),$F$4)),0) -> 0 | Y218: =IF($X$2="TODOS",U218,IF(S218<>"",SUMIFS(COMPRAS!$J$3:$J$4997,COMPRAS!$G$3:$G$4997,S218,COMPRAS!$D$3:$D$4997,$X$2,COMPRAS!$B$3:$B$4997,">="&IF($C$4="",DATE(1900,1,1),$C$4),COMPRAS!$B$3:$B$4997,"<="&IF($F$4="",DATE(2999,12,31),$F$4)),0)) -> 0 | Z218: =IF($X$2="TODOS",V218,IF(S218<>"",SUMIFS(COMPRAS!$O$3:$O$4997,COMPRAS!$G$3:$G$4997,S218,COMPRAS!$D$3:$D$4997,$X$2,COMPRAS!$B$3:$B$4997,">="&IF($C$4="",DATE(1900,1,1),$C$4),COMPRAS!$B$3:$B$4997,"<="&IF($F$4="",DATE(2999,12,31),$F$4)),0)) -> 0
... S231: =PRODUCTOS!A232 -> 0 | T231: =PRODUCTOS!B232 -> 0 | U231: =IF(S231<>"",SUMIFS(COMPRAS!$J$3:$J$4997,COMPRAS!$G$3:$G$4997,S231,COMPRAS!$B$3:$B$4997,">="&IF($C$4="",DATE(1900,1,1),$C$4),COMPRAS!$B$3:$B$4997,"<="&IF($F$4="",DATE(2999,12,31),$F$4)),0) -> 0 | V231: =IF(S231<>"",SUMIFS(COMPRAS!$O$3:$O$4997,COMPRAS!$G$3:$G$4997,S231,COMPRAS!$B$3:$B$4997,">="&IF($C$4="",DATE(1900,1,1),$C$4),COMPRAS!$B$3:$B$4997,"<="&IF($F$4="",DATE(2999,12,31),$F$4)),0) -> 0 | Y231: =IF($X$2="TODOS",U231,IF(S231<>"",SUMIFS(COMPRAS!$J$3:$J$4997,COMPRAS!$G$3:$G$4997,S231,COMPRAS!$D$3:$D$4997,$X$2,COMPRAS!$B$3:$B$4997,">="&IF($C$4="",DATE(1900,1,1),$C$4),COMPRAS!$B$3:$B$4997,"<="&IF($F$4="",DATE(2999,12,31),$F$4)),0)) -> 0 | Z231: =IF($X$2="TODOS",V231,IF(S231<>"",SUMIFS(COMPRAS!$O$3:$O$4997,COMPRAS!$G$3:$G$4997,S231,COMPRAS!$D$3:$D$4997,$X$2,COMPRAS!$B$3:$B$4997,">="&IF($C$4="",DATE(1900,1,1),$C$4),COMPRAS!$B$3:$B$4997,"<="&IF($F$4="",DATE(2999,12,31),$F$4)),0)) -> 0

Sheet PRECIO MEDIO
A1: MARINAFISK PESCADOS, S.A. — PRECIO MEDIO DE COMPRA POR ARTÍCULO
A2: FILTROS — Selecciona artículo y/o rango de fechas. Los resultados se actualizan automáticamente.
A3: COD ARTÍCULO | B3: DESCRIPCIÓN | C3: FECHA DESDE | D3: FECHA HASTA
B4: =IF(A4<>"",IFERROR(VLOOKUP(B5,PRODUCTOS!$A:$B,2,0),""),"") | C4: 46276 | D4: 46276 | E4: ← Rellena el código de artículo (amarillo) y/o fechas. Deja vacío para ver todos.
A5: CÓD. DETECTADO: | B5: =IF(A4="","",IFERROR(INDEX(PRODUCTOS!$A:$A,MATCH(A4,PRODUCTOS!$A:$A,0)),IFERROR(INDEX(PRODUCTOS!$A:$A,MATCH("*"&A4&"*",PRODUCTOS!$B:$B,0)),A4))) | C5: ← Escribe el código o el nombre del pescado en la casilla amarilla de arriba
A6: RESUMEN DEL PERÍODO SELECCIONADO | D6: TOTAL KG | E6: TOTAL KG | F6: TOTAL BASE IMP REAL
A7: =IF(A4<>"",B4,"TODOS LOS ARTÍCULOS") -> TODOS LOS ARTÍCULOS | D7: =SUMPRODUCT((IF(B5="",1,COMPRAS!$G$3:$G$4997=B5))*(IF(C4="",1,COMPRAS!$B$3:$B$4997>=C4))*(IF(D4="",1,COMPRAS!$B$3:$B$4997<=D4))*(COMPRAS!$J$3:$J$4997)) -> 455.75 | E7: =IF(AND($C$4="",$D$4=""),SUMIFS(COMPRAS!$J$3:$J$4997,COMPRAS!$G$3:$G$4997,IF($B$5="","<>",$B$5)),SUMIFS(COMPRAS!$J$3:$J$4997,COMPRAS!$G$3:$G$4997,IF($B$5="","<>",$B$5),COMPRAS!$B$3:$B$4997,">="&$C$4,COMPRAS!$B$3:$B$4997,"<="&$D$4)) -> 455.75 | F7: =IF(AND($C$4="",$D$4=""),SUMIFS(COMPRAS!$O$3:$O$4997,COMPRAS!$G$3:$G$4997,IF($B$5="","<>",$B$5)),SUMIFS(COMPRAS!$O$3:$O$4997,COMPRAS!$G$3:$G$4997,IF($B$5="","<>",$B$5),COMPRAS!$B$3:$B$4997,">="&$C$4,COMPRAS!$B$3:$B$4997,"<="&$D$4)) -> 1235.1435
A9: COD ARTÍCULO | B9: DESCRIPCIÓN | C9: TOTAL KG | D9: TOTAL BASE IMP. REAL | E9: PRECIO MEDIO €/KG | F9: Nº COMPRAS | G9: ¿TIENE COMPRAS? | H9: TOTAL KG REAL (si hubo mermas, opcional)
A10: 💡 Filtra por artículo en A4 y/o fechas en C4-D4. Luego usa el AUTOFILTRO en columna G para ver solo los artículos con compras (SI).
A11: CHIC | B11: CHICHARRO | C11: =IF(AND($C$4="",$D$4=""),SUMIFS(COMPRAS!$J$3:$J$4997,COMPRAS!$G$3:$G$4997,A11),SUMIFS(COMPRAS!$J$3:$J$4997,COMPRAS!$G$3:$G$4997,A11,COMPRAS!$B$3:$B$4997,">="&$C$4,COMPRAS!$B$3:$B$4997,"<="&$D$4)) -> 0 | D11: =IF(AND($C$4="",$D$4=""),SUMIFS(COMPRAS!$O$3:$O$4997,COMPRAS!$G$3:$G$4997,A11),SUMIFS(COMPRAS!$O$3:$O$4997,COMPRAS!$G$3:$G$4997,A11,COMPRAS!$B$3:$B$4997,">="&$C$4,COMPRAS!$B$3:$B$4997,"<="&$D$4)) -> 0 | E11: =IF(C11>0,D11/IF(H11<>"",H11,C11),"") | F11: =IF(AND($C$4="",$D$4=""),COUNTIF(COMPRAS!$G$3:$G$4997,A11),COUNTIFS(COMPRAS!$G$3:$G$4997,A11,COMPRAS!$B$3:$B$4997,">="&$C$4,COMPRAS!$B$3:$B$4997,"<="&$D$4)) -> 0 | G11: =IF(C11>0,"SI","")
A12: LIRI | B12: LIRIO | C12: =IF(AND($C$4="",$D$4=""),SUMIFS(COMPRAS!$J$3:$J$4997,COMPRAS!$G$3:$G$4997,A12),SUMIFS(COMPRAS!$J$3:$J$4997,COMPRAS!$G$3:$G$4997,A12,COMPRAS!$B$3:$B$4997,">="&$C$4,COMPRAS!$B$3:$B$4997,"<="&$D$4)) -> 0 | D12: =IF(AND($C$4="",$D$4=""),SUMIFS(COMPRAS!$O$3:$O$4997,COMPRAS!$G$3:$G$4997,A12),SUMIFS(COMPRAS!$O$3:$O$4997,COMPRAS!$G$3:$G$4997,A12,COMPRAS!$B$3:$B$4997,">="&$C$4,COMPRAS!$B$3:$B$4997,"<="&$D$4)) -> 0 | E12: =IF(C12>0,D12/IF(H12<>"",H12,C12),"") | F12: =IF(AND($C$4="",$D$4=""),COUNTIF(COMPRAS!$G$3:$G$4997,A12),COUNTIFS(COMPRAS!$G$3:$G$4997,A12,COMPRAS!$B$3:$B$4997,">="&$C$4,COMPRAS!$B$3:$B$4997,"<="&$D$4)) -> 0 | G12: =IF(C12>0,"SI","")
A13: VERD | B13: VERDEL | C13: =IF(AND($C$4="",$D$4=""),SUMIFS(COMPRAS!$J$3:$J$4997,COMPRAS!$G$3:$G$4997,A13),SUMIFS(COMPRAS!$J$3:$J$4997,COMPRAS!$G$3:$G$4997,A13,COMPRAS!$B$3:$B$4997,">="&$C$4,COMPRAS!$B$3:$B$4997,"<="&$D$4)) -> 0 | D13: =IF(AND($C$4="",$D$4=""),SUMIFS(COMPRAS!$O$3:$O$4997,COMPRAS!$G$3:$G$4997,A13),SUMIFS(COMPRAS!$O$3:$O$4997,COMPRAS!$G$3:$G$4997,A13,COMPRAS!$B$3:$B$4997,">="&$C$4,COMPRAS!$B$3:$B$4997,"<="&$D$4)) -> 0 | E13: =IF(C13>0,D13/IF(H13<>"",H13,C13),"") | F13: =IF(AND($C$4="",$D$4=""),COUNTIF(COMPRAS!$G$3:$G$4997,A13),COUNTIFS(COMPRAS!$G$3:$G$4997,A13,COMPRAS!$B$3:$B$4997,">="&$C$4,COMPRAS!$B$3:$B$4997,"<="&$D$4)) -> 0 | G13: =IF(C13>0,"SI","")
A14: C255P | B14: CABRAS PÑA | C14: =IF(AND($C$4="",$D$4=""),SUMIFS(COMPRAS!$J$3:$J$4997,COMPRAS!$G$3:$G$4997,A14),SUMIFS(COMPRAS!$J$3:$J$4997,COMPRAS!$G$3:$G$4997,A14,COMPRAS!$B$3:$B$4997,">="&$C$4,COMPRAS!$B$3:$B$4997,"<="&$D$4)) -> 0 | D14: =IF(AND($C$4="",$D$4=""),SUMIFS(COMPRAS!$O$3:$O$4997,COMPRAS!$G$3:$G$4997,A14),SUMIFS(COMPRAS!$O$3:$O$4997,COMPRAS!$G$3:$G$4997,A14,COMPRAS!$B$3:$B$4997,">="&$C$4,COMPRAS!$B$3:$B$4997,"<="&$D$4)) -> 0 | E14: =IF(C14>0,D14/IF(H14<>"",H14,C14),"") | F14: =IF(AND($C$4="",$D$4=""),COUNTIF(COMPRAS!$G$3:$G$4997,A14),COUNTIFS(COMPRAS!$G$3:$G$4997,A14,COMPRAS!$B$3:$B$4997,">="&$C$4,COMPRAS!$B$3:$B$4997,"<="&$D$4)) -> 0 | G14: =IF(C14>0,"SI","")
A15: CHOC | B15: CHOCOS | C15: =IF(AND($C$4="",$D$4=""),SUMIFS(COMPRAS!$J$3:$J$4997,COMPRAS!$G$3:$G$4997,A15),SUMIFS(COMPRAS!$J$3:$J$4997,COMPRAS!$G$3:$G$4997,A15,COMPRAS!$B$3:$B$4997,">="&$C$4,COMPRAS!$B$3:$B$4997,"<="&$D$4)) -> 0 | D15: =IF(AND($C$4="",$D$4=""),SUMIFS(COMPRAS!$O$3:$O$4997,COMPRAS!$G$3:$G$4997,A15),SUMIFS(COMPRAS!$O$3:$O$4997,COMPRAS!$G$3:$G$4997,A15,COMPRAS!$B$3:$B$4997,">="&$C$4,COMPRAS!$B$3:$B$4997,"<="&$D$4)) -> 0 | E15: =IF(C15>0,D15/IF(H15<>"",H15,C15),"") | F15: =IF(AND($C$4="",$D$4=""),COUNTIF(COMPRAS!$G$3:$G$4997,A15),COUNTIFS(COMPRAS!$G$3:$G$4997,A15,COMPRAS!$B$3:$B$4997,">="&$C$4,COMPRAS!$B$3:$B$4997,"<="&$D$4)) -> 0 | G15: =IF(C15>0,"SI","")
A16: PION | B16: PIONS | C16: =IF(AND($C$4="",$D$4=""),SUMIFS(COMPRAS!$J$3:$J$4997,COMPRAS!$G$3:$G$4997,A16),SUMIFS(COMPRAS!$J$3:$J$4997,COMPRAS!$G$3:$G$4997,A16,COMPRAS!$B$3:$B$4997,">="&$C$4,COMPRAS!$B$3:$B$4997,"<="&$D$4)) -> 0 | D16: =IF(AND($C$4="",$D$4=""),SUMIFS(COMPRAS!$O$3:$O$4997,COMPRAS!$G$3:$G$4997,A16),SUMIFS(COMPRAS!$O$3:$O$4997,COMPRAS!$G$3:$G$4997,A16,COMPRAS!$B$3:$B$4997,">="&$C$4,COMPRAS!$B$3:$B$4997,"<="&$D$4)) -> 0 | E16: =IF(C16>0,D16/IF(H16<>"",H16,C16),"") | F16: =IF(AND($C$4="",$D$4=""),COUNTIF(COMPRAS!$G$3:$G$4997,A16),COUNTIFS(COMPRAS!$G$3:$G$4997,A16,COMPRAS!$B$3:$B$4997,">="&$C$4,COMPRAS!$B$3:$B$4997,"<="&$D$4)) -> 0 | G16: =IF(C16>0,"SI","")
A17: RAPN | B17: RAPE NEGRO | C17: =IF(AND($C$4="",$D$4=""),SUMIFS(COMPRAS!$J$3:$J$4997,COMPRAS!$G$3:$G$4997,A17),SUMIFS(COMPRAS!$J$3:$J$4997,COMPRAS!$G$3:$G$4997,A17,COMPRAS!$B$3:$B$4997,">="&$C$4,COMPRAS!$B$3:$B$4997,"<="&$D$4)) -> 0 | D17: =IF(AND($C$4="",$D$4=""),SUMIFS(COMPRAS!$O$3:$O$4997,COMPRAS!$G$3:$G$4997,A17),SUMIFS(COMPRAS!$O$3:$O$4997,COMPRAS!$G$3:$G$4997,A17,COMPRAS!$B$3:$B$4997,">="&$C$4,COMPRAS!$B$3:$B$4997,"<="&$D$4)) -> 0 | E17: =IF(C17>0,D17/IF(H17<>"",H17,C17),"") | F17: =IF(AND($C$4="",$D$4=""),COUNTIF(COMPRAS!$G$3:$G$4997,A17),COUNTIFS(COMPRAS!$G$3:$G$4997,A17,COMPRAS!$B$3:$B$4997,">="&$C$4,COMPRAS!$B$3:$B$4997,"<="&$D$4)) -> 0 | G17: =IF(C17>0,"SI","")
A18: RAPB | B18: RAPE BLANCO | C18: =IF(AND($C$4="",$D$4=""),SUMIFS(COMPRAS!$J$3:$J$4997,COMPRAS!$G$3:$G$4997,A18),SUMIFS(COMPRAS!$J$3:$J$4997,COMPRAS!$G$3:$G$4997,A18,COMPRAS!$B$3:$B$4997,">="&$C$4,COMPRAS!$B$3:$B$4997,"<="&$D$4)) -> 0 | D18: =IF(AND($C$4="",$D$4=""),SUMIFS(COMPRAS!$O$3:$O$4997,COMPRAS!$G$3:$G$4997,A18),SUMIFS(COMPRAS!$O$3:$O$4997,COMPRAS!$G$3:$G$4997,A18,COMPRAS!$B$3:$B$4997,">="&$C$4,COMPRAS!$B$3:$B$4997,"<="&$D$4)) -> 0 | E18: =IF(C18>0,D18/IF(H18<>"",H18,C18),"") | F18: =IF(AND($C$4="",$D$4=""),COUNTIF(COMPRAS!$G$3:$G$4997,A18),COUNTIFS(COMPRAS!$G$3:$G$4997,A18,COMPRAS!$B$3:$B$4997,">="&$C$4,COMPRAS!$B$3:$B$4997,"<="&$D$4)) -> 0 | G18: =IF(C18>0,"SI","")
A19: SARG | B19: SARGO | C19: =IF(AND($C$4="",$D$4=""),SUMIFS(COMPRAS!$J$3:$J$4997,COMPRAS!$G$3:$G$4997,A19),SUMIFS(COMPRAS!$J$3:$J$4997,COMPRAS!$G$3:$G$4997,A19,COMPRAS!$B$3:$B$4997,">="&$C$4,COMPRAS!$B$3:$B$4997,"<="&$D$4)) -> 0 | D19: =IF(AND($C$4="",$D$4=""),SUMIFS(COMPRAS!$O$3:$O$4997,COMPRAS!$G$3:$G$4997,A19),SUMIFS(COMPRAS!$O$3:$O$4997,COMPRAS!$G$3:$G$4997,A19,COMPRAS!$B$3:$B$4997,">="&$C$4,COMPRAS!$B$3:$B$4997,"<="&$D$4)) -> 0 | E19: =IF(C19>0,D19/IF(H19<>"",H19,C19),"") | F19: =IF(AND($C$4="",$D$4=""),COUNTIF(COMPRAS!$G$3:$G$4997,A19),COUNTIFS(COMPRAS!$G$3:$G$4997,A19,COMPRAS!$B$3:$B$4997,">="&$C$4,COMPRAS!$B$3:$B$4997,"<="&$D$4)) -> 0 | G19: =IF(C19>0,"SI","")
A20: C650 | B20: ABADEJO RIA (POL) | C20: =IF(AND($C$4="",$D$4=""),SUMIFS(COMPRAS!$J$3:$J$4997,COMPRAS!$G$3:$G$4997,A20),SUMIFS(COMPRAS!$J$3:$J$4997,COMPRAS!$G$3:$G$4997,A20,COMPRAS!$B$3:$B$4997,">="&$C$4,COMPRAS!$B$3:$B$4997,"<="&$D$4)) -> 0 | D20: =IF(AND($C$4="",$D$4=""),SUMIFS(COMPRAS!$O$3:$O$4997,COMPRAS!$G$3:$G$4997,A20),SUMIFS(COMPRAS!$O$3:$O$4997,COMPRAS!$G$3:$G$4997,A20,COMPRAS!$B$3:$B$4997,">="&$C$4,COMPRAS!$B$3:$B$4997,"<="&$D$4)) -> 0 | E20: =IF(C20>0,D20/IF(H20<>"",H20,C20),"") | F20: =IF(AND($C$4="",$D$4=""),COUNTIF(COMPRAS!$G$3:$G$4997,A20),COUNTIFS(COMPRAS!$G$3:$G$4997,A20,COMPRAS!$B$3:$B$4997,">="&$C$4,COMPRAS!$B$3:$B$4997,"<="&$D$4)) -> 0 | G20: =IF(C20>0,"SI","")
A21: C620 | B21: ACEDIA (CET) | C21: =IF(AND($C$4="",$D$4=""),SUMIFS(COMPRAS!$J$3:$J$4997,COMPRAS!$G$3:$G$4997,A21),SUMIFS(COMPRAS!$J$3:$J$4997,COMPRAS!$G$3:$G$4997,A21,COMPRAS!$B$3:$B$4997,">="&$C$4,COMPRAS!$B$3:$B$4997,"<="&$D$4)) -> 0 | D21: =IF(AND($C$4="",$D$4=""),SUMIFS(COMPRAS!$O$3:$O$4997,COMPRAS!$G$3:$G$4997,A21),SUMIFS(COMPRAS!$O$3:$O$4997,COMPRAS!$G$3:$G$4997,A21,COMPRAS!$B$3:$B$4997,">="&$C$4,COMPRAS!$B$3:$B$4997,"<="&$D$4)) -> 0 | E21: =IF(C21>0,D21/IF(H21<>"",H21,C21),"") | F21: =IF(AND($C$4="",$D$4=""),COUNTIF(COMPRAS!$G$3:$G$4997,A21),COUNTIFS(COMPRAS!$G$3:$G$4997,A21,COMPRAS!$B$3:$B$4997,">="&$C$4,COMPRAS!$B$3:$B$4997,"<="&$D$4)) -> 0 | G21: =IF(C21>0,"SI","")
A22: C2555 | B22: ALFONDIGA/RUBIO/ESCACHO (GUU) | C22: =IF(AND($C$4="",$D$4=""),SUMIFS(COMPRAS!$J$3:$J$4997,COMPRAS!$G$3:$G$4997,A22),SUMIFS(COMPRAS!$J$3:$J$4997,COMPRAS!$G$3:$G$4997,A22,COMPRAS!$B$3:$B$4997,">="&$C$4,COMPRAS!$B$3:$B$4997,"<="&$D$4)) -> 0 | D22: =IF(AND($C$4="",$D$4=""),SUMIFS(COMPRAS!$O$3:$O$4997,COMPRAS!$G$3:$G$4997,A22),SUMIFS(COMPRAS!$O$3:$O$4997,COMPRAS!$G$3:$G$4997,A22,COMPRAS!$B$3:$B$4997,">="&$C$4,COMPRAS!$B$3:$B$4997,"<="&$D$4)) -> 0 | E22: =IF(C22>0,D22/IF(H22<>"",H22,C22),"") | F22: =IF(AND($C$4="",$D$4=""),COUNTIF(COMPRAS!$G$3:$G$4997,A22),COUNTIFS(COMPRAS!$G$3:$G$4997,A22,COMPRAS!$B$3:$B$4997,">="&$C$4,COMPRAS!$B$3:$B$4997,"<="&$D$4)) -> 0 | G22: =IF(C22>0,"SI","")
... A53: C2100 | B53: CIGALA "0" (NEP) | C53: =IF(AND($C$4="",$D$4=""),SUMIFS(COMPRAS!$J$3:$J$4997,COMPRAS!$G$3:$G$4997,A53),SUMIFS(COMPRAS!$J$3:$J$4997,COMPRAS!$G$3:$G$4997,A53,COMPRAS!$B$3:$B$4997,">="&$C$4,COMPRAS!$B$3:$B$4997,"<="&$D$4)) -> 0 | D53: =IF(AND($C$4="",$D$4=""),SUMIFS(COMPRAS!$O$3:$O$4997,COMPRAS!$G$3:$G$4997,A53),SUMIFS(COMPRAS!$O$3:$O$4997,COMPRAS!$G$3:$G$4997,A53,COMPRAS!$B$3:$B$4997,">="&$C$4,COMPRAS!$B$3:$B$4997,"<="&$D$4)) -> 0 | E53: =IF(C53>0,D53/IF(H53<>"",H53,C53),"") | F53: =IF(AND($C$4="",$D$4=""),COUNTIF(COMPRAS!$G$3:$G$4997,A53),COUNTIFS(COMPRAS!$G$3:$G$4997,A53,COMPRAS!$B$3:$B$4997,">="&$C$4,COMPRAS!$B$3:$B$4997,"<="&$D$4)) -> 0 | G53: =IF(C53>0,"SI","")
A54: C410 | B54: CINTAS/ PEZ CINTA (CBC) | C54: 145 | D54: =IF(AND($C$4="",$D$4=""),SUMIFS(COMPRAS!$O$3:$O$4997,COMPRAS!$G$3:$G$4997,A54),SUMIFS(COMPRAS!$O$3:$O$4997,COMPRAS!$G$3:$G$4997,A54,COMPRAS!$B$3:$B$4997,">="&$C$4,COMPRAS!$B$3:$B$4997,"<="&$D$4)) -> 237.7875 | E54: =IF(C54>0,D54/IF(H54<>"",H54,C54),"") -> 1.6399138 | F54: =IF(AND($C$4="",$D$4=""),COUNTIF(COMPRAS!$G$3:$G$4997,A54),COUNTIFS(COMPRAS!$G$3:$G$4997,A54,COMPRAS!$B$3:$B$4997,">="&$C$4,COMPRAS!$B$3:$B$4997,"<="&$D$4)) -> 1
A55: C250 | B55: CONGRIO 10+ (COE) | C55: =IF(AND($C$4="",$D$4=""),SUMIFS(COMPRAS!$J$3:$J$4997,COMPRAS!$G$3:$G$4997,A55),SUMIFS(COMPRAS!$J$3:$J$4997,COMPRAS!$G$3:$G$4997,A55,COMPRAS!$B$3:$B$4997,">="&$C$4,COMPRAS!$B$3:$B$4997,"<="&$D$4)) -> 50 | D55: =IF(AND($C$4="",$D$4=""),SUMIFS(COMPRAS!$O$3:$O$4997,COMPRAS!$G$3:$G$4997,A55),SUMIFS(COMPRAS!$O$3:$O$4997,COMPRAS!$G$3:$G$4997,A55,COMPRAS!$B$3:$B$4997,">="&$C$4,COMPRAS!$B$3:$B$4997,"<="&$D$4)) -> 196.095 | E55: =IF(C55>0,D55/IF(H55<>"",H55,C55),"") -> 3.9219 | F55: =IF(AND($C$4="",$D$4=""),COUNTIF(COMPRAS!$G$3:$G$4997,A55),COUNTIFS(COMPRAS!$G$3:$G$4997,A55,COMPRAS!$B$3:$B$4997,">="&$C$4,COMPRAS!$B$3:$B$4997,"<="&$D$4)) -> 3 | G55: =IF(C55>0,"SI","") -> SI
A56: C2507 | B56: CONGRIO 7/10 (COE) | C56: =IF(AND($C$4="",$D$4=""),SUMIFS(COMPRAS!$J$3:$J$4997,COMPRAS!$G$3:$G$4997,A56),SUMIFS(COMPRAS!$J$3:$J$4997,COMPRAS!$G$3:$G$4997,A56,COMPRAS!$B$3:$B$4997,">="&$C$4,COMPRAS!$B$3:$B$4997,"<="&$D$4)) -> 0 | D56: =IF(AND($C$4="",$D$4=""),SUMIFS(COMPRAS!$O$3:$O$4997,COMPRAS!$G$3:$G$4997,A56),SUMIFS(COMPRAS!$O$3:$O$4997,COMPRAS!$G$3:$G$4997,A56,COMPRAS!$B$3:$B$4997,">="&$C$4,COMPRAS!$B$3:$B$4997,"<="&$D$4)) -> 0 | E56: =IF(C56>0,D56/IF(H56<>"",H56,C56),"") | F56: =IF(AND($C$4="",$D$4=""),COUNTIF(COMPRAS!$G$3:$G$4997,A56),COUNTIFS(COMPRAS!$G$3:$G$4997,A56,COMPRAS!$B$3:$B$4997,">="&$C$4,COMPRAS!$B$3:$B$4997,"<="&$D$4)) -> 0 | G56: =IF(C56>0,"SI","") | H56: 46.7
A57: C2505 | B57: CONGRIO 5/07 (COE) | C57: =IF(AND($C$4="",$D$4=""),SUMIFS(COMPRAS!$J$3:$J$4997,COMPRAS!$G$3:$G$4997,A57),SUMIFS(COMPRAS!$J$3:$J$4997,COMPRAS!$G$3:$G$4997,A57,COMPRAS!$B$3:$B$4997,">="&$C$4,COMPRAS!$B$3:$B$4997,"<="&$D$4)) -> 0 | D57: =IF(AND($C$4="",$D$4=""),SUMIFS(COMPRAS!$O$3:$O$4997,COMPRAS!$G$3:$G$4997,A57),SUMIFS(COMPRAS!$O$3:$O$4997,COMPRAS!$G$3:$G$4997,A57,COMPRAS!$B$3:$B$4997,">="&$C$4,COMPRAS!$B$3:$B$4997,"<="&$D$4)) -> 0 | E57: =IF(C57>0,D57/IF(H57<>"",H57,C57),"") | F57: =IF(AND($C$4="",$D$4=""),COUNTIF(COMPRAS!$G$3:$G$4997,A57),COUNTIFS(COMPRAS!$G$3:$G$4997,A57,COMPRAS!$B$3:$B$4997,">="&$C$4,COMPRAS!$B$3:$B$4997,"<="&$D$4)) -> 0 | G57: =IF(C57>0,"SI","")
A58: C6530 | B58: CORENO/ MENDO (WYT) | C58: =IF(AND($C$4="",$D$4=""),SUMIFS(COMPRAS!$J$3:$J$4997,COMPRAS!$G$3:$G$4997,A58),SUMIFS(COMPRAS!$J$3:$J$4997,COMPRAS!$G$3:$G$4997,A58,COMPRAS!$B$3:$B$4997,">="&$C$4,COMPRAS!$B$3:$B$4997,"<="&$D$4)) -> 0 | D58: =IF(AND($C$4="",$D$4=""),SUMIFS(COMPRAS!$O$3:$O$4997,COMPRAS!$G$3:$G$4997,A58),SUMIFS(COMPRAS!$O$3:$O$4997,COMPRAS!$G$3:$G$4997,A58,COMPRAS!$B$3:$B$4997,">="&$C$4,COMPRAS!$B$3:$B$4997,"<="&$D$4)) -> 0 | E58: =IF(C58>0,D58/IF(H58<>"",H58,C58),"") | F58: =IF(AND($C$4="",$D$4=""),COUNTIF(COMPRAS!$G$3:$G$4997,A58),COUNTIFS(COMPRAS!$G$3:$G$4997,A58,COMPRAS!$B$3:$B$4997,">="&$C$4,COMPRAS!$B$3:$B$4997,"<="&$D$4)) -> 0 | G58: =IF(C58>0,"SI","")
A59: C6301 | B59: CORUXO/ SOLLO/ REMOL (BLL) | C59: =IF(AND($C$4="",$D$4=""),SUMIFS(COMPRAS!$J$3:$J$4997,COMPRAS!$G$3:$G$4997,A59),SUMIFS(COMPRAS!$J$3:$J$4997,COMPRAS!$G$3:$G$4997,A59,COMPRAS!$B$3:$B$4997,">="&$C$4,COMPRAS!$B$3:$B$4997,"<="&$D$4)) -> 0 | D59: =IF(AND($C$4="",$D$4=""),SUMIFS(COMPRAS!$O$3:$O$4997,COMPRAS!$G$3:$G$4997,A59),SUMIFS(COMPRAS!$O$3:$O$4997,COMPRAS!$G$3:$G$4997,A59,COMPRAS!$B$3:$B$4997,">="&$C$4,COMPRAS!$B$3:$B$4997,"<="&$D$4)) -> 0 | E59: =IF(C59>0,D59/IF(H59<>"",H59,C59),"") | F59: =IF(AND($C$4="",$D$4=""),COUNTIF(COMPRAS!$G$3:$G$4997,A59),COUNTIFS(COMPRAS!$G$3:$G$4997,A59,COMPRAS!$B$3:$B$4997,">="&$C$4,COMPRAS!$B$3:$B$4997,"<="&$D$4)) -> 0 | G59: =IF(C59>0,"SI","")
A60: C561 | B60: DENTON (DEC) | C60: =IF(AND($C$4="",$D$4=""),SUMIFS(COMPRAS!$J$3:$J$4997,COMPRAS!$G$3:$G$4997,A60),SUMIFS(COMPRAS!$J$3:$J$4997,COMPRAS!$G$3:$G$4997,A60,COMPRAS!$B$3:$B$4997,">="&$C$4,COMPRAS!$B$3:$B$4997,"<="&$D$4)) -> 0 | D60: =IF(AND($C$4="",$D$4=""),SUMIFS(COMPRAS!$O$3:$O$4997,COMPRAS!$G$3:$G$4997,A60),SUMIFS(COMPRAS!$O$3:$O$4997,COMPRAS!$G$3:$G$4997,A60,COMPRAS!$B$3:$B$4997,">="&$C$4,COMPRAS!$B$3:$B$4997,"<="&$D$4)) -> 0 | E60: =IF(C60>0,D60/IF(H60<>"",H60,C60),"") | F60: =IF(AND($C$4="",$D$4=""),COUNTIF(COMPRAS!$G$3:$G$4997,A60),COUNTIFS(COMPRAS!$G$3:$G$4997,A60,COMPRAS!$B$3:$B$4997,">="&$C$4,COMPRAS!$B$3:$B$4997,"<="&$D$4)) -> 0 | G60: =IF(C60>0,"SI","")
A61: C3500 | B61: DORADA SALVAJE (SBG) | C61: =IF(AND($C$4="",$D$4=""),SUMIFS(COMPRAS!$J$3:$J$4997,COMPRAS!$G$3:$G$4997,A61),SUMIFS(COMPRAS!$J$3:$J$4997,COMPRAS!$G$3:$G$4997,A61,COMPRAS!$B$3:$B$4997,">="&$C$4,COMPRAS!$B$3:$B$4997,"<="&$D$4)) -> 0 | D61: =IF(AND($C$4="",$D$4=""),SUMIFS(COMPRAS!$O$3:$O$4997,COMPRAS!$G$3:$G$4997,A61),SUMIFS(COMPRAS!$O$3:$O$4997,COMPRAS!$G$3:$G$4997,A61,COMPRAS!$B$3:$B$4997,">="&$C$4,COMPRAS!$B$3:$B$4997,"<="&$D$4)) -> 0 | E61: =IF(C61>0,D61/IF(H61<>"",H61,C61),"") | F61: =IF(AND($C$4="",$D$4=""),COUNTIF(COMPRAS!$G$3:$G$4997,A61),COUNTIFS(COMPRAS!$G$3:$G$4997,A61,COMPRAS!$B$3:$B$4997,">="&$C$4,COMPRAS!$B$3:$B$4997,"<="&$D$4)) -> 0 | G61: =IF(C61>0,"SI","")
A62: C867 | B62: ERIZO DE MAR (URM) | C62: =IF(AND($C$4="",$D$4=""),SUMIFS(COMPRAS!$J$3:$J$4997,COMPRAS!$G$3:$G$4997,A62),SUMIFS(COMPRAS!$J$3:$J$4997,COMPRAS!$G$3:$G$4997,A62,COMPRAS!$B$3:$B$4997,">="&$C$4,COMPRAS!$B$3:$B$4997,"<="&$D$4)) -> 0 | D62: =IF(AND($C$4="",$D$4=""),SUMIFS(COMPRAS!$O$3:$O$4997,COMPRAS!$G$3:$G$4997,A62),SUMIFS(COMPRAS!$O$3:$O$4997,COMPRAS!$G$3:$G$4997,A62,COMPRAS!$B$3:$B$4997,">="&$C$4,COMPRAS!$B$3:$B$4997,"<="&$D$4)) -> 0 | E62: =IF(C62>0,D62/IF(H62<>"",H62,C62),"") | F62: =IF(AND($C$4="",$D$4=""),COUNTIF(COMPRAS!$G$3:$G$4997,A62),COUNTIFS(COMPRAS!$G$3:$G$4997,A62,COMPRAS!$B$3:$B$4997,">="&$C$4,COMPRAS!$B$3:$B$4997,"<="&$D$4)) -> 0 | G62: =IF(C62>0,"SI","")
A63: C2566 | B63: ESCACHO/ ARETE/ RUBIO (GUR) | C63: =IF(AND($C$4="",$D$4=""),SUMIFS(COMPRAS!$J$3:$J$4997,COMPRAS!$G$3:$G$4997,A63),SUMIFS(COMPRAS!$J$3:$J$4997,COMPRAS!$G$3:$G$4997,A63,COMPRAS!$B$3:$B$4997,">="&$C$4,COMPRAS!$B$3:$B$4997,"<="&$D$4)) -> 0 | D63: =IF(AND($C$4="",$D$4=""),SUMIFS(COMPRAS!$O$3:$O$4997,COMPRAS!$G$3:$G$4997,A63),SUMIFS(COMPRAS!$O$3:$O$4997,COMPRAS!$G$3:$G$4997,A63,COMPRAS!$B$3:$B$4997,">="&$C$4,COMPRAS!$B$3:$B$4997,"<="&$D$4)) -> 0 | E63: =IF(C63>0,D63/IF(H63<>"",H63,C63),"") | F63: =IF(AND($C$4="",$D$4=""),COUNTIF(COMPRAS!$G$3:$G$4997,A63),COUNTIFS(COMPRAS!$G$3:$G$4997,A63,COMPRAS!$B$3:$B$4997,">="&$C$4,COMPRAS!$B$3:$B$4997,"<="&$D$4)) -> 0 | G63: =IF(C63>0,"SI","")
A64: C495 | B64: ESCARPON/ DRAGON | C64: =IF(AND($C$4="",$D$4=""),SUMIFS(COMPRAS!$J$3:$J$4997,COMPRAS!$G$3:$G$4997,A64),SUMIFS(COMPRAS!$J$3:$J$4997,COMPRAS!$G$3:$G$4997,A64,COMPRAS!$B$3:$B$4997,">="&$C$4,COMPRAS!$B$3:$B$4997,"<="&$D$4)) -> 0 | D64: =IF(AND($C$4="",$D$4=""),SUMIFS(COMPRAS!$O$3:$O$4997,COMPRAS!$G$3:$G$4997,A64),SUMIFS(COMPRAS!$O$3:$O$4997,COMPRAS!$G$3:$G$4997,A64,COMPRAS!$B$3:$B$4997,">="&$C$4,COMPRAS!$B$3:$B$4997,"<="&$D$4)) -> 0 | E64: =IF(C64>0,D64/IF(H64<>"",H64,C64),"") | F64: =IF(AND($C$4="",$D$4=""),COUNTIF(COMPRAS!$G$3:$G$4997,A64),COUNTIFS(COMPRAS!$G$3:$G$4997,A64,COMPRAS!$B$3:$B$4997,">="&$C$4,COMPRAS!$B$3:$B$4997,"<="&$D$4)) -> 0 | G64: =IF(C64>0,"SI","")
A65: C214 | B65: FANECA (BIB) | C65: =IF(AND($C$4="",$D$4=""),SUMIFS(COMPRAS!$J$3:$J$4997,COMPRAS!$G$3:$G$4997,A65),SUMIFS(COMPRAS!$J$3:$J$4997,COMPRAS!$G$3:$G$4997,A65,COMPRAS!$B$3:$B$4997,">="&$C$4,COMPRAS!$B$3:$B$4997,"<="&$D$4)) -> 0 | D65: =IF(AND($C$4="",$D$4=""),SUMIFS(COMPRAS!$O$3:$O$4997,COMPRAS!$G$3:$G$4997,A65),SUMIFS(COMPRAS!$O$3:$O$4997,COMPRAS!$G$3:$G$4997,A65,COMPRAS!$B$3:$B$4997,">="&$C$4,COMPRAS!$B$3:$B$4997,"<="&$D$4)) -> 0 | E65: =IF(C65>0,D65/IF(H65<>"",H65,C65),"") | F65: =IF(AND($C$4="",$D$4=""),COUNTIF(COMPRAS!$G$3:$G$4997,A65),COUNTIFS(COMPRAS!$G$3:$G$4997,A65,COMPRAS!$B$3:$B$4997,">="&$C$4,COMPRAS!$B$3:$B$4997,"<="&$D$4)) -> 0 | G65: =IF(C65>0,"SI","")
A66: C420 | B66: GALLANO/ REI (USI) | C66: =IF(AND($C$4="",$D$4=""),SUMIFS(COMPRAS!$J$3:$J$4997,COMPRAS!$G$3:$G$4997,A66),SUMIFS(COMPRAS!$J$3:$J$4997,COMPRAS!$G$3:$G$4997,A66,COMPRAS!$B$3:$B$4997,">="&$C$4,COMPRAS!$B$3:$B$4997,"<="&$D$4)) -> 0 | D66: =IF(AND($C$4="",$D$4=""),SUMIFS(COMPRAS!$O$3:$O$4997,COMPRAS!$G$3:$G$4997,A66),SUMIFS(COMPRAS!$O$3:$O$4997,COMPRAS!$G$3:$G$4997,A66,COMPRAS!$B$3:$B$4997,">="&$C$4,COMPRAS!$B$3:$B$4997,"<="&$D$4)) -> 0 | E66: =IF(C66>0,D66/IF(H66<>"",H66,C66),"") | F66: =IF(AND($C$4="",$D$4=""),COUNTIF(COMPRAS!$G$3:$G$4997,A66),COUNTIFS(COMPRAS!$G$3:$G$4997,A66,COMPRAS!$B$3:$B$4997,">="&$C$4,COMPRAS!$B$3:$B$4997,"<="&$D$4)) -> 0 | G66: =IF(C66>0,"SI","")
A67: C269 | B67: GALLINETA NORTE OCEANICA (FILETES) | C67: =IF(AND($C$4="",$D$4=""),SUMIFS(COMPRAS!$J$3:$J$4997,COMPRAS!$G$3:$G$4997,A67),SUMIFS(COMPRAS!$J$3:$J$4997,COMPRAS!$G$3:$G$4997,A67,COMPRAS!$B$3:$B$4997,">="&$C$4,COMPRAS!$B$3:$B$4997,"<="&$D$4)) -> 0 | D67: =IF(AND($C$4="",$D$4=""),SUMIFS(COMPRAS!$O$3:$O$4997,COMPRAS!$G$3:$G$4997,A67),SUMIFS(COMPRAS!$O$3:$O$4997,COMPRAS!$G$3:$G$4997,A67,COMPRAS!$B$3:$B$4997,">="&$C$4,COMPRAS!$B$3:$B$4997,"<="&$D$4)) -> 0 | E67: =IF(C67>0,D67/IF(H67<>"",H67,C67),"") | F67: =IF(AND($C$4="",$D$4=""),COUNTIF(COMPRAS!$G$3:$G$4997,A67),COUNTIFS(COMPRAS!$G$3:$G$4997,A67,COMPRAS!$B$3:$B$4997,">="&$C$4,COMPRAS!$B$3:$B$4997,"<="&$D$4)) -> 0 | G67: =IF(C67>0,"SI","")
A68: C270 | B68: GALLO | C68: =IF(AND($C$4="",$D$4=""),SUMIFS(COMPRAS!$J$3:$J$4997,COMPRAS!$G$3:$G$4997,A68),SUMIFS(COMPRAS!$J$3:$J$4997,COMPRAS!$G$3:$G$4997,A68,COMPRAS!$B$3:$B$4997,">="&$C$4,COMPRAS!$B$3:$B$4997,"<="&$D$4)) -> 0 | D68: =IF(AND($C$4="",$D$4=""),SUMIFS(COMPRAS!$O$3:$O$4997,COMPRAS!$G$3:$G$4997,A68),SUMIFS(COMPRAS!$O$3:$O$4997,COMPRAS!$G$3:$G$4997,A68,COMPRAS!$B$3:$B$4997,">="&$C$4,COMPRAS!$B$3:$B$4997,"<="&$D$4)) -> 0 | E68: =IF(C68>0,D68/IF(H68<>"",H68,C68),"") | F68: =IF(AND($C$4="",$D$4=""),COUNTIF(COMPRAS!$G$3:$G$4997,A68),COUNTIFS(COMPRAS!$G$3:$G$4997,A68,COMPRAS!$B$3:$B$4997,">="&$C$4,COMPRAS!$B$3:$B$4997,"<="&$D$4)) -> 0 | G68: =IF(C68>0,"SI","")
... A143: C516 | B143: HUESOS DE RAPE (MON) | C143: =IF(AND($C$4="",$D$4=""),SUMIFS(COMPRAS!$J$3:$J$4997,COMPRAS!$G$3:$G$4997,A143),SUMIFS(COMPRAS!$J$3:$J$4997,COMPRAS!$G$3:$G$4997,A143,COMPRAS!$B$3:$B$4997,">="&$C$4,COMPRAS!$B$3:$B$4997,"<="&$D$4)) -> 0 | D143: =IF(AND($C$4="",$D$4=""),SUMIFS(COMPRAS!$O$3:$O$4997,COMPRAS!$G$3:$G$4997,A143),SUMIFS(COMPRAS!$O$3:$O$4997,COMPRAS!$G$3:$G$4997,A143,COMPRAS!$B$3:$B$4997,">="&$C$4,COMPRAS!$B$3:$B$4997,"<="&$D$4)) -> 0 | E143: =IF(C143>0,D143/IF(H143<>"",H143,C143),"") | F143: =IF(AND($C$4="",$D$4=""),COUNTIF(COMPRAS!$G$3:$G$4997,A143),COUNTIFS(COMPRAS!$G$3:$G$4997,A143,COMPRAS!$B$3:$B$4997,">="&$C$4,COMPRAS!$B$3:$B$4997,"<="&$D$4)) -> 0 | G143: =IF(C143>0,"SI","")
A144: C5262 | B144: RAPE BLANCO RASCO (MON) | C144: =IF(AND($C$4="",$D$4=""),SUMIFS(COMPRAS!$J$3:$J$4997,COMPRAS!$G$3:$G$4997,A144),SUMIFS(COMPRAS!$J$3:$J$4997,COMPRAS!$G$3:$G$4997,A144,COMPRAS!$B$3:$B$4997,">="&$C$4,COMPRAS!$B$3:$B$4997,"<="&$D$4)) -> 0 | D144: =IF(AND($C$4="",$D$4=""),SUMIFS(COMPRAS!$O$3:$O$4997,COMPRAS!$G$3:$G$4997,A144),SUMIFS(COMPRAS!$O$3:$O$4997,COMPRAS!$G$3:$G$4997,A144,COMPRAS!$B$3:$B$4997,">="&$C$4,COMPRAS!$B$3:$B$4997,"<="&$D$4)) -> 0 | E144: =IF(C144>0,D144/IF(H144<>"",H144,C144),"") | F144: =IF(AND($C$4="",$D$4=""),COUNTIF(COMPRAS!$G$3:$G$4997,A144),COUNTIFS(COMPRAS!$G$3:$G$4997,A144,COMPRAS!$B$3:$B$4997,">="&$C$4,COMPRAS!$B$3:$B$4997,"<="&$D$4)) -> 0 | G144: =IF(C144>0,"SI","") | H144: 106.9
A145: C5260 | B145: RAPE BLANCO ARRASTRE (MON) | C145: =IF(AND($C$4="",$D$4=""),SUMIFS(COMPRAS!$J$3:$J$4997,COMPRAS!$G$3:$G$4997,A145),SUMIFS(COMPRAS!$J$3:$J$4997,COMPRAS!$G$3:$G$4997,A145,COMPRAS!$B$3:$B$4997,">="&$C$4,COMPRAS!$B$3:$B$4997,"<="&$D$4)) -> 0 | D145: =IF(AND($C$4="",$D$4=""),SUMIFS(COMPRAS!$O$3:$O$4997,COMPRAS!$G$3:$G$4997,A145),SUMIFS(COMPRAS!$O$3:$O$4997,COMPRAS!$G$3:$G$4997,A145,COMPRAS!$B$3:$B$4997,">="&$C$4,COMPRAS!$B$3:$B$4997,"<="&$D$4)) -> 0 | E145: =IF(C145>0,D145/IF(H145<>"",H145,C145),"") | F145: =IF(AND($C$4="",$D$4=""),COUNTIF(COMPRAS!$G$3:$G$4997,A145),COUNTIFS(COMPRAS!$G$3:$G$4997,A145,COMPRAS!$B$3:$B$4997,">="&$C$4,COMPRAS!$B$3:$B$4997,"<="&$D$4)) -> 0 | G145: =IF(C145>0,"SI","")
A146: C5240 | B146: RAPE NEGRO (ANK) | C146: =IF(AND($C$4="",$D$4=""),SUMIFS(COMPRAS!$J$3:$J$4997,COMPRAS!$G$3:$G$4997,A146),SUMIFS(COMPRAS!$J$3:$J$4997,COMPRAS!$G$3:$G$4997,A146,COMPRAS!$B$3:$B$4997,">="&$C$4,COMPRAS!$B$3:$B$4997,"<="&$D$4)) -> 0 | D146: =IF(AND($C$4="",$D$4=""),SUMIFS(COMPRAS!$O$3:$O$4997,COMPRAS!$G$3:$G$4997,A146),SUMIFS(COMPRAS!$O$3:$O$4997,COMPRAS!$G$3:$G$4997,A146,COMPRAS!$B$3:$B$4997,">="&$C$4,COMPRAS!$B$3:$B$4997,"<="&$D$4)) -> 0 | E146: =IF(C146>0,D146/IF(H146<>"",H146,C146),"") | F146: =IF(AND($C$4="",$D$4=""),COUNTIF(COMPRAS!$G$3:$G$4997,A146),COUNTIFS(COMPRAS!$G$3:$G$4997,A146,COMPRAS!$B$3:$B$4997,">="&$C$4,COMPRAS!$B$3:$B$4997,"<="&$D$4)) -> 0 | G146: =IF(C146>0,"SI","")
A147: C3061 | B147: RAYA ROCAROSA (RJH) | C147: =IF(AND($C$4="",$D$4=""),SUMIFS(COMPRAS!$J$3:$J$4997,COMPRAS!$G$3:$G$4997,A147),SUMIFS(COMPRAS!$J$3:$J$4997,COMPRAS!$G$3:$G$4997,A147,COMPRAS!$B$3:$B$4997,">="&$C$4,COMPRAS!$B$3:$B$4997,"<="&$D$4)) -> 0 | D147: =IF(AND($C$4="",$D$4=""),SUMIFS(COMPRAS!$O$3:$O$4997,COMPRAS!$G$3:$G$4997,A147),SUMIFS(COMPRAS!$O$3:$O$4997,COMPRAS!$G$3:$G$4997,A147,COMPRAS!$B$3:$B$4997,">="&$C$4,COMPRAS!$B$3:$B$4997,"<="&$D$4)) -> 0 | E147: =IF(C147>0,D147/IF(H147<>"",H147,C147),"") | F147: =IF(AND($C$4="",$D$4=""),COUNTIF(COMPRAS!$G$3:$G$4997,A147),COUNTIFS(COMPRAS!$G$3:$G$4997,A147,COMPRAS!$B$3:$B$4997,">="&$C$4,COMPRAS!$B$3:$B$4997,"<="&$D$4)) -> 0 | G147: =IF(C147>0,"SI","")
A148: C3062 | B148: RAYA COLORADA (RJE) | C148: =IF(AND($C$4="",$D$4=""),SUMIFS(COMPRAS!$J$3:$J$4997,COMPRAS!$G$3:$G$4997,A148),SUMIFS(COMPRAS!$J$3:$J$4997,COMPRAS!$G$3:$G$4997,A148,COMPRAS!$B$3:$B$4997,">="&$C$4,COMPRAS!$B$3:$B$4997,"<="&$D$4)) -> 0 | D148: =IF(AND($C$4="",$D$4=""),SUMIFS(COMPRAS!$O$3:$O$4997,COMPRAS!$G$3:$G$4997,A148),SUMIFS(COMPRAS!$O$3:$O$4997,COMPRAS!$G$3:$G$4997,A148,COMPRAS!$B$3:$B$4997,">="&$C$4,COMPRAS!$B$3:$B$4997,"<="&$D$4)) -> 0 | E148: =IF(C148>0,D148/IF(H148<>"",H148,C148),"") | F148: =IF(AND($C$4="",$D$4=""),COUNTIF(COMPRAS!$G$3:$G$4997,A148),COUNTIFS(COMPRAS!$G$3:$G$4997,A148,COMPRAS!$B$3:$B$4997,">="&$C$4,COMPRAS!$B$3:$B$4997,"<="&$D$4)) -> 0 | G148: =IF(C148>0,"SI","")
A149: C3060 | B149: RAYA COMUN ALAS | C149: =IF(AND($C$4="",$D$4=""),SUMIFS(COMPRAS!$J$3:$J$4997,COMPRAS!$G$3:$G$4997,A149),SUMIFS(COMPRAS!$J$3:$J$4997,COMPRAS!$G$3:$G$4997,A149,COMPRAS!$B$3:$B$4997,">="&$C$4,COMPRAS!$B$3:$B$4997,"<="&$D$4)) -> 0 | D149: =IF(AND($C$4="",$D$4=""),SUMIFS(COMPRAS!$O$3:$O$4997,COMPRAS!$G$3:$G$4997,A149),SUMIFS(COMPRAS!$O$3:$O$4997,COMPRAS!$G$3:$G$4997,A149,COMPRAS!$B$3:$B$4997,">="&$C$4,COMPRAS!$B$3:$B$4997,"<="&$D$4)) -> 0 | E149: =IF(C149>0,D149/IF(H149<>"",H149,C149),"") | F149: =IF(AND($C$4="",$D$4=""),COUNTIF(COMPRAS!$G$3:$G$4997,A149),COUNTIFS(COMPRAS!$G$3:$G$4997,A149,COMPRAS!$B$3:$B$4997,">="&$C$4,COMPRAS!$B$3:$B$4997,"<="&$D$4)) -> 0 | G149: =IF(C149>0,"SI","")
A150: C306 | B150: RAYA SPP (SKA) | C150: =IF(AND($C$4="",$D$4=""),SUMIFS(COMPRAS!$J$3:$J$4997,COMPRAS!$G$3:$G$4997,A150),SUMIFS(COMPRAS!$J$3:$J$4997,COMPRAS!$G$3:$G$4997,A150,COMPRAS!$B$3:$B$4997,">="&$C$4,COMPRAS!$B$3:$B$4997,"<="&$D$4)) -> 0 | D150: =IF(AND($C$4="",$D$4=""),SUMIFS(COMPRAS!$O$3:$O$4997,COMPRAS!$G$3:$G$4997,A150),SUMIFS(COMPRAS!$O$3:$O$4997,COMPRAS!$G$3:$G$4997,A150,COMPRAS!$B$3:$B$4997,">="&$C$4,COMPRAS!$B$3:$B$4997,"<="&$D$4)) -> 0 | E150: =IF(C150>0,D150/IF(H150<>"",H150,C150),"") | F150: =IF(AND($C$4="",$D$4=""),COUNTIF(COMPRAS!$G$3:$G$4997,A150),COUNTIFS(COMPRAS!$G$3:$G$4997,A150,COMPRAS!$B$3:$B$4997,">="&$C$4,COMPRAS!$B$3:$B$4997,"<="&$D$4)) -> 0 | G150: =IF(C150>0,"SI","")
A151: C630 | B151: RODABALLO (TUR) | C151: =IF(AND($C$4="",$D$4=""),SUMIFS(COMPRAS!$J$3:$J$4997,COMPRAS!$G$3:$G$4997,A151),SUMIFS(COMPRAS!$J$3:$J$4997,COMPRAS!$G$3:$G$4997,A151,COMPRAS!$B$3:$B$4997,">="&$C$4,COMPRAS!$B$3:$B$4997,"<="&$D$4)) -> 0 | D151: =IF(AND($C$4="",$D$4=""),SUMIFS(COMPRAS!$O$3:$O$4997,COMPRAS!$G$3:$G$4997,A151),SUMIFS(COMPRAS!$O$3:$O$4997,COMPRAS!$G$3:$G$4997,A151,COMPRAS!$B$3:$B$4997,">="&$C$4,COMPRAS!$B$3:$B$4997,"<="&$D$4)) -> 0 | E151: =IF(C151>0,D151/IF(H151<>"",H151,C151),"") | F151: =IF(AND($C$4="",$D$4=""),COUNTIF(COMPRAS!$G$3:$G$4997,A151),COUNTIFS(COMPRAS!$G$3:$G$4997,A151,COMPRAS!$B$3:$B$4997,">="&$C$4,COMPRAS!$B$3:$B$4997,"<="&$D$4)) -> 0 | G151: =IF(C151>0,"SI","")
A152: C7599 | B152: SABLE BLANCO (SFS) | C152: =IF(AND($C$4="",$D$4=""),SUMIFS(COMPRAS!$J$3:$J$4997,COMPRAS!$G$3:$G$4997,A152),SUMIFS(COMPRAS!$J$3:$J$4997,COMPRAS!$G$3:$G$4997,A152,COMPRAS!$B$3:$B$4997,">="&$C$4,COMPRAS!$B$3:$B$4997,"<="&$D$4)) -> 0 | D152: =IF(AND($C$4="",$D$4=""),SUMIFS(COMPRAS!$O$3:$O$4997,COMPRAS!$G$3:$G$4997,A152),SUMIFS(COMPRAS!$O$3:$O$4997,COMPRAS!$G$3:$G$4997,A152,COMPRAS!$B$3:$B$4997,">="&$C$4,COMPRAS!$B$3:$B$4997,"<="&$D$4)) -> 0 | E152: =IF(C152>0,D152/IF(H152<>"",H152,C152),"") | F152: =IF(AND($C$4="",$D$4=""),COUNTIF(COMPRAS!$G$3:$G$4997,A152),COUNTIFS(COMPRAS!$G$3:$G$4997,A152,COMPRAS!$B$3:$B$4997,">="&$C$4,COMPRAS!$B$3:$B$4997,"<="&$D$4)) -> 0 | G152: =IF(C152>0,"SI","")
A153: C770 | B153: SABOGA/ SALEMA/ SALMA (SLM) | C153: =IF(AND($C$4="",$D$4=""),SUMIFS(COMPRAS!$J$3:$J$4997,COMPRAS!$G$3:$G$4997,A153),SUMIFS(COMPRAS!$J$3:$J$4997,COMPRAS!$G$3:$G$4997,A153,COMPRAS!$B$3:$B$4997,">="&$C$4,COMPRAS!$B$3:$B$4997,"<="&$D$4)) -> 0 | D153: =IF(AND($C$4="",$D$4=""),SUMIFS(COMPRAS!$O$3:$O$4997,COMPRAS!$G$3:$G$4997,A153),SUMIFS(COMPRAS!$O$3:$O$4997,COMPRAS!$G$3:$G$4997,A153,COMPRAS!$B$3:$B$4997,">="&$C$4,COMPRAS!$B$3:$B$4997,"<="&$D$4)) -> 0 | E153: =IF(C153>0,D153/IF(H153<>"",H153,C153),"") | F153: =IF(AND($C$4="",$D$4=""),COUNTIF(COMPRAS!$G$3:$G$4997,A153),COUNTIFS(COMPRAS!$G$3:$G$4997,A153,COMPRAS!$B$3:$B$4997,">="&$C$4,COMPRAS!$B$3:$B$4997,"<="&$D$4)) -> 0 | G153: =IF(C153>0,"SI","")
A154: C900 | B154: SALMON (SAL) | C154: =IF(AND($C$4="",$D$4=""),SUMIFS(COMPRAS!$J$3:$J$4997,COMPRAS!$G$3:$G$4997,A154),SUMIFS(COMPRAS!$J$3:$J$4997,COMPRAS!$G$3:$G$4997,A154,COMPRAS!$B$3:$B$4997,">="&$C$4,COMPRAS!$B$3:$B$4997,"<="&$D$4)) -> 0 | D154: =IF(AND($C$4="",$D$4=""),SUMIFS(COMPRAS!$O$3:$O$4997,COMPRAS!$G$3:$G$4997,A154),SUMIFS(COMPRAS!$O$3:$O$4997,COMPRAS!$G$3:$G$4997,A154,COMPRAS!$B$3:$B$4997,">="&$C$4,COMPRAS!$B$3:$B$4997,"<="&$D$4)) -> 0 | E154: =IF(C154>0,D154/IF(H154<>"",H154,C154),"") | F154: =IF(AND($C$4="",$D$4=""),COUNTIF(COMPRAS!$G$3:$G$4997,A154),COUNTIFS(COMPRAS!$G$3:$G$4997,A154,COMPRAS!$B$3:$B$4997,">="&$C$4,COMPRAS!$B$3:$B$4997,"<="&$D$4)) -> 0 | G154: =IF(C154>0,"SI","")
A155: C340 | B155: SALMONETE | C155: =IF(AND($C$4="",$D$4=""),SUMIFS(COMPRAS!$J$3:$J$4997,COMPRAS!$G$3:$G$4997,A155),SUMIFS(COMPRAS!$J$3:$J$4997,COMPRAS!$G$3:$G$4997,A155,COMPRAS!$B$3:$B$4997,">="&$C$4,COMPRAS!$B$3:$B$4997,"<="&$D$4)) -> 0 | D155: =IF(AND($C$4="",$D$4=""),SUMIFS(COMPRAS!$O$3:$O$4997,COMPRAS!$G$3:$G$4997,A155),SUMIFS(COMPRAS!$O$3:$O$4997,COMPRAS!$G$3:$G$4997,A155,COMPRAS!$B$3:$B$4997,">="&$C$4,COMPRAS!$B$3:$B$4997,"<="&$D$4)) -> 0 | E155: =IF(C155>0,D155/IF(H155<>"",H155,C155),"") | F155: =IF(AND($C$4="",$D$4=""),COUNTIF(COMPRAS!$G$3:$G$4997,A155),COUNTIFS(COMPRAS!$G$3:$G$4997,A155,COMPRAS!$B$3:$B$4997,">="&$C$4,COMPRAS!$B$3:$B$4997,"<="&$D$4)) -> 0 | G155: =IF(C155>0,"SI","")
A156: C341 | B156: SALMONETE ROCA (MUR) | C156: =IF(AND($C$4="",$D$4=""),SUMIFS(COMPRAS!$J$3:$J$4997,COMPRAS!$G$3:$G$4997,A156),SUMIFS(COMPRAS!$J$3:$J$4997,COMPRAS!$G$3:$G$4997,A156,COMPRAS!$B$3:$B$4997,">="&$C$4,COMPRAS!$B$3:$B$4997,"<="&$D$4)) -> 0 | D156: =IF(AND($C$4="",$D$4=""),SUMIFS(COMPRAS!$O$3:$O$4997,COMPRAS!$G$3:$G$4997,A156),SUMIFS(COMPRAS!$O$3:$O$4997,COMPRAS!$G$3:$G$4997,A156,COMPRAS!$B$3:$B$4997,">="&$C$4,COMPRAS!$B$3:$B$4997,"<="&$D$4)) -> 0 | E156: =IF(C156>0,D156/IF(H156<>"",H156,C156),"") | F156: =IF(AND($C$4="",$D$4=""),COUNTIF(COMPRAS!$G$3:$G$4997,A156),COUNTIFS(COMPRAS!$G$3:$G$4997,A156,COMPRAS!$B$3:$B$4997,">="&$C$4,COMPRAS!$B$3:$B$4997,"<="&$D$4)) -> 0 | G156: =IF(C156>0,"SI","")
... A167: C2551 | B167: VISPOS/ ESCORPORAS | C167: =IF(AND($C$4="",$D$4=""),SUMIFS(COMPRAS!$J$3:$J$4997,COMPRAS!$G$3:$G$4997,A167),SUMIFS(COMPRAS!$J$3:$J$4997,COMPRAS!$G$3:$G$4997,A167,COMPRAS!$B$3:$B$4997,">="&$C$4,COMPRAS!$B$3:$B$4997,"<="&$D$4)) -> 12.75 | D167: =IF(AND($C$4="",$D$4=""),SUMIFS(COMPRAS!$O$3:$O$4997,COMPRAS!$G$3:$G$4997,A167),SUMIFS(COMPRAS!$O$3:$O$4997,COMPRAS!$G$3:$G$4997,A167,COMPRAS!$B$3:$B$4997,">="&$C$4,COMPRAS!$B$3:$B$4997,"<="&$D$4)) -> 91.035 | E167: =IF(C167>0,D167/IF(H167<>"",H167,C167),"") -> 7.14 | F167: =IF(AND($C$4="",$D$4=""),COUNTIF(COMPRAS!$G$3:$G$4997,A167),COUNTIFS(COMPRAS!$G$3:$G$4997,A167,COMPRAS!$B$3:$B$4997,">="&$C$4,COMPRAS!$B$3:$B$4997,"<="&$D$4)) -> 1 | G167: =IF(C167>0,"SI","") -> SI

Sheet COMPRAS
A2: N PARTIDA | B2: FECHA | C2: ALB PROV | D2: COD PROV | E2: PROVEEDOR | F2: OP 2% | G2: COD PROD | H2: DESCRIPCION | I2: CAJAS | J2: KILOS | K2: EUR/KG | L2: BASE IMP ZARAGOZA | M2: BASE IMP ZGZ + IVA | N2: 2% OP | O2: BASE IMP REAL | P2: IVA 10% | Q2: TOTAL FACT | R2: CONTROL
A3: 5900 | B3: 46186 | C3: 6125 | D3: 50020 | E3: =IF(D3<>"",IFERROR(VLOOKUP(D3,PROVEEDORES!$A:$B,2,0),"!COD NO ENCONTRADO"),"") -> PACO MOINELO | F3: =IF(D3<>"",IFERROR(VLOOKUP(D3,PROVEEDORES!$A:$C,3,0),""),"") -> S | G3: C250 | H3: =IF(G3<>"",IFERROR(VLOOKUP(G3,PRODUCTOS!$A:$B,2,0),"!COD NO ENCONTRADO"),"") -> CONGRIO 10+ (COE) | I3: 2 | J3: =12+13.5 -> 25.5 | K3: 3.8 | L3: =IF(AND(J3<>"",K3<>""),J3*K3,"") -> 96.9 | M3: =IF(L3<>"",L3*1.1,"") -> 106.59 | N3: =IF(F3="S",L3*0.02,0) -> 1.938 | O3: =IF(L3<>"",L3+N3,"") -> 98.838 | P3: =IF(O3<>"",O3*0.1,"") -> 9.8838 | Q3: =IF(O3<>"",O3+P3,"") -> 108.7218 | R3: s
A4: 5901 | B4: 46186 | C4: 31595 | D4: 50106 | E4: =IF(D4<>"",IFERROR(VLOOKUP(D4,PROVEEDORES!$A:$B,2,0),"!COD NO ENCONTRADO"),"") -> SONIA VENTAS S.L | F4: =IF(D4<>"",IFERROR(VLOOKUP(D4,PROVEEDORES!$A:$C,3,0),""),"") -> S | G4: C1300 | H4: =IF(G4<>"",IFERROR(VLOOKUP(G4,PRODUCTOS!$A:$B,2,0),"!COD NO ENCONTRADO"),"") -> MERLUZA EUROPEA PINCHO COSTA | I4: 1 | J4: 14.5 | K4: 5.3 | L4: =IF(AND(J4<>"",K4<>""),J4*K4,"") -> 76.85 | M4: =IF(L4<>"",L4*1.1,"") -> 84.535 | N4: =IF(F4="S",L4*0.02,0) -> 1.537 | O4: =IF(L4<>"",L4+N4,"") -> 78.387 | P4: =IF(O4<>"",O4*0.1,"") -> 7.8387 | Q4: =IF(O4<>"",O4+P4,"") -> 86.2257 | R4: s
A5: 5901 | B5: 46186 | C5: 31595 | D5: 50106 | E5: =IF(D5<>"",IFERROR(VLOOKUP(D5,PROVEEDORES!$A:$B,2,0),"!COD NO ENCONTRADO"),"") -> SONIA VENTAS S.L | F5: =IF(D5<>"",IFERROR(VLOOKUP(D5,PROVEEDORES!$A:$C,3,0),""),"") -> S | G5: C1300 | H5: =IF(G5<>"",IFERROR(VLOOKUP(G5,PRODUCTOS!$A:$B,2,0),"!COD NO ENCONTRADO"),"") -> MERLUZA EUROPEA PINCHO COSTA | I5: 1 | J5: 16 | K5: 8.8 | L5: =IF(AND(J5<>"",K5<>""),J5*K5,"") -> 140.8 | M5: =IF(L5<>"",L5*1.1,"") -> 154.88 | N5: =IF(F5="S",L5*0.02,0) -> 2.816 | O5: =IF(L5<>"",L5+N5,"") -> 143.616 | P5: =IF(O5<>"",O5*0.1,"") -> 14.3616 | Q5: =IF(O5<>"",O5+P5,"") -> 157.9776 | R5: s
A6: 5902 | B6: 46186 | C6: 8630 | D6: 50001 | E6: =IF(D6<>"",IFERROR(VLOOKUP(D6,PROVEEDORES!$A:$B,2,0),"!COD NO ENCONTRADO"),"") -> COPESA | F6: =IF(D6<>"",IFERROR(VLOOKUP(D6,PROVEEDORES!$A:$C,3,0),""),"") -> S | G6: C1730 | H6: =IF(G6<>"",IFERROR(VLOOKUP(G6,PRODUCTOS!$A:$B,2,0),"!COD NO ENCONTRADO"),"") -> MERLUZA EUROPEA ARRASTRE (HKE) | I6: 7 | J6: =6.5+5.25+5.75+18+4.75 -> 40.25 | K6: 5.4 | L6: =IF(AND(J6<>"",K6<>""),J6*K6,"") -> 217.35 | M6: =IF(L6<>"",L6*1.1,"") -> 239.085 | N6: =IF(F6="S",L6*0.02,0) -> 4.347 | O6: =IF(L6<>"",L6+N6,"") -> 221.697 | P6: =IF(O6<>"",O6*0.1,"") -> 22.1697 | Q6: =IF(O6<>"",O6+P6,"") -> 243.8667 | R6: s
A7: 5902 | B7: 46186 | C7: 8630 | D7: 50001 | E7: =IF(D7<>"",IFERROR(VLOOKUP(D7,PROVEEDORES!$A:$B,2,0),"!COD NO ENCONTRADO"),"") -> COPESA | F7: =IF(D7<>"",IFERROR(VLOOKUP(D7,PROVEEDORES!$A:$C,3,0),""),"") -> S | G7: C5240 | H7: =IF(G7<>"",IFERROR(VLOOKUP(G7,PRODUCTOS!$A:$B,2,0),"!COD NO ENCONTRADO"),"") -> RAPE NEGRO (ANK) | I7: 2 | J7: =15.5+12.75 -> 28.25 | K7: 4.3 | L7: =IF(AND(J7<>"",K7<>""),J7*K7,"") -> 121.475 | M7: =IF(L7<>"",L7*1.1,"") -> 133.6225 | N7: =IF(F7="S",L7*0.02,0) -> 2.4295 | O7: =IF(L7<>"",L7+N7,"") -> 123.9045 | P7: =IF(O7<>"",O7*0.1,"") -> 12.39045 | Q7: =IF(O7<>"",O7+P7,"") -> 136.29495 | R7: s
A8: 5902 | B8: 46186 | C8: 8630 | D8: 50001 | E8: =IF(D8<>"",IFERROR(VLOOKUP(D8,PROVEEDORES!$A:$B,2,0),"!COD NO ENCONTRADO"),"") -> COPESA | F8: =IF(D8<>"",IFERROR(VLOOKUP(D8,PROVEEDORES!$A:$C,3,0),""),"") -> S | G8: C410 | H8: =IF(G8<>"",IFERROR(VLOOKUP(G8,PRODUCTOS!$A:$B,2,0),"!COD NO ENCONTRADO"),"") -> CINTAS/ PEZ CINTA (CBC) | I8: 2 | J8: 11.5 | K8: 2.4 | L8: =IF(AND(J8<>"",K8<>""),J8*K8,"") -> 27.6 | M8: =IF(L8<>"",L8*1.1,"") -> 30.36 | N8: =IF(F8="S",L8*0.02,0) -> 0.552 | O8: =IF(L8<>"",L8+N8,"") -> 28.152 | P8: =IF(O8<>"",O8*0.1,"") -> 2.8152 | Q8: =IF(O8<>"",O8+P8,"") -> 30.9672 | R8: s
A9: 5903 | B9: 46186 | C9: 3499 | D9: 50163 | E9: =IF(D9<>"",IFERROR(VLOOKUP(D9,PROVEEDORES!$A:$B,2,0),"!COD NO ENCONTRADO"),"") -> SUBASTAS RIVERA S.L. | F9: =IF(D9<>"",IFERROR(VLOOKUP(D9,PROVEEDORES!$A:$C,3,0),""),"") -> S | G9: C5240 | H9: =IF(G9<>"",IFERROR(VLOOKUP(G9,PRODUCTOS!$A:$B,2,0),"!COD NO ENCONTRADO"),"") -> RAPE NEGRO (ANK) | I9: 2 | J9: =10.25+7.25 -> 17.5 | K9: 4.2 | L9: =IF(AND(J9<>"",K9<>""),J9*K9,"") -> 73.5 | M9: =IF(L9<>"",L9*1.1,"") -> 80.85 | N9: =IF(F9="S",L9*0.02,0) -> 1.47 | O9: =IF(L9<>"",L9+N9,"") -> 74.97 | P9: =IF(O9<>"",O9*0.1,"") -> 7.497 | Q9: =IF(O9<>"",O9+P9,"") -> 82.467 | R9: s
A10: 5903 | B10: 46186 | C10: 3499 | D10: 50163 | E10: =IF(D10<>"",IFERROR(VLOOKUP(D10,PROVEEDORES!$A:$B,2,0),"!COD NO ENCONTRADO"),"") -> SUBASTAS RIVERA S.L. | F10: =IF(D10<>"",IFERROR(VLOOKUP(D10,PROVEEDORES!$A:$C,3,0),""),"") -> S | G10: C5240 | H10: =IF(G10<>"",IFERROR(VLOOKUP(G10,PRODUCTOS!$A:$B,2,0),"!COD NO ENCONTRADO"),"") -> RAPE NEGRO (ANK) | I10: 5 | J10: =5.9+2.75+0.75+4.9+4.8 -> 19.1 | K10: 4.2 | L10: =IF(AND(J10<>"",K10<>""),J10*K10,"") -> 80.22 | M10: =IF(L10<>"",L10*1.1,"") -> 88.242 | N10: =IF(F10="S",L10*0.02,0) -> 1.6044 | O10: =IF(L10<>"",L10+N10,"") -> 81.8244 | P10: =IF(O10<>"",O10*0.1,"") -> 8.18244 | Q10: =IF(O10<>"",O10+P10,"") -> 90.00684 | R10: s
A11: 5903 | B11: 46186 | C11: 3499 | D11: 50163 | E11: =IF(D11<>"",IFERROR(VLOOKUP(D11,PROVEEDORES!$A:$B,2,0),"!COD NO ENCONTRADO"),"") -> SUBASTAS RIVERA S.L. | F11: =IF(D11<>"",IFERROR(VLOOKUP(D11,PROVEEDORES!$A:$C,3,0),""),"") -> S | G11: C5250 | H11: =IF(G11<>"",IFERROR(VLOOKUP(G11,PRODUCTOS!$A:$B,2,0),"!COD NO ENCONTRADO"),"") -> RAPE BLANCO DIA (MON) | I11: 3 | J11: =5+2.3+2.5 -> 9.8 | K11: 5.3 | L11: =IF(AND(J11<>"",K11<>""),J11*K11,"") -> 51.94 | M11: =IF(L11<>"",L11*1.1,"") -> 57.134 | N11: =IF(F11="S",L11*0.02,0) -> 1.0388 | O11: =IF(L11<>"",L11+N11,"") -> 52.9788 | P11: =IF(O11<>"",O11*0.1,"") -> 5.29788 | Q11: =IF(O11<>"",O11+P11,"") -> 58.27668 | R11: s
A12: 5903 | B12: 46186 | C12: 3499 | D12: 50163 | E12: =IF(D12<>"",IFERROR(VLOOKUP(D12,PROVEEDORES!$A:$B,2,0),"!COD NO ENCONTRADO"),"") -> SUBASTAS RIVERA S.L. | F12: =IF(D12<>"",IFERROR(VLOOKUP(D12,PROVEEDORES!$A:$C,3,0),""),"") -> S | G12: C5240 | H12: =IF(G12<>"",IFERROR(VLOOKUP(G12,PRODUCTOS!$A:$B,2,0),"!COD NO ENCONTRADO"),"") -> RAPE NEGRO (ANK) | I12: 2 | J12: =5.4+5.1 -> 10.5 | K12: 4.2 | L12: =IF(AND(J12<>"",K12<>""),J12*K12,"") -> 44.1 | M12: =IF(L12<>"",L12*1.1,"") -> 48.51 | N12: =IF(F12="S",L12*0.02,0) -> 0.882 | O12: =IF(L12<>"",L12+N12,"") -> 44.982 | P12: =IF(O12<>"",O12*0.1,"") -> 4.4982 | Q12: =IF(O12<>"",O12+P12,"") -> 49.4802 | R12: s
A13: 5904 | B13: 46188 | C13: 26SM/2328 | D13: 50509 | E13: =IF(D13<>"",IFERROR(VLOOKUP(D13,PROVEEDORES!$A:$B,2,0),"!COD NO ENCONTRADO"),"") -> AZORFISK UNIPERSONAL LDA | F13: =IF(D13<>"",IFERROR(VLOOKUP(D13,PROVEEDORES!$A:$C,3,0),""),"") -> N | G13: C365 | H13: =IF(G13<>"",IFERROR(VLOOKUP(G13,PRODUCTOS!$A:$B,2,0),"!COD NO ENCONTRADO"),"") -> BESUGO (BSR) | I13: 1 | J13: 7.6 | K13: 22 | L13: =IF(AND(J13<>"",K13<>""),J13*K13,"") -> 167.2 | M13: =IF(L13<>"",L13*1.1,"") -> 183.92 | N13: =IF(F13="S",L13*0.02,0) -> 0 | O13: =IF(L13<>"",L13+N13,"") -> 167.2 | P13: =IF(O13<>"",O13*0.1,"") -> 16.72 | Q13: =IF(O13<>"",O13+P13,"") -> 183.92 | R13: s
A14: 5904 | B14: 46188 | C14: 26SM/2329 | D14: 50509 | E14: =IF(D14<>"",IFERROR(VLOOKUP(D14,PROVEEDORES!$A:$B,2,0),"!COD NO ENCONTRADO"),"") -> AZORFISK UNIPERSONAL LDA | F14: =IF(D14<>"",IFERROR(VLOOKUP(D14,PROVEEDORES!$A:$C,3,0),""),"") -> N | G14: C3110 | H14: =IF(G14<>"",IFERROR(VLOOKUP(G14,PRODUCTOS!$A:$B,2,0),"!COD NO ENCONTRADO"),"") -> MACHOS/ REYES/ ALFONSINOS (BYS) | I14: 1 | J14: 8.3 | K14: 20.9 | L14: =IF(AND(J14<>"",K14<>""),J14*K14,"") -> 173.47 | M14: =IF(L14<>"",L14*1.1,"") -> 190.817 | N14: =IF(F14="S",L14*0.02,0) -> 0 | O14: =IF(L14<>"",L14+N14,"") -> 173.47 | P14: =IF(O14<>"",O14*0.1,"") -> 17.347 | Q14: =IF(O14<>"",O14+P14,"") -> 190.817 | R14: s
A15: 5904 | B15: 46188 | C15: 26SM/2330 | D15: 50509 | E15: =IF(D15<>"",IFERROR(VLOOKUP(D15,PROVEEDORES!$A:$B,2,0),"!COD NO ENCONTRADO"),"") -> AZORFISK UNIPERSONAL LDA | F15: =IF(D15<>"",IFERROR(VLOOKUP(D15,PROVEEDORES!$A:$C,3,0),""),"") -> N | G15: C3111 | H15: =IF(G15<>"",IFERROR(VLOOKUP(G15,PRODUCTOS!$A:$B,2,0),"!COD NO ENCONTRADO"),"") -> VIRREY/ PALOMETA ROJA | I15: 1 | J15: 15.7 | K15: 63.5 | L15: =IF(AND(J15<>"",K15<>""),J15*K15,"") -> 996.95 | M15: =IF(L15<>"",L15*1.1,"") -> 1096.645 | N15: =IF(F15="S",L15*0.02,0) -> 0 | O15: =IF(L15<>"",L15+N15,"") -> 996.95 | P15: =IF(O15<>"",O15*0.1,"") -> 99.695 | Q15: =IF(O15<>"",O15+P15,"") -> 1096.645 | R15: s
A16: 5905 | B16: 46188 | C16: 8783 | D16: 50001 | E16: =IF(D16<>"",IFERROR(VLOOKUP(D16,PROVEEDORES!$A:$B,2,0),"!COD NO ENCONTRADO"),"") -> COPESA | F16: =IF(D16<>"",IFERROR(VLOOKUP(D16,PROVEEDORES!$A:$C,3,0),""),"") -> S | G16: C1730 | H16: =IF(G16<>"",IFERROR(VLOOKUP(G16,PRODUCTOS!$A:$B,2,0),"!COD NO ENCONTRADO"),"") -> MERLUZA EUROPEA ARRASTRE (HKE) | I16: 3 | J16: =27.75+31.75+29 -> 88.5 | K16: 3.8 | L16: =IF(AND(J16<>"",K16<>""),J16*K16,"") -> 336.3 | M16: =IF(L16<>"",L16*1.1,"") -> 369.93 | N16: =IF(F16="S",L16*0.02,0) -> 6.726 | O16: =IF(L16<>"",L16+N16,"") -> 343.026 | P16: =IF(O16<>"",O16*0.1,"") -> 34.3026 | Q16: =IF(O16<>"",O16+P16,"") -> 377.3286 | R16: s
A17: 5906 | B17: 46188 | C17: 10600 | D17: 50048 | E17: =IF(D17<>"",IFERROR(VLOOKUP(D17,PROVEEDORES!$A:$B,2,0),"!COD NO ENCONTRADO"),"") -> JOSE LUIS CORREA KESSLER S.L. | F17: =IF(D17<>"",IFERROR(VLOOKUP(D17,PROVEEDORES!$A:$C,3,0),""),"") -> N | G17: C211 | H17: =IF(G17<>"",IFERROR(VLOOKUP(G17,PRODUCTOS!$A:$B,2,0),"!COD NO ENCONTRADO"),"") -> POTA (SQI) | I17: 5 | J17: 30 | K17: 2.1 | L17: =IF(AND(J17<>"",K17<>""),J17*K17,"") -> 63 | M17: =IF(L17<>"",L17*1.1,"") -> 69.3 | N17: =IF(F17="S",L17*0.02,0) -> 0 | O17: =IF(L17<>"",L17+N17,"") -> 63 | P17: =IF(O17<>"",O17*0.1,"") -> 6.3 | Q17: =IF(O17<>"",O17+P17,"") -> 69.3 | R17: s
A18: 5907 | B18: 46188 | C18: PV3/3311 | D18: 50035 | E18: =IF(D18<>"",IFERROR(VLOOKUP(D18,PROVEEDORES!$A:$B,2,0),"!COD NO ENCONTRADO"),"") -> SCANFISK SEAFFOD S,L | F18: =IF(D18<>"",IFERROR(VLOOKUP(D18,PROVEEDORES!$A:$C,3,0),""),"") -> N | G18: C142 | H18: =IF(G18<>"",IFERROR(VLOOKUP(G18,PRODUCTOS!$A:$B,2,0),"!COD NO ENCONTRADO"),"") -> MERLUZA EUROPEA VOLANTA ALTURA | I18: 4 | J18: 43 | K18: 6.4 | L18: =IF(AND(J18<>"",K18<>""),J18*K18,"") -> 275.2 | M18: =IF(L18<>"",L18*1.1,"") -> 302.72 | N18: =IF(F18="S",L18*0.02,0) -> 0 | O18: =IF(L18<>"",L18+N18,"") -> 275.2 | P18: =IF(O18<>"",O18*0.1,"") -> 27.52 | Q18: =IF(O18<>"",O18+P18,"") -> 302.72 | R18: s
A19: 5907 | B19: 46188 | C19: PV3/3311 | D19: 50035 | E19: =IF(D19<>"",IFERROR(VLOOKUP(D19,PROVEEDORES!$A:$B,2,0),"!COD NO ENCONTRADO"),"") -> SCANFISK SEAFFOD S,L | F19: =IF(D19<>"",IFERROR(VLOOKUP(D19,PROVEEDORES!$A:$C,3,0),""),"") -> N | G19: C1206 | H19: =IF(G19<>"",IFERROR(VLOOKUP(G19,PRODUCTOS!$A:$B,2,0),"!COD NO ENCONTRADO"),"") -> MERLUZA EUROPEA PINCHO | I19: 4 | J19: 21.5 | K19: 5.9 | L19: =IF(AND(J19<>"",K19<>""),J19*K19,"") -> 126.85 | M19: =IF(L19<>"",L19*1.1,"") -> 139.535 | N19: =IF(F19="S",L19*0.02,0) -> 0 | O19: =IF(L19<>"",L19+N19,"") -> 126.85 | P19: =IF(O19<>"",O19*0.1,"") -> 12.685 | Q19: =IF(O19<>"",O19+P19,"") -> 139.535 | R19: s
A20: 5907 | B20: 46188 | C20: PV3/3311 | D20: 50035 | E20: =IF(D20<>"",IFERROR(VLOOKUP(D20,PROVEEDORES!$A:$B,2,0),"!COD NO ENCONTRADO"),"") -> SCANFISK SEAFFOD S,L | F20: =IF(D20<>"",IFERROR(VLOOKUP(D20,PROVEEDORES!$A:$C,3,0),""),"") -> N | G20: C2106 | H20: =IF(G20<>"",IFERROR(VLOOKUP(G20,PRODUCTOS!$A:$B,2,0),"!COD NO ENCONTRADO"),"") -> !COD NO ENCONTRADO | I20: 2 | J20: 22.5 | K20: 9.4 | L20: =IF(AND(J20<>"",K20<>""),J20*K20,"") -> 211.5 | M20: =IF(L20<>"",L20*1.1,"") -> 232.65 | N20: =IF(F20="S",L20*0.02,0) -> 0 | O20: =IF(L20<>"",L20+N20,"") -> 211.5 | P20: =IF(O20<>"",O20*0.1,"") -> 21.15 | Q20: =IF(O20<>"",O20+P20,"") -> 232.65 | R20: s
A21: 5908 | B21: 46188 | C21: 528/1206 | D21: 50232 | E21: =IF(D21<>"",IFERROR(VLOOKUP(D21,PROVEEDORES!$A:$B,2,0),"!COD NO ENCONTRADO"),"") -> XESTION NOVA LONXA RIVEIRA S.L. | F21: =IF(D21<>"",IFERROR(VLOOKUP(D21,PROVEEDORES!$A:$C,3,0),""),"") -> S | G21: C9860 | H21: =IF(G21<>"",IFERROR(VLOOKUP(G21,PRODUCTOS!$A:$B,2,0),"!COD NO ENCONTRADO"),"") -> PEON/ PION (ATP) | I21: 9 | J21: 44 | K21: 4 | L21: =IF(AND(J21<>"",K21<>""),J21*K21,"") -> 176 | M21: =IF(L21<>"",L21*1.1,"") -> 193.6 | N21: =IF(F21="S",L21*0.02,0) -> 3.52 | O21: =IF(L21<>"",L21+N21,"") -> 179.52 | P21: =IF(O21<>"",O21*0.1,"") -> 17.952 | Q21: =IF(O21<>"",O21+P21,"") -> 197.472 | R21: s
A22: 5908 | B22: 46188 | C22: 528/1206 | D22: 50232 | E22: =IF(D22<>"",IFERROR(VLOOKUP(D22,PROVEEDORES!$A:$B,2,0),"!COD NO ENCONTRADO"),"") -> XESTION NOVA LONXA RIVEIRA S.L. | F22: =IF(D22<>"",IFERROR(VLOOKUP(D22,PROVEEDORES!$A:$C,3,0),""),"") -> S | G22: C2566 | H22: =IF(G22<>"",IFERROR(VLOOKUP(G22,PRODUCTOS!$A:$B,2,0),"!COD NO ENCONTRADO"),"") -> ESCACHO/ ARETE/ RUBIO (GUR) | I22: 4 | J22: 22.25 | K22: 1.5 | L22: =IF(AND(J22<>"",K22<>""),J22*K22,"") -> 33.375 | M22: =IF(L22<>"",L22*1.1,"") -> 36.7125 | N22: =IF(F22="S",L22*0.02,0) -> 0.6675 | O22: =IF(L22<>"",L22+N22,"") -> 34.0425 | P22: =IF(O22<>"",O22*0.1,"") -> 3.40425 | Q22: =IF(O22<>"",O22+P22,"") -> 37.44675 | R22: s
A23: 5909 | B23: 46189 | C23: 16405 | D23: 50163 | E23: =IF(D23<>"",IFERROR(VLOOKUP(D23,PROVEEDORES!$A:$B,2,0),"!COD NO ENCONTRADO"),"") -> SUBASTAS RIVERA S.L. | F23: =IF(D23<>"",IFERROR(VLOOKUP(D23,PROVEEDORES!$A:$C,3,0),""),"") -> S | G23: C255 | H23: =IF(G23<>"",IFERROR(VLOOKUP(G23,PRODUCTOS!$A:$B,2,0),"!COD NO ENCONTRADO"),"") -> CABRAS/ GALLINETA (BRF) | I23: 2 | J23: =7.1+5.75 -> 12.85 | K23: 11 | L23: =IF(AND(J23<>"",K23<>""),J23*K23,"") -> 141.35 | M23: =IF(L23<>"",L23*1.1,"") -> 155.485 | N23: =IF(F23="S",L23*0.02,0) -> 2.827 | O23: =IF(L23<>"",L23+N23,"") -> 144.177 | P23: =IF(O23<>"",O23*0.1,"") -> 14.4177 | Q23: =IF(O23<>"",O23+P23,"") -> 158.5947 | R23: s
A24: 5909 | B24: 46189 | C24: 16405 | D24: 50163 | E24: =IF(D24<>"",IFERROR(VLOOKUP(D24,PROVEEDORES!$A:$B,2,0),"!COD NO ENCONTRADO"),"") -> SUBASTAS RIVERA S.L. | F24: =IF(D24<>"",IFERROR(VLOOKUP(D24,PROVEEDORES!$A:$C,3,0),""),"") -> S | G24: C999 | H24: =IF(G24<>"",IFERROR(VLOOKUP(G24,PRODUCTOS!$A:$B,2,0),"!COD NO ENCONTRADO"),"") -> VARIADO PEQUEÑO | I24: 2 | J24: =5.25+4.25 -> 9.5 | K24: 0.5 | L24: =IF(AND(J24<>"",K24<>""),J24*K24,"") -> 4.75 | M24: =IF(L24<>"",L24*1.1,"") -> 5.225 | N24: =IF(F24="S",L24*0.02,0) -> 0.095 | O24: =IF(L24<>"",L24+N24,"") -> 4.845 | P24: =IF(O24<>"",O24*0.1,"") -> 0.4845 | Q24: =IF(O24<>"",O24+P24,"") -> 5.3295 | R24: s
A25: 5909 | B25: 46189 | C25: 16405 | D25: 50163 | E25: =IF(D25<>"",IFERROR(VLOOKUP(D25,PROVEEDORES!$A:$B,2,0),"!COD NO ENCONTRADO"),"") -> SUBASTAS RIVERA S.L. | F25: =IF(D25<>"",IFERROR(VLOOKUP(D25,PROVEEDORES!$A:$C,3,0),""),"") -> S | G25: C999 | H25: =IF(G25<>"",IFERROR(VLOOKUP(G25,PRODUCTOS!$A:$B,2,0),"!COD NO ENCONTRADO"),"") -> VARIADO PEQUEÑO | I25: 3 | J25: =18.25+10.75 -> 29 | K25: 1.15 | L25: =IF(AND(J25<>"",K25<>""),J25*K25,"") -> 33.35 | M25: =IF(L25<>"",L25*1.1,"") -> 36.685 | N25: =IF(F25="S",L25*0.02,0) -> 0.667 | O25: =IF(L25<>"",L25+N25,"") -> 34.017 | P25: =IF(O25<>"",O25*0.1,"") -> 3.4017 | Q25: =IF(O25<>"",O25+P25,"") -> 37.4187 | R25: s
A26: 5909 | B26: 46189 | C26: 16405 | D26: 50163 | E26: =IF(D26<>"",IFERROR(VLOOKUP(D26,PROVEEDORES!$A:$B,2,0),"!COD NO ENCONTRADO"),"") -> SUBASTAS RIVERA S.L. | F26: =IF(D26<>"",IFERROR(VLOOKUP(D26,PROVEEDORES!$A:$C,3,0),""),"") -> S | G26: C1730 | H26: =IF(G26<>"",IFERROR(VLOOKUP(G26,PRODUCTOS!$A:$B,2,0),"!COD NO ENCONTRADO"),"") -> MERLUZA EUROPEA ARRASTRE (HKE) | I26: 2 | J26: =9.25+9.75 -> 19 | K26: 4.8 | L26: =IF(AND(J26<>"",K26<>""),J26*K26,"") -> 91.2 | M26: =IF(L26<>"",L26*1.1,"") -> 100.32 | N26: =IF(F26="S",L26*0.02,0) -> 1.824 | O26: =IF(L26<>"",L26+N26,"") -> 93.024 | P26: =IF(O26<>"",O26*0.1,"") -> 9.3024 | Q26: =IF(O26<>"",O26+P26,"") -> 102.3264 | R26: s
A27: 5910 | B27: 46189 | D27: 50160 | E27: =IF(D27<>"",IFERROR(VLOOKUP(D27,PROVEEDORES!$A:$B,2,0),"!COD NO ENCONTRADO"),"") -> SUBASTAS CORUÑA S.L. | F27: =IF(D27<>"",IFERROR(VLOOKUP(D27,PROVEEDORES!$A:$C,3,0),""),"") -> S | G27: C999 | H27: =IF(G27<>"",IFERROR(VLOOKUP(G27,PRODUCTOS!$A:$B,2,0),"!COD NO ENCONTRADO"),"") -> VARIADO PEQUEÑO | I27: 8 | J27: =6.25+6.25+5.75+5.75+6+5.5+6.25+6.25 -> 48 | K27: 0.5 | L27: =IF(AND(J27<>"",K27<>""),J27*K27,"") -> 24 | M27: =IF(L27<>"",L27*1.1,"") -> 26.4 | N27: =IF(F27="S",L27*0.02,0) -> 0.48 | O27: =IF(L27<>"",L27+N27,"") -> 24.48 | P27: =IF(O27<>"",O27*0.1,"") -> 2.448 | Q27: =IF(O27<>"",O27+P27,"") -> 26.928 | R27: s
A28: 5910 | B28: 46189 | C28: 4660 | D28: 50160 | E28: =IF(D28<>"",IFERROR(VLOOKUP(D28,PROVEEDORES!$A:$B,2,0),"!COD NO ENCONTRADO"),"") -> SUBASTAS CORUÑA S.L. | F28: =IF(D28<>"",IFERROR(VLOOKUP(D28,PROVEEDORES!$A:$C,3,0),""),"") -> S | G28: C1730 | H28: =IF(G28<>"",IFERROR(VLOOKUP(G28,PRODUCTOS!$A:$B,2,0),"!COD NO ENCONTRADO"),"") -> MERLUZA EUROPEA ARRASTRE (HKE) | I28: 1 | J28: 7 | K28: 4.9 | L28: =IF(AND(J28<>"",K28<>""),J28*K28,"") -> 34.3 | M28: =IF(L28<>"",L28*1.1,"") -> 37.73 | N28: =IF(F28="S",L28*0.02,0) -> 0.686 | O28: =IF(L28<>"",L28+N28,"") -> 34.986 | P28: =IF(O28<>"",O28*0.1,"") -> 3.4986 | Q28: =IF(O28<>"",O28+P28,"") -> 38.4846 | R28: s
A29: 5910 | B29: 46189 | C29: 4660 | D29: 50160 | E29: =IF(D29<>"",IFERROR(VLOOKUP(D29,PROVEEDORES!$A:$B,2,0),"!COD NO ENCONTRADO"),"") -> SUBASTAS CORUÑA S.L. | F29: =IF(D29<>"",IFERROR(VLOOKUP(D29,PROVEEDORES!$A:$C,3,0),""),"") -> S | G29: C1750 | H29: =IF(G29<>"",IFERROR(VLOOKUP(G29,PRODUCTOS!$A:$B,2,0),"!COD NO ENCONTRADO"),"") -> MERLUZA EUROPEA PAREJA (HKE) | I29: 1 | J29: 13.25 | K29: 5.4 | L29: =IF(AND(J29<>"",K29<>""),J29*K29,"") -> 71.55 | M29: =IF(L29<>"",L29*1.1,"") -> 78.705 | N29: =IF(F29="S",L29*0.02,0) -> 1.431 | O29: =IF(L29<>"",L29+N29,"") -> 72.981 | P29: =IF(O29<>"",O29*0.1,"") -> 7.2981 | Q29: =IF(O29<>"",O29+P29,"") -> 80.2791 | R29: s
A30: 5910 | B30: 46189 | C30: 4660 | D30: 50160 | E30: =IF(D30<>"",IFERROR(VLOOKUP(D30,PROVEEDORES!$A:$B,2,0),"!COD NO ENCONTRADO"),"") -> SUBASTAS CORUÑA S.L. | F30: =IF(D30<>"",IFERROR(VLOOKUP(D30,PROVEEDORES!$A:$C,3,0),""),"") -> S | G30: C5240 | H30: =IF(G30<>"",IFERROR(VLOOKUP(G30,PRODUCTOS!$A:$B,2,0),"!COD NO ENCONTRADO"),"") -> RAPE NEGRO (ANK) | I30: 4 | J30: 38.65 | K30: 4 | L30: =IF(AND(J30<>"",K30<>""),J30*K30,"") -> 154.6 | M30: =IF(L30<>"",L30*1.1,"") -> 170.06 | N30: =IF(F30="S",L30*0.02,0) -> 3.092 | O30: =IF(L30<>"",L30+N30,"") -> 157.692 | P30: =IF(O30<>"",O30*0.1,"") -> 15.7692 | Q30: =IF(O30<>"",O30+P30,"") -> 173.4612 | R30: s
A31: 5910 | B31: 46189 | D31: 50160 | E31: =IF(D31<>"",IFERROR(VLOOKUP(D31,PROVEEDORES!$A:$B,2,0),"!COD NO ENCONTRADO"),"") -> SUBASTAS CORUÑA S.L. | F31: =IF(D31<>"",IFERROR(VLOOKUP(D31,PROVEEDORES!$A:$C,3,0),""),"") -> S | G31: C221 | H31: =IF(G31<>"",IFERROR(VLOOKUP(G31,PRODUCTOS!$A:$B,2,0),"!COD NO ENCONTRADO"),"") -> LIRIO/ BACALADILLA/ PERLA (WHB) | I31: 20 | J31: 300 | K31: 1.46 | L31: =IF(AND(J31<>"",K31<>""),J31*K31,"") -> 438 | M31: =IF(L31<>"",L31*1.1,"") -> 481.8 | N31: =IF(F31="S",L31*0.02,0) -> 8.76 | O31: =IF(L31<>"",L31+N31,"") -> 446.76 | P31: =IF(O31<>"",O31*0.1,"") -> 44.676 | Q31: =IF(O31<>"",O31+P31,"") -> 491.436 | R31: s
A32: 5911 | B32: 46189 | C32: 31684 | D32: 50106 | E32: =IF(D32<>"",IFERROR(VLOOKUP(D32,PROVEEDORES!$A:$B,2,0),"!COD NO ENCONTRADO"),"") -> SONIA VENTAS S.L | F32: =IF(D32<>"",IFERROR(VLOOKUP(D32,PROVEEDORES!$A:$C,3,0),""),"") -> S | G32: C1300 | H32: =IF(G32<>"",IFERROR(VLOOKUP(G32,PRODUCTOS!$A:$B,2,0),"!COD NO ENCONTRADO"),"") -> MERLUZA EUROPEA PINCHO COSTA | I32: 1 | J32: 15.75 | K32: 8.9 | L32: =IF(AND(J32<>"",K32<>""),J32*K32,"") -> 140.175 | M32: =IF(L32<>"",L32*1.1,"") -> 154.1925 | N32: =IF(F32="S",L32*0.02,0) -> 2.8035 | O32: =IF(L32<>"",L32+N32,"") -> 142.9785 | P32: =IF(O32<>"",O32*0.1,"") -> 14.29785 | Q32: =IF(O32<>"",O32+P32,"") -> 157.27635 | R32: s
A33: 5911 | B33: 46189 | C33: 31684 | D33: 50106 | E33: =IF(D33<>"",IFERROR(VLOOKUP(D33,PROVEEDORES!$A:$B,2,0),"!COD NO ENCONTRADO"),"") -> SONIA VENTAS S.L | F33: =IF(D33<>"",IFERROR(VLOOKUP(D33,PROVEEDORES!$A:$C,3,0),""),"") -> S | G33: C1300 | H33: =IF(G33<>"",IFERROR(VLOOKUP(G33,PRODUCTOS!$A:$B,2,0),"!COD NO ENCONTRADO"),"") -> MERLUZA EUROPEA PINCHO COSTA | I33: 3 | J33: =14+14.5+14.25 -> 42.75 | K33: 5.2 | L33: =IF(AND(J33<>"",K33<>""),J33*K33,"") -> 222.3 | M33: =IF(L33<>"",L33*1.1,"") -> 244.53 | N33: =IF(F33="S",L33*0.02,0) -> 4.446 | O33: =IF(L33<>"",L33+N33,"") -> 226.746 | P33: =IF(O33<>"",O33*0.1,"") -> 22.6746 | Q33: =IF(O33<>"",O33+P33,"") -> 249.4206 | R33: s
A34: 5911 | B34: 46189 | C34: 31684 | D34: 50106 | E34: =IF(D34<>"",IFERROR(VLOOKUP(D34,PROVEEDORES!$A:$B,2,0),"!COD NO ENCONTRADO"),"") -> SONIA VENTAS S.L | F34: =IF(D34<>"",IFERROR(VLOOKUP(D34,PROVEEDORES!$A:$C,3,0),""),"") -> S | G34: C1300 | H34: =IF(G34<>"",IFERROR(VLOOKUP(G34,PRODUCTOS!$A:$B,2,0),"!COD NO ENCONTRADO"),"") -> MERLUZA EUROPEA PINCHO COSTA | I34: 2 | J34: =14+13.75 -> 27.75 | K34: 5.1 | L34: =IF(AND(J34<>"",K34<>""),J34*K34,"") -> 141.525 | M34: =IF(L34<>"",L34*1.1,"") -> 155.6775 | N34: =IF(F34="S",L34*0.02,0) -> 2.8305 | O34: =IF(L34<>"",L34+N34,"") -> 144.3555 | P34: =IF(O34<>"",O34*0.1,"") -> 14.43555 | Q34: =IF(O34<>"",O34+P34,"") -> 158.79105 | R34: s
A35: 5911 | B35: 46189 | C35: 31684 | D35: 50106 | E35: =IF(D35<>"",IFERROR(VLOOKUP(D35,PROVEEDORES!$A:$B,2,0),"!COD NO ENCONTRADO"),"") -> SONIA VENTAS S.L | F35: =IF(D35<>"",IFERROR(VLOOKUP(D35,PROVEEDORES!$A:$C,3,0),""),"") -> S | G35: C1300 | H35: =IF(G35<>"",IFERROR(VLOOKUP(G35,PRODUCTOS!$A:$B,2,0),"!COD NO ENCONTRADO"),"") -> MERLUZA EUROPEA PINCHO COSTA | I35: 3 | J35: =15.25+14.5+14.75 -> 44.5 | K35: 7.1 | L35: =IF(AND(J35<>"",K35<>""),J35*K35,"") -> 315.95 | M35: =IF(L35<>"",L35*1.1,"") -> 347.545 | N35: =IF(F35="S",L35*0.02,0) -> 6.319 | O35: =IF(L35<>"",L35+N35,"") -> 322.269 | P35: =IF(O35<>"",O35*0.1,"") -> 32.2269 | Q35: =IF(O35<>"",O35+P35,"") -> 354.4959 | R35: s
A36: 5911 | B36: 46189 | C36: 31684 | D36: 50106 | E36: =IF(D36<>"",IFERROR(VLOOKUP(D36,PROVEEDORES!$A:$B,2,0),"!COD NO ENCONTRADO"),"") -> SONIA VENTAS S.L | F36: =IF(D36<>"",IFERROR(VLOOKUP(D36,PROVEEDORES!$A:$C,3,0),""),"") -> S | G36: C1300 | H36: =IF(G36<>"",IFERROR(VLOOKUP(G36,PRODUCTOS!$A:$B,2,0),"!COD NO ENCONTRADO"),"") -> MERLUZA EUROPEA PINCHO COSTA | I36: 4 | J36: =12.5+12+12+11.5 -> 48 | K36: 3 | L36: =IF(AND(J36<>"",K36<>""),J36*K36,"") -> 144 | M36: =IF(L36<>"",L36*1.1,"") -> 158.4 | N36: =IF(F36="S",L36*0.02,0) -> 2.88 | O36: =IF(L36<>"",L36+N36,"") -> 146.88 | P36: =IF(O36<>"",O36*0.1,"") -> 14.688 | Q36: =IF(O36<>"",O36+P36,"") -> 161.568 | R36: s
A37: 5911 | B37: 46189 | C37: 31684 | D37: 50106 | E37: =IF(D37<>"",IFERROR(VLOOKUP(D37,PROVEEDORES!$A:$B,2,0),"!COD NO ENCONTRADO"),"") -> SONIA VENTAS S.L | F37: =IF(D37<>"",IFERROR(VLOOKUP(D37,PROVEEDORES!$A:$C,3,0),""),"") -> S | G37: C1300 | H37: =IF(G37<>"",IFERROR(VLOOKUP(G37,PRODUCTOS!$A:$B,2,0),"!COD NO ENCONTRADO"),"") -> MERLUZA EUROPEA PINCHO COSTA | I37: 6 | J37: =13.75+13.5+13.75+13.75+13.5+15 -> 83.25 | K37: 5.2 | L37: =IF(AND(J37<>"",K37<>""),J37*K37,"") -> 432.9 | M37: =IF(L37<>"",L37*1.1,"") -> 476.19 | N37: =IF(F37="S",L37*0.02,0) -> 8.658 | O37: =IF(L37<>"",L37+N37,"") -> 441.558 | P37: =IF(O37<>"",O37*0.1,"") -> 44.1558 | Q37: =IF(O37<>"",O37+P37,"") -> 485.7138 | R37: s
A38: 5911 | B38: 46189 | C38: 31684 | D38: 50106 | E38: =IF(D38<>"",IFERROR(VLOOKUP(D38,PROVEEDORES!$A:$B,2,0),"!COD NO ENCONTRADO"),"") -> SONIA VENTAS S.L | F38: =IF(D38<>"",IFERROR(VLOOKUP(D38,PROVEEDORES!$A:$C,3,0),""),"") -> S | G38: C1300 | H38: =IF(G38<>"",IFERROR(VLOOKUP(G38,PRODUCTOS!$A:$B,2,0),"!COD NO ENCONTRADO"),"") -> MERLUZA EUROPEA PINCHO COSTA | I38: 4 | J38: =14.25+14+13.5+14 -> 55.75 | K38: 5.3 | L38: =IF(AND(J38<>"",K38<>""),J38*K38,"") -> 295.475 | M38: =IF(L38<>"",L38*1.1,"") -> 325.0225 | N38: =IF(F38="S",L38*0.02,0) -> 5.9095 | O38: =IF(L38<>"",L38+N38,"") -> 301.3845 | P38: =IF(O38<>"",O38*0.1,"") -> 30.13845 | Q38: =IF(O38<>"",O38+P38,"") -> 331.52295 | R38: S
A39: 5911 | B39: 46189 | C39: 31684 | D39: 50106 | E39: =IF(D39<>"",IFERROR(VLOOKUP(D39,PROVEEDORES!$A:$B,2,0),"!COD NO ENCONTRADO"),"") -> SONIA VENTAS S.L | F39: =IF(D39<>"",IFERROR(VLOOKUP(D39,PROVEEDORES!$A:$C,3,0),""),"") -> S | G39: C1300 | H39: =IF(G39<>"",IFERROR(VLOOKUP(G39,PRODUCTOS!$A:$B,2,0),"!COD NO ENCONTRADO"),"") -> MERLUZA EUROPEA PINCHO COSTA | I39: 2 | J39: =14.25+13.25 -> 27.5 | K39: 5.2 | L39: =IF(AND(J39<>"",K39<>""),J39*K39,"") -> 143 | M39: =IF(L39<>"",L39*1.1,"") -> 157.3 | N39: =IF(F39="S",L39*0.02,0) -> 2.86 | O39: =IF(L39<>"",L39+N39,"") -> 145.86 | P39: =IF(O39<>"",O39*0.1,"") -> 14.586 | Q39: =IF(O39<>"",O39+P39,"") -> 160.446 | R39: S
A40: 5911 | B40: 46189 | C40: 31684 | D40: 50106 | E40: =IF(D40<>"",IFERROR(VLOOKUP(D40,PROVEEDORES!$A:$B,2,0),"!COD NO ENCONTRADO"),"") -> SONIA VENTAS S.L | F40: =IF(D40<>"",IFERROR(VLOOKUP(D40,PROVEEDORES!$A:$C,3,0),""),"") -> S | G40: C1300 | H40: =IF(G40<>"",IFERROR(VLOOKUP(G40,PRODUCTOS!$A:$B,2,0),"!COD NO ENCONTRADO"),"") -> MERLUZA EUROPEA PINCHO COSTA | I40: 3 | J40: =14+14.25+14.25 -> 42.5 | K40: 5.5 | L40: =IF(AND(J40<>"",K40<>""),J40*K40,"") -> 233.75 | M40: =IF(L40<>"",L40*1.1,"") -> 257.125 | N40: =IF(F40="S",L40*0.02,0) -> 4.675 | O40: =IF(L40<>"",L40+N40,"") -> 238.425 | P40: =IF(O40<>"",O40*0.1,"") -> 23.8425 | Q40: =IF(O40<>"",O40+P40,"") -> 262.2675 | R40: S
A41: 5911 | B41: 46189 | C41: 31684 | D41: 50106 | E41: =IF(D41<>"",IFERROR(VLOOKUP(D41,PROVEEDORES!$A:$B,2,0),"!COD NO ENCONTRADO"),"") -> SONIA VENTAS S.L | F41: =IF(D41<>"",IFERROR(VLOOKUP(D41,PROVEEDORES!$A:$C,3,0),""),"") -> S | G41: C255 | H41: =IF(G41<>"",IFERROR(VLOOKUP(G41,PRODUCTOS!$A:$B,2,0),"!COD NO ENCONTRADO"),"") -> CABRAS/ GALLINETA (BRF) | I41: 1 | J41: 9.25 | K41: 5 | L41: =IF(AND(J41<>"",K41<>""),J41*K41,"") -> 46.25 | M41: =IF(L41<>"",L41*1.1,"") -> 50.875 | N41: =IF(F41="S",L41*0.02,0) -> 0.925 | O41: =IF(L41<>"",L41+N41,"") -> 47.175 | P41: =IF(O41<>"",O41*0.1,"") -> 4.7175 | Q41: =IF(O41<>"",O41+P41,"") -> 51.8925 | R41: S
A42: 5911 | B42: 46189 | C42: 31684 | D42: 50106 | E42: =IF(D42<>"",IFERROR(VLOOKUP(D42,PROVEEDORES!$A:$B,2,0),"!COD NO ENCONTRADO"),"") -> SONIA VENTAS S.L | F42: =IF(D42<>"",IFERROR(VLOOKUP(D42,PROVEEDORES!$A:$C,3,0),""),"") -> S | G42: C255 | H42: =IF(G42<>"",IFERROR(VLOOKUP(G42,PRODUCTOS!$A:$B,2,0),"!COD NO ENCONTRADO"),"") -> CABRAS/ GALLINETA (BRF) | I42: 1 | J42: 6.4 | K42: 10 | L42: =IF(AND(J42<>"",K42<>""),J42*K42,"") -> 64 | M42: =IF(L42<>"",L42*1.1,"") -> 70.4 | N42: =IF(F42="S",L42*0.02,0) -> 1.28 | O42: =IF(L42<>"",L42+N42,"") -> 65.28 | P42: =IF(O42<>"",O42*0.1,"") -> 6.528 | Q42: =IF(O42<>"",O42+P42,"") -> 71.808 | R42: S
A43: 5912 | B43: 46189 | D43: 50001 | E43: =IF(D43<>"",IFERROR(VLOOKUP(D43,PROVEEDORES!$A:$B,2,0),"!COD NO ENCONTRADO"),"") -> COPESA | F43: =IF(D43<>"",IFERROR(VLOOKUP(D43,PROVEEDORES!$A:$C,3,0),""),"") -> S | G43: C5260 | H43: =IF(G43<>"",IFERROR(VLOOKUP(G43,PRODUCTOS!$A:$B,2,0),"!COD NO ENCONTRADO"),"") -> RAPE BLANCO ARRASTRE (MON) | I43: 2 | J43: =5+4.5 -> 9.5 | K43: 6.5 | L43: =IF(AND(J43<>"",K43<>""),J43*K43,"") -> 61.75 | M43: =IF(L43<>"",L43*1.1,"") -> 67.925 | N43: =IF(F43="S",L43*0.02,0) -> 1.235 | O43: =IF(L43<>"",L43+N43,"") -> 62.985 | P43: =IF(O43<>"",O43*0.1,"") -> 6.2985 | Q43: =IF(O43<>"",O43+P43,"") -> 69.2835
A44: 5912 | B44: 46189 | D44: 50001 | E44: =IF(D44<>"",IFERROR(VLOOKUP(D44,PROVEEDORES!$A:$B,2,0),"!COD NO ENCONTRADO"),"") -> COPESA | F44: =IF(D44<>"",IFERROR(VLOOKUP(D44,PROVEEDORES!$A:$C,3,0),""),"") -> S | G44: C5260 | H44: =IF(G44<>"",IFERROR(VLOOKUP(G44,PRODUCTOS!$A:$B,2,0),"!COD NO ENCONTRADO"),"") -> RAPE BLANCO ARRASTRE (MON) | I44: 1 | J44: 13.5 | K44: 6 | L44: =IF(AND(J44<>"",K44<>""),J44*K44,"") -> 81 | M44: =IF(L44<>"",L44*1.1,"") -> 89.1 | N44: =IF(F44="S",L44*0.02,0) -> 1.62 | O44: =IF(L44<>"",L44+N44,"") -> 82.62 | P44: =IF(O44<>"",O44*0.1,"") -> 8.262 | Q44: =IF(O44<>"",O44+P44,"") -> 90.882
A45: 5912 | B45: 46189 | D45: 50001 | E45: =IF(D45<>"",IFERROR(VLOOKUP(D45,PROVEEDORES!$A:$B,2,0),"!COD NO ENCONTRADO"),"") -> COPESA | F45: =IF(D45<>"",IFERROR(VLOOKUP(D45,PROVEEDORES!$A:$C,3,0),""),"") -> S | G45: C5240 | H45: =IF(G45<>"",IFERROR(VLOOKUP(G45,PRODUCTOS!$A:$B,2,0),"!COD NO ENCONTRADO"),"") -> RAPE NEGRO (ANK) | I45: 1 | J45: 6.3 | K45: 9.6 | L45: =IF(AND(J45<>"",K45<>""),J45*K45,"") -> 60.48 | M45: =IF(L45<>"",L45*1.1,"") -> 66.528 | N45: =IF(F45="S",L45*0.02,0) -> 1.2096 | O45: =IF(L45<>"",L45+N45,"") -> 61.6896 | P45: =IF(O45<>"",O45*0.1,"") -> 6.16896 | Q45: =IF(O45<>"",O45+P45,"") -> 67.85856
